Workbook

Sheet README
A1: Carcinome Billing Tracker
A2: How this workbook works
A4: Sheet | B4: Purpose
A5: Patient Bills | B5: Same layout as before - ID Number, Patient Name, Patient Number, Notes, then one block per infusion round. Each round has: Fixed Charges (flat fee, manual), Consumable (auto-pulled MRP), Nursing (auto-pulled billed amount), Carcinome (auto-calculated profit for that round), Total Charges (Fixed+Consumable+Nursing), Total Received, Balance, and Payment Status. Round 1 is billed and closed before Round 2, etc.
A6: Nursing Charges | B6: Log nursing per Patient ID + Round. Supports a Fixed Package rate or an Hourly rate (shifts x rate) for the "Amount Billed to Patient" column. Separately enter "Amount Paid to Nurse" - the actual amount the nurse is paid, which is usually less than what the patient is billed. The difference is your nursing margin. Feeds Patient Bills and Nurse Payments.
A7: Nursing Rate Card | B7: Your standard nursing rates for reference (24-hr package, 12-hr package, per-visit, per-hour). Edit the numbers to your real rates - these are placeholder assumptions.
A8: Consumables Master | B8: Your price list: MRP (billed to patient) vs Landing Price (your cost) per item, with margin calculated.
A9: Consumable Usage | B9: Log consumables per Patient ID + Round - just ONE row per round. Enter the total MRP you're charging the patient and the total Landing (supplier) cost for that round; no need to itemize each medicine. Margin calculates automatically. Feeds Patient Bills.
A10: Nurse Payments | B10: What each nurse is owed for a billing period, what's been paid, and what's pending.
A11: Overall Summary | B11: Dashboard totals across everything.
A13: Color legend
A14: Blue text on pale yellow | B14: Cells you type into.
A15: Green text | B15: Pulled automatically from another sheet - don't overwrite.
A16: Black text | B16: Calculated by formula - don't overwrite.
A18: Key linking fields | B18: 'ID Number' (Patient ID, e.g. CC2026001) connects every sheet. 'Round' number (1, 2, 3...) connects a charge to the right round on Patient Bills. Keep the ID Number spelling and Round number consistent across sheets or the totals will show 0.
A19: Fixed Charges | B19: There's a dedicated "Fixed Charges" column inside each round block on Patient Bills - use it for any flat/package fee for that round (procedure fee, etc.) on top of nursing + consumables. This amount is treated as pure profit (Carcinome). Leave blank if not applicable.
A20: Carcinome (₹) column | B20: Your actual profit for that round: Fixed Charges (100% profit) + (Nursing billed - Nursing paid to nurse) + (Consumable MRP - Consumable landing cost). Automatically calculated - don't overwrite. Rolls up into "Total Carcinome Profit" on Overall Summary.
A21: Need more than 16 rounds for a patient? | B21: Copy the last round block's 10 columns and paste them after Round 16, following the same header pattern.

Sheet Patient Bills
A1: Patient Bills - Round by Round
A2: Round 1 is billed & closed before Round 2 opens, etc. Total Charges = Nursing + Consumables (auto) + Fixed Charges (you enter).
A4: ID Number | B4: Patient Name | C4: Patient Number | E4: Notes | F4: Round 1 | P4: Round 2 | Z4: Round 3 | AJ4: Round 4 | AT4: Round 5 | BD4: Round 6 | BN4: Round 7 | BX4: Round 8 | CH4: Round 9 | CR4: Round 10 | DB4: Round 11 | DL4: Round 12 | DV4: Round 13 | EF4: Round 14 | EP4: Round 15 | EZ4: Round 16 | FJ4: Round 17
F5: Service | G5: Infusion Date | H5: Fixed Charges (₹) | I5: Consumable (₹) | J5: Nursing (₹) | K5: Carcinome (₹) | L5: Total Charges (₹) | N5: Balance (₹) | O5: Payment Status | P5: Service | Q5: Infusion Date | R5: Fixed Charges (₹) | S5: Consumable (₹) | T5: Nursing (₹) | U5: Carcinome (₹) | V5: Total Charges (₹) | W5: Total Received (₹) | X5: Balance (₹) | Y5: Payment Status | Z5: Service | AA5: Infusion Date | AB5: Fixed Charges (₹) | AC5: Consumable (₹) | AD5: Nursing (₹) | AE5: Carcinome (₹) | AF5: Total Charges (₹) | AG5: Total Received (₹) | AH5: Balance (₹) | AI5: Payment Status | AJ5: Service | AK5: Infusion Date | AL5: Fixed Charges (₹) | AM5: Consumable (₹) | AN5: Nursing (₹) | AO5: Carcinome (₹) | AP5: Total Charges (₹) | AQ5: Total Received (₹) | AR5: Balance (₹) | AS5: Payment Status | AT5: Service | AU5: Infusion Date | AV5: Fixed Charges (₹) | AW5: Consumable (₹) | AX5: Nursing (₹) | AY5: Carcinome (₹) | AZ5: Total Charges (₹) | BA5: Total Received (₹) | BB5: Balance (₹) | BC5: Payment Status | BD5: Service | BE5: Infusion Date | BF5: Fixed Charges (₹) | BG5: Consumable (₹) | BH5: Nursing (₹) | BI5: Carcinome (₹) | BJ5: Total Charges (₹) | BK5: Total Received (₹) | BL5: Balance (₹) | BM5: Payment Status | BN5: Service | BO5: Infusion Date | BP5: Fixed Charges (₹) | BQ5: Consumable (₹) | BR5: Nursing (₹) | BS5: Carcinome (₹) | BT5: Total Charges (₹) | BU5: Total Received (₹) | BV5: Balance (₹) | BW5: Payment Status | BX5: Service | BY5: Infusion Date | BZ5: Fixed Charges (₹) | CA5: Consumable (₹) | CB5: Nursing (₹) | CC5: Carcinome (₹) | CD5: Total Charges (₹) | CE5: Total Received (₹) | CF5: Balance (₹) | CG5: Payment Status | CH5: Service | CI5: Infusion Date | CJ5: Fixed Charges (₹) | CK5: Consumable (₹) | CL5: Nursing (₹) | CM5: Carcinome (₹) | CN5: Total Charges (₹) | CO5: Total Received (₹) | CP5: Balance (₹) | CQ5: Payment Status | CR5: Service | CS5: Infusion Date | CT5: Fixed Charges (₹) | CU5: Consumable (₹) | CV5: Nursing (₹) | CW5: Carcinome (₹) | CX5: Total Charges (₹) | CY5: Total Received (₹) | CZ5: Balance (₹) | DA5: Payment Status | DB5: Service | DC5: Infusion Date | DD5: Fixed Charges (₹) | DE5: Consumable (₹) | DF5: Nursing (₹) | DG5: Carcinome (₹) | DH5: Total Charges (₹) | DI5: Total Received (₹) | DJ5: Balance (₹) | DK5: Payment Status | DL5: Service | DM5: Infusion Date | DN5: Fixed Charges (₹) | DO5: Consumable (₹) | DP5: Nursing (₹) | DQ5: Carcinome (₹) | DR5: Total Charges (₹) | DS5: Total Received (₹) | DT5: Balance (₹) | DU5: Payment Status | DV5: Service | DW5: Infusion Date | DX5: Fixed Charges (₹) | DY5: Consumable (₹) | DZ5: Nursing (₹) | EA5: Carcinome (₹) | EB5: Total Charges (₹) | EC5: Total Received (₹) | ED5: Balance (₹) | EE5: Payment Status | EF5: Service | EG5: Infusion Date | EH5: Fixed Charges (₹) | EI5: Consumable (₹) | EJ5: Nursing (₹) | EK5: Carcinome (₹) | EL5: Total Charges (₹) | EM5: Total Received (₹) | EN5: Balance (₹) | EO5: Payment Status | EP5: Service | EQ5: Infusion Date | ER5: Fixed Charges (₹) | ES5: Consumable (₹) | ET5: Nursing (₹) | EU5: Carcinome (₹) | EV5: Total Charges (₹) | EW5: Total Received (₹) | EX5: Balance (₹) | EY5: Payment Status | EZ5: Service | FA5: Infusion Date | FB5: Fixed Charges (₹) | FC5: Consumable (₹) | FD5: Nursing (₹) | FE5: Carcinome (₹) | FF5: Total Charges (₹) | FG5: Total Received (₹) | FH5: Balance (₹) | FI5: Payment Status | FJ5: Service | FK5: Infusion Date | FL5: Fixed Charges (₹) | FM5: Consumable (₹) | FN5: Nursing (₹) | FO5: Carcinome (₹) | FP5: Total Charges (₹) | FQ5: Total Received (₹) | FR5: Balance (₹) | FS5: Payment Status
A6: CC2026001 | B6: Pappu | C6: VIJAY | D6: 99340 38365 | E6: so the treatment is over all bills paid | G6: 2026-07-21 | H6: 0 | I6: =IF($A6="","",SUMIFS('Consumable Usage'!$E:$E,'Consumable Usage'!$A:$A,$A6,'Consumable Usage'!$D:$D,1)) -> 0 | J6: =IF($A6="","",SUMIFS('Nursing Charges'!$I:$I,'Nursing Charges'!$A:$A,$A6,'Nursing Charges'!$C:$C,1)) -> 5400 | K6: =IF($A6="","",H6+(J6-SUMIFS('Nursing Charges'!$J:$J,'Nursing Charges'!$A:$A,$A6,'Nursing Charges'!$C:$C,1))+(I6-SUMIFS('Consumable Usage'!$F:$F,'Consumable Usage'!$A:$A,$A6,'Consumable Usage'!$D:$D,1))) -> 5400 | L6: =IF($A6="","",H6+J6+I6) -> 5400 | N6: =IF(L6="","",L6-M6) -> 5400 | O6: =IF(OR($A6="",F6=""),"",IF(L6=0,"No Charges",IF(N6<=0,"Paid",IF(M6>0,"Partial","Pending")))) | P6: Chemo Infusion | Q6: 2026-07-29 | R6: 0 | S6: =IF($A6="","",SUMIFS('Consumable Usage'!$E:$E,'Consumable Usage'!$A:$A,$A6,'Consumable Usage'!$D:$D,2)) -> 0 | T6: =IF($A6="","",SUMIFS('Nursing Charges'!$I:$I,'Nursing Charges'!$A:$A,$A6,'Nursing Charges'!$C:$C,2)) -> 0 | U6: =IF($A6="","",R6+(T6-SUMIFS('Nursing Charges'!$J:$J,'Nursing Charges'!$A:$A,$A6,'Nursing Charges'!$C:$C,2))+(S6-SUMIFS('Consumable Usage'!$F:$F,'Consumable Usage'!$A:$A,$A6,'Consumable Usage'!$D:$D,2))) -> 0 | V6: =IF($A6="","",R6+T6+S6) -> 0 | X6: =IF(V6="","",V6-W6) -> 0 | Y6: =IF(OR($A6="",P6=""),"",IF(V6=0,"No Charges",IF(X6<=0,"Paid",IF(W6>0,"Partial","Pending")))) -> No Charges | AC6: =IF($A6="","",SUMIFS('Consumable Usage'!$E:$E,'Consumable Usage'!$A:$A,$A6,'Consumable Usage'!$D:$D,3)) -> 0 | AD6: =IF($A6="","",SUMIFS('Nursing Charges'!$I:$I,'Nursing Charges'!$A:$A,$A6,'Nursing Charges'!$C:$C,3)) -> 0 | AE6: =IF($A6="","",AB6+(AD6-SUMIFS('Nursing Charges'!$J:$J,'Nursing Charges'!$A:$A,$A6,'Nursing Charges'!$C:$C,3))+(AC6-SUMIFS('Consumable Usage'!$F:$F,'Consumable Usage'!$A:$A,$A6,'Consumable Usage'!$D:$D,3))) -> 0 | AF6: =IF($A6="","",AB6+AD6+AC6) -> 0 | AH6: =IF(AF6="","",AF6-AG6) -> 0 | AI6: =IF(OR($A6="",Z6=""),"",IF(AF6=0,"No Charges",IF(AH6<=0,"Paid",IF(AG6>0,"Partial","Pending")))) | AM6: =IF($A6="","",SUMIFS('Consumable Usage'!$E:$E,'Consumable Usage'!$A:$A,$A6,'Consumable Usage'!$D:$D,4)) -> 0 | AN6: =IF($A6="","",SUMIFS('Nursing Charges'!$I:$I,'Nursing Charges'!$A:$A,$A6,'Nursing Charges'!$C:$C,4)) -> 0 | AO6: =IF($A6="","",AL6+(AN6-SUMIFS('Nursing Charges'!$J:$J,'Nursing Charges'!$A:$A,$A6,'Nursing Charges'!$C:$C,4))+(AM6-SUMIFS('Consumable Usage'!$F:$F,'Consumable Usage'!$A:$A,$A6,'Consumable Usage'!$D:$D,4))) -> 0 | AP6: =IF($A6="","",AL6+AN6+AM6) -> 0 | AR6: =IF(AP6="","",AP6-AQ6) -> 0 | AS6: =IF(OR($A6="",AJ6=""),"",IF(AP6=0,"No Charges",IF(AR6<=0,"Paid",IF(AQ6>0,"Partial","Pending")))) | AW6: =IF($A6="","",SUMIFS('Consumable Usage'!$E:$E,'Consumable Usage'!$A:$A,$A6,'Consumable Usage'!$D:$D,5)) -> 0 | AX6: =IF($A6="","",SUMIFS('Nursing Charges'!$I:$I,'Nursing Charges'!$A:$A,$A6,'Nursing Charges'!$C:$C,5)) -> 0 | AY6: =IF($A6="","",AV6+(AX6-SUMIFS('Nursing Charges'!$J:$J,'Nursing Charges'!$A:$A,$A6,'Nursing Charges'!$C:$C,5))+(AW6-SUMIFS('Consumable Usage'!$F:$F,'Consumable Usage'!$A:$A,$A6,'Consumable Usage'!$D:$D,5))) -> 0 | AZ6: =IF($A6="","",AV6+AX6+AW6) -> 0 | BB6: =IF(AZ6="","",AZ6-BA6) -> 0 | BC6: =IF(OR($A6="",AT6=""),"",IF(AZ6=0,"No Charges",IF(BB6<=0,"Paid",IF(BA6>0,"Partial","Pending")))) | BG6: =IF($A6="","",SUMIFS('Consumable Usage'!$E:$E,'Consumable Usage'!$A:$A,$A6,'Consumable Usage'!$D:$D,6)) -> 850 | BH6: =IF($A6="","",SUMIFS('Nursing Charges'!$I:$I,'Nursing Charges'!$A:$A,$A6,'Nursing Charges'!$C:$C,6)) -> 0 | BI6: =IF($A6="","",BF6+(BH6-SUMIFS('Nursing Charges'!$J:$J,'Nursing Charges'!$A:$A,$A6,'Nursing Charges'!$C:$C,6))+(BG6-SUMIFS('Consumable Usage'!$F:$F,'Consumable Usage'!$A:$A,$A6,'Consumable Usage'!$D:$D,6))) -> 330 | BJ6: =IF($A6="","",BF6+BH6+BG6) -> 850 | BL6: =IF(BJ6="","",BJ6-BK6) -> 850 | BM6: =IF(OR($A6="",BD6=""),"",IF(BJ6=0,"No Charges",IF(BL6<=0,"Paid",IF(BK6>0,"Partial","Pending")))) | BQ6: =IF($A6="","",SUMIFS('Consumable Usage'!$E:$E,'Consumable Usage'!$A:$A,$A6,'Consumable Usage'!$D:$D,7)) -> 0 | BR6: =IF($A6="","",SUMIFS('Nursing Charges'!$I:$I,'Nursing Charges'!$A:$A,$A6,'Nursing Charges'!$C:$C,7)) -> 0 | BS6: =IF($A6="","",BP6+(BR6-SUMIFS('Nursing Charges'!$J:$J,'Nursing Charges'!$A:$A,$A6,'Nursing Charges'!$C:$C,7))+(BQ6-SUMIFS('Consumable Usage'!$F:$F,'Consumable Usage'!$A:$A,$A6,'Consumable Usage'!$D:$D,7))) -> 0 | BT6: =IF($A6="","",BP6+BR6+BQ6) -> 0 | BV6: =IF(BT6="","",BT6-BU6) -> 0 | BW6: =IF(OR($A6="",BN6=""),"",IF(BT6=0,"No Charges",IF(BV6<=0,"Paid",IF(BU6>0,"Partial","Pending")))) | CA6: =IF($A6="","",SUMIFS('Consumable Usage'!$E:$E,'Consumable Usage'!$A:$A,$A6,'Consumable Usage'!$D:$D,8)) -> 0 | CB6: =IF($A6="","",SUMIFS('Nursing Charges'!$I:$I,'Nursing Charges'!$A:$A,$A6,'Nursing Charges'!$C:$C,8)) -> 0 | CC6: =IF($A6="","",BZ6+(CB6-SUMIFS('Nursing Charges'!$J:$J,'Nursing Charges'!$A:$A,$A6,'Nursing Charges'!$C:$C,8))+(CA6-SUMIFS('Consumable Usage'!$F:$F,'Consumable Usage'!$A:$A,$A6,'Consumable Usage'!$D:$D,8))) -> 0 | CD6: =IF($A6="","",BZ6+CB6+CA6) -> 0 | CF6: =IF(CD6="","",CD6-CE6) -> 0 | CG6: =IF(OR($A6="",BX6=""),"",IF(CD6=0,"No Charges",IF(CF6<=0,"Paid",IF(CE6>0,"Partial","Pending")))) | CK6: =IF($A6="","",SUMIFS('Consumable Usage'!$E:$E,'Consumable Usage'!$A:$A,$A6,'Consumable Usage'!$D:$D,9)) -> 0 | CL6: =IF($A6="","",SUMIFS('Nursing Charges'!$I:$I,'Nursing Charges'!$A:$A,$A6,'Nursing Charges'!$C:$C,9)) -> 0 | CM6: =IF($A6="","",CJ6+(CL6-SUMIFS('Nursing Charges'!$J:$J,'Nursing Charges'!$A:$A,$A6,'Nursing Charges'!$C:$C,9))+(CK6-SUMIFS('Consumable Usage'!$F:$F,'Consumable Usage'!$A:$A,$A6,'Consumable Usage'!$D:$D,9))) -> 0 | CN6: =IF($A6="","",CJ6+CL6+CK6) -> 0 | CP6: =IF(CN6="","",CN6-CO6) -> 0 | CQ6: =IF(OR($A6="",CH6=""),"",IF(CN6=0,"No Charges",IF(CP6<=0,"Paid",IF(CO6>0,"Partial","Pending")))) | CU6: =IF($A6="","",SUMIFS('Consumable Usage'!$E:$E,'Consumable Usage'!$A:$A,$A6,'Consumable Usage'!$D:$D,10)) -> 0 | CV6: =IF($A6="","",SUMIFS('Nursing Charges'!$I:$I,'Nursing Charges'!$A:$A,$A6,'Nursing Charges'!$C:$C,10)) -> 0 | CW6: =IF($A6="","",CT6+(CV6-SUMIFS('Nursing Charges'!$J:$J,'Nursing Charges'!$A:$A,$A6,'Nursing Charges'!$C:$C,10))+(CU6-SUMIFS('Consumable Usage'!$F:$F,'Consumable Usage'!$A:$A,$A6,'Consumable Usage'!$D:$D,10))) -> 0 | CX6: =IF($A6="","",CT6+CV6+CU6) -> 0 | CZ6: =IF(CX6="","",CX6-CY6) -> 0 | DA6: =IF(OR($A6="",CR6=""),"",IF(CX6=0,"No Charges",IF(CZ6<=0,"Paid",IF(CY6>0,"Partial","Pending")))) | DE6: =IF($A6="","",SUMIFS('Consumable Usage'!$E:$E,'Consumable Usage'!$A:$A,$A6,'Consumable Usage'!$D:$D,11)) -> 0 | DF6: =IF($A6="","",SUMIFS('Nursing Charges'!$I:$I,'Nursing Charges'!$A:$A,$A6,'Nursing Charges'!$C:$C,11)) -> 0 | DG6: =IF($A6="","",DD6+(DF6-SUMIFS('Nursing Charges'!$J:$J,'Nursing Charges'!$A:$A,$A6,'Nursing Charges'!$C:$C,11))+(DE6-SUMIFS('Consumable Usage'!$F:$F,'Consumable Usage'!$A:$A,$A6,'Consumable Usage'!$D:$D,11))) -> 0 | DH6: =IF($A6="","",DD6+DF6+DE6) -> 0 | DJ6: =IF(DH6="","",DH6-DI6) -> 0 | DK6: =IF(OR($A6="",DB6=""),"",IF(DH6=0,"No Charges",IF(DJ6<=0,"Paid",IF(DI6>0,"Partial","Pending")))) | DO6: =IF($A6="","",SUMIFS('Consumable Usage'!$E:$E,'Consumable Usage'!$A:$A,$A6,'Consumable Usage'!$D:$D,12)) -> 0 | DP6: =IF($A6="","",SUMIFS('Nursing Charges'!$I:$I,'Nursing Charges'!$A:$A,$A6,'Nursing Charges'!$C:$C,12)) -> 0 | DQ6: =IF($A6="","",DN6+(DP6-SUMIFS('Nursing Charges'!$J:$J,'Nursing Charges'!$A:$A,$A6,'Nursing Charges'!$C:$C,12))+(DO6-SUMIFS('Consumable Usage'!$F:$F,'Consumable Usage'!$A:$A,$A6,'Consumable Usage'!$D:$D,12))) -> 0 | DR6: =IF($A6="","",DN6+DP6+DO6) -> 0 | DT6: =IF(DR6="","",DR6-DS6) -> 0 | DU6: =IF(OR($A6="",DL6=""),"",IF(DR6=0,"No Charges",IF(DT6<=0,"Paid",IF(DS6>0,"Partial","Pending")))) | DY6: =IF($A6="","",SUMIFS('Consumable Usage'!$E:$E,'Consumable Usage'!$A:$A,$A6,'Consumable Usage'!$D:$D,13)) -> 0 | DZ6: =IF($A6="","",SUMIFS('Nursing Charges'!$I:$I,'Nursing Charges'!$A:$A,$A6,'Nursing Charges'!$C:$C,13)) -> 0 | EA6: =IF($A6="","",DX6+(DZ6-SUMIFS('Nursing Charges'!$J:$J,'Nursing Charges'!$A:$A,$A6,'Nursing Charges'!$C:$C,13))+(DY6-SUMIFS('Consumable Usage'!$F:$F,'Consumable Usage'!$A:$A,$A6,'Consumable Usage'!$D:$D,13))) -> 0 | EB6: =IF($A6="","",DX6+DZ6+DY6) -> 0 | ED6: =IF(EB6="","",EB6-EC6) -> 0 | EE6: =IF(OR($A6="",DV6=""),"",IF(EB6=0,"No Charges",IF(ED6<=0,"Paid",IF(EC6>0,"Partial","Pending")))) | EI6: =IF($A6="","",SUMIFS('Consumable Usage'!$E:$E,'Consumable Usage'!$A:$A,$A6,'Consumable Usage'!$D:$D,14)) -> 0 | EJ6: =IF($A6="","",SUMIFS('Nursing Charges'!$I:$I,'Nursing Charges'!$A:$A,$A6,'Nursing Charges'!$C:$C,14)) -> 0 | EK6: =IF($A6="","",EH6+(EJ6-SUMIFS('Nursing Charges'!$J:$J,'Nursing Charges'!$A:$A,$A6,'Nursing Charges'!$C:$C,14))+(EI6-SUMIFS('Consumable Usage'!$F:$F,'Consumable Usage'!$A:$A,$A6,'Consumable Usage'!$D:$D,14))) -> 0 | EL6: =IF($A6="","",EH6+EJ6+EI6) -> 0 | EN6: =IF(EL6="","",EL6-EM6) -> 0 | EO6: =IF(OR($A6="",EF6=""),"",IF(EL6=0,"No Charges",IF(EN6<=0,"Paid",IF(EM6>0,"Partial","Pending")))) | ES6: =IF($A6="","",SUMIFS('Consumable Usage'!$E:$E,'Consumable Usage'!$A:$A,$A6,'Consumable Usage'!$D:$D,15)) -> 0 | ET6: =IF($A6="","",SUMIFS('Nursing Charges'!$I:$I,'Nursing Charges'!$A:$A,$A6,'Nursing Charges'!$C:$C,15)) -> 0 | EU6: =IF($A6="","",ER6+(ET6-SUMIFS('Nursing Charges'!$J:$J,'Nursing Charges'!$A:$A,$A6,'Nursing Charges'!$C:$C,15))+(ES6-SUMIFS('Consumable Usage'!$F:$F,'Consumable Usage'!$A:$A,$A6,'Consumable Usage'!$D:$D,15))) -> 0 | EV6: =IF($A6="","",ER6+ET6+ES6) -> 0 | EX6: =IF(EV6="","",EV6-EW6) -> 0 | EY6: =IF(OR($A6="",EP6=""),"",IF(EV6=0,"No Charges",IF(EX6<=0,"Paid",IF(EW6>0,"Partial","Pending")))) | FC6: =IF($A6="","",SUMIFS('Consumable Usage'!$E:$E,'Consumable Usage'!$A:$A,$A6,'Consumable Usage'!$D:$D,16)) -> 0 | FD6: =IF($A6="","",SUMIFS('Nursing Charges'!$I:$I,'Nursing Charges'!$A:$A,$A6,'Nursing Charges'!$C:$C,16)) -> 0 | FE6: =IF($A6="","",FB6+(FD6-SUMIFS('Nursing Charges'!$J:$J,'Nursing Charges'!$A:$A,$A6,'Nursing Charges'!$C:$C,16))+(FC6-SUMIFS('Consumable Usage'!$F:$F,'Consumable Usage'!$A:$A,$A6,'Consumable Usage'!$D:$D,16))) -> 0 | FF6: =IF($A6="","",FB6+FD6+FC6) -> 0 | FH6: =IF(FF6="","",FF6-FG6) -> 0 | FI6: =IF(OR($A6="",EZ6=""),"",IF(FF6=0,"No Charges",IF(FH6<=0,"Paid",IF(FG6>0,"Partial","Pending")))) | FM6: =IF($A6="","",SUMIFS('Consumable Usage'!$E:$E,'Consumable Usage'!$A:$A,$A6,'Consumable Usage'!$D:$D,16)) -> 0 | FN6: =IF($A6="","",SUMIFS('Nursing Charges'!$I:$I,'Nursing Charges'!$A:$A,$A6,'Nursing Charges'!$C:$C,16)) -> 0 | FO6: =IF($A6="","",FL6+(FN6-SUMIFS('Nursing Charges'!$J:$J,'Nursing Charges'!$A:$A,$A6,'Nursing Charges'!$C:$C,16))+(FM6-SUMIFS('Consumable Usage'!$F:$F,'Consumable Usage'!$A:$A,$A6,'Consumable Usage'!$D:$D,16))) -> 0 | FP6: =IF($A6="","",FL6+FN6+FM6) -> 0 | FR6: =IF(FP6="","",FP6-FQ6) -> 0 | FS6: =IF(OR($A6="",FJ6=""),"",IF(FP6=0,"No Charges",IF(FR6<=0,"Paid",IF(FQ6>0,"Partial","Pending"))))
A7: CC2026002 | B7: Pushpa Ram Bachani | C7: SOUMYA AND TANYA | D7: 98338 63777 : Divesh Bachani | E7: need to create bill for 19th and 25th | G7: 2026-07-19 | H7: 0 | I7: =IF($A7="","",SUMIFS('Consumable Usage'!$E:$E,'Consumable Usage'!$A:$A,$A7,'Consumable Usage'!$D:$D,1)) -> 0 | J7: =IF($A7="","",SUMIFS('Nursing Charges'!$I:$I,'Nursing Charges'!$A:$A,$A7,'Nursing Charges'!$C:$C,1)) -> 0 | K7: =IF($A7="","",H7+(J7-SUMIFS('Nursing Charges'!$J:$J,'Nursing Charges'!$A:$A,$A7,'Nursing Charges'!$C:$C,1))+(I7-SUMIFS('Consumable Usage'!$F:$F,'Consumable Usage'!$A:$A,$A7,'Consumable Usage'!$D:$D,1))) -> 0 | L7: =IF($A7="","",H7+J7+I7) -> 0 | M7: 0 | N7: =IF(L7="","",L7-M7) -> 0 | O7: =IF(OR($A7="",F7=""),"",IF(L7=0,"No Charges",IF(N7<=0,"Paid",IF(M7>0,"Partial","Pending")))) | P7: Chemo Infusion | Q7: 2026-07-25 | R7: 0 | S7: =IF($A7="","",SUMIFS('Consumable Usage'!$E:$E,'Consumable Usage'!$A:$A,$A7,'Consumable Usage'!$D:$D,2)) -> 0 | T7: =IF($A7="","",SUMIFS('Nursing Charges'!$I:$I,'Nursing Charges'!$A:$A,$A7,'Nursing Charges'!$C:$C,2)) -> 0 | U7: =IF($A7="","",R7+(T7-SUMIFS('Nursing Charges'!$J:$J,'Nursing Charges'!$A:$A,$A7,'Nursing Charges'!$C:$C,2))+(S7-SUMIFS('Consumable Usage'!$F:$F,'Consumable Usage'!$A:$A,$A7,'Consumable Usage'!$D:$D,2))) -> 0 | V7: =IF($A7="","",R7+T7+S7) -> 0 | W7: 0 | X7: =IF(V7="","",V7-W7) -> 0 | Y7: =IF(OR($A7="",P7=""),"",IF(V7=0,"No Charges",IF(X7<=0,"Paid",IF(W7>0,"Partial","Pending")))) -> No Charges | AC7: =IF($A7="","",SUMIFS('Consumable Usage'!$E:$E,'Consumable Usage'!$A:$A,$A7,'Consumable Usage'!$D:$D,3)) -> 0 | AD7: =IF($A7="","",SUMIFS('Nursing Charges'!$I:$I,'Nursing Charges'!$A:$A,$A7,'Nursing Charges'!$C:$C,3)) -> 0 | AE7: =IF($A7="","",AB7+(AD7-SUMIFS('Nursing Charges'!$J:$J,'Nursing Charges'!$A:$A,$A7,'Nursing Charges'!$C:$C,3))+(AC7-SUMIFS('Consumable Usage'!$F:$F,'Consumable Usage'!$A:$A,$A7,'Consumable Usage'!$D:$D,3))) -> 0 | AF7: =IF($A7="","",AB7+AD7+AC7) -> 0 | AH7: =IF(AF7="","",AF7-AG7) -> 0 | AI7: =IF(OR($A7="",Z7=""),"",IF(AF7=0,"No Charges",IF(AH7<=0,"Paid",IF(AG7>0,"Partial","Pending")))) | AM7: =IF($A7="","",SUMIFS('Consumable Usage'!$E:$E,'Consumable Usage'!$A:$A,$A7,'Consumable Usage'!$D:$D,4)) -> 0 | AN7: =IF($A7="","",SUMIFS('Nursing Charges'!$I:$I,'Nursing Charges'!$A:$A,$A7,'Nursing Charges'!$C:$C,4)) -> 0 | AO7: =IF($A7="","",AL7+(AN7-SUMIFS('Nursing Charges'!$J:$J,'Nursing Charges'!$A:$A,$A7,'Nursing Charges'!$C:$C,4))+(AM7-SUMIFS('Consumable Usage'!$F:$F,'Consumable Usage'!$A:$A,$A7,'Consumable Usage'!$D:$D,4))) -> 0 | AP7: =IF($A7="","",AL7+AN7+AM7) -> 0 | AR7: =IF(AP7="","",AP7-AQ7) -> 0 | AS7: =IF(OR($A7="",AJ7=""),"",IF(AP7=0,"No Charges",IF(AR7<=0,"Paid",IF(AQ7>0,"Partial","Pending")))) | AW7: =IF($A7="","",SUMIFS('Consumable Usage'!$E:$E,'Consumable Usage'!$A:$A,$A7,'Consumable Usage'!$D:$D,5)) -> 0 | AX7: =IF($A7="","",SUMIFS('Nursing Charges'!$I:$I,'Nursing Charges'!$A:$A,$A7,'Nursing Charges'!$C:$C,5)) -> 0 | AY7: =IF($A7="","",AV7+(AX7-SUMIFS('Nursing Charges'!$J:$J,'Nursing Charges'!$A:$A,$A7,'Nursing Charges'!$C:$C,5))+(AW7-SUMIFS('Consumable Usage'!$F:$F,'Consumable Usage'!$A:$A,$A7,'Consumable Usage'!$D:$D,5))) -> 0 | AZ7: =IF($A7="","",AV7+AX7+AW7) -> 0 | BB7: =IF(AZ7="","",AZ7-BA7) -> 0 | BC7: =IF(OR($A7="",AT7=""),"",IF(AZ7=0,"No Charges",IF(BB7<=0,"Paid",IF(BA7>0,"Partial","Pending")))) | BG7: =IF($A7="","",SUMIFS('Consumable Usage'!$E:$E,'Consumable Usage'!$A:$A,$A7,'Consumable Usage'!$D:$D,6)) -> 0 | BH7: =IF($A7="","",SUMIFS('Nursing Charges'!$I:$I,'Nursing Charges'!$A:$A,$A7,'Nursing Charges'!$C:$C,6)) -> 0 | BI7: =IF($A7="","",BF7+(BH7-SUMIFS('Nursing Charges'!$J:$J,'Nursing Charges'!$A:$A,$A7,'Nursing Charges'!$C:$C,6))+(BG7-SUMIFS('Consumable Usage'!$F:$F,'Consumable Usage'!$A:$A,$A7,'Consumable Usage'!$D:$D,6))) -> 0 | BJ7: =IF($A7="","",BF7+BH7+BG7) -> 0 | BL7: =IF(BJ7="","",BJ7-BK7) -> 0 | BM7: =IF(OR($A7="",BD7=""),"",IF(BJ7=0,"No Charges",IF(BL7<=0,"Paid",IF(BK7>0,"Partial","Pending")))) | BQ7: =IF($A7="","",SUMIFS('Consumable Usage'!$E:$E,'Consumable Usage'!$A:$A,$A7,'Consumable Usage'!$D:$D,7)) -> 0 | BR7: =IF($A7="","",SUMIFS('Nursing Charges'!$I:$I,'Nursing Charges'!$A:$A,$A7,'Nursing Charges'!$C:$C,7)) -> 0 | BS7: =IF($A7="","",BP7+(BR7-SUMIFS('Nursing Charges'!$J:$J,'Nursing Charges'!$A:$A,$A7,'Nursing Charges'!$C:$C,7))+(BQ7-SUMIFS('Consumable Usage'!$F:$F,'Consumable Usage'!$A:$A,$A7,'Consumable Usage'!$D:$D,7))) -> 0 | BT7: =IF($A7="","",BP7+BR7+BQ7) -> 0 | BV7: =IF(BT7="","",BT7-BU7) -> 0 | BW7: =IF(OR($A7="",BN7=""),"",IF(BT7=0,"No Charges",IF(BV7<=0,"Paid",IF(BU7>0,"Partial","Pending")))) | CA7: =IF($A7="","",SUMIFS('Consumable Usage'!$E:$E,'Consumable Usage'!$A:$A,$A7,'Consumable Usage'!$D:$D,8)) -> 0 | CB7: =IF($A7="","",SUMIFS('Nursing Charges'!$I:$I,'Nursing Charges'!$A:$A,$A7,'Nursing Charges'!$C:$C,8)) -> 0 | CC7: =IF($A7="","",BZ7+(CB7-SUMIFS('Nursing Charges'!$J:$J,'Nursing Charges'!$A:$A,$A7,'Nursing Charges'!$C:$C,8))+(CA7-SUMIFS('Consumable Usage'!$F:$F,'Consumable Usage'!$A:$A,$A7,'Consumable Usage'!$D:$D,8))) -> 0 | CD7: =IF($A7="","",BZ7+CB7+CA7) -> 0 | CF7: =IF(CD7="","",CD7-CE7) -> 0 | CG7: =IF(OR($A7="",BX7=""),"",IF(CD7=0,"No Charges",IF(CF7<=0,"Paid",IF(CE7>0,"Partial","Pending")))) | CK7: =IF($A7="","",SUMIFS('Consumable Usage'!$E:$E,'Consumable Usage'!$A:$A,$A7,'Consumable Usage'!$D:$D,9)) -> 0 | CL7: =IF($A7="","",SUMIFS('Nursing Charges'!$I:$I,'Nursing Charges'!$A:$A,$A7,'Nursing Charges'!$C:$C,9)) -> 0 | CM7: =IF($A7="","",CJ7+(CL7-SUMIFS('Nursing Charges'!$J:$J,'Nursing Charges'!$A:$A,$A7,'Nursing Charges'!$C:$C,9))+(CK7-SUMIFS('Consumable Usage'!$F:$F,'Consumable Usage'!$A:$A,$A7,'Consumable Usage'!$D:$D,9))) -> 0 | CN7: =IF($A7="","",CJ7+CL7+CK7) -> 0 | CP7: =IF(CN7="","",CN7-CO7) -> 0 | CQ7: =IF(OR($A7="",CH7=""),"",IF(CN7=0,"No Charges",IF(CP7<=0,"Paid",IF(CO7>0,"Partial","Pending")))) | CU7: =IF($A7="","",SUMIFS('Consumable Usage'!$E:$E,'Consumable Usage'!$A:$A,$A7,'Consumable Usage'!$D:$D,10)) -> 0 | CV7: =IF($A7="","",SUMIFS('Nursing Charges'!$I:$I,'Nursing Charges'!$A:$A,$A7,'Nursing Charges'!$C:$C,10)) -> 0 | CW7: =IF($A7="","",CT7+(CV7-SUMIFS('Nursing Charges'!$J:$J,'Nursing Charges'!$A:$A,$A7,'Nursing Charges'!$C:$C,10))+(CU7-SUMIFS('Consumable Usage'!$F:$F,'Consumable Usage'!$A:$A,$A7,'Consumable Usage'!$D:$D,10))) -> 0 | CX7: =IF($A7="","",CT7+CV7+CU7) -> 0 | CZ7: =IF(CX7="","",CX7-CY7) -> 0 | DA7: =IF(OR($A7="",CR7=""),"",IF(CX7=0,"No Charges",IF(CZ7<=0,"Paid",IF(CY7>0,"Partial","Pending")))) | DE7: =IF($A7="","",SUMIFS('Consumable Usage'!$E:$E,'Consumable Usage'!$A:$A,$A7,'Consumable Usage'!$D:$D,11)) -> 0 | DF7: =IF($A7="","",SUMIFS('Nursing Charges'!$I:$I,'Nursing Charges'!$A:$A,$A7,'Nursing Charges'!$C:$C,11)) -> 0 | DG7: =IF($A7="","",DD7+(DF7-SUMIFS('Nursing Charges'!$J:$J,'Nursing Charges'!$A:$A,$A7,'Nursing Charges'!$C:$C,11))+(DE7-SUMIFS('Consumable Usage'!$F:$F,'Consumable Usage'!$A:$A,$A7,'Consumable Usage'!$D:$D,11))) -> 0 | DH7: =IF($A7="","",DD7+DF7+DE7) -> 0 | DJ7: =IF(DH7="","",DH7-DI7) -> 0 | DK7: =IF(OR($A7="",DB7=""),"",IF(DH7=0,"No Charges",IF(DJ7<=0,"Paid",IF(DI7>0,"Partial","Pending")))) | DO7: =IF($A7="","",SUMIFS('Consumable Usage'!$E:$E,'Consumable Usage'!$A:$A,$A7,'Consumable Usage'!$D:$D,12)) -> 0 | DP7: =IF($A7="","",SUMIFS('Nursing Charges'!$I:$I,'Nursing Charges'!$A:$A,$A7,'Nursing Charges'!$C:$C,12)) -> 0 | DQ7: =IF($A7="","",DN7+(DP7-SUMIFS('Nursing Charges'!$J:$J,'Nursing Charges'!$A:$A,$A7,'Nursing Charges'!$C:$C,12))+(DO7-SUMIFS('Consumable Usage'!$F:$F,'Consumable Usage'!$A:$A,$A7,'Consumable Usage'!$D:$D,12))) -> 0 | DR7: =IF($A7="","",DN7+DP7+DO7) -> 0 | DT7: =IF(DR7="","",DR7-DS7) -> 0 | DU7: =IF(OR($A7="",DL7=""),"",IF(DR7=0,"No Charges",IF(DT7<=0,"Paid",IF(DS7>0,"Partial","Pending")))) | DY7: =IF($A7="","",SUMIFS('Consumable Usage'!$E:$E,'Consumable Usage'!$A:$A,$A7,'Consumable Usage'!$D:$D,13)) -> 0 | DZ7: =IF($A7="","",SUMIFS('Nursing Charges'!$I:$I,'Nursing Charges'!$A:$A,$A7,'Nursing Charges'!$C:$C,13)) -> 0 | EA7: =IF($A7="","",DX7+(DZ7-SUMIFS('Nursing Charges'!$J:$J,'Nursing Charges'!$A:$A,$A7,'Nursing Charges'!$C:$C,13))+(DY7-SUMIFS('Consumable Usage'!$F:$F,'Consumable Usage'!$A:$A,$A7,'Consumable Usage'!$D:$D,13))) -> 0 | EB7: =IF($A7="","",DX7+DZ7+DY7) -> 0 | ED7: =IF(EB7="","",EB7-EC7) -> 0 | EE7: =IF(OR($A7="",DV7=""),"",IF(EB7=0,"No Charges",IF(ED7<=0,"Paid",IF(EC7>0,"Partial","Pending")))) | EI7: =IF($A7="","",SUMIFS('Consumable Usage'!$E:$E,'Consumable Usage'!$A:$A,$A7,'Consumable Usage'!$D:$D,14)) -> 0 | EJ7: =IF($A7="","",SUMIFS('Nursing Charges'!$I:$I,'Nursing Charges'!$A:$A,$A7,'Nursing Charges'!$C:$C,14)) -> 0 | EK7: =IF($A7="","",EH7+(EJ7-SUMIFS('Nursing Charges'!$J:$J,'Nursing Charges'!$A:$A,$A7,'Nursing Charges'!$C:$C,14))+(EI7-SUMIFS('Consumable Usage'!$F:$F,'Consumable Usage'!$A:$A,$A7,'Consumable Usage'!$D:$D,14))) -> 0 | EL7: =IF($A7="","",EH7+EJ7+EI7) -> 0 | EN7: =IF(EL7="","",EL7-EM7) -> 0 | EO7: =IF(OR($A7="",EF7=""),"",IF(EL7=0,"No Charges",IF(EN7<=0,"Paid",IF(EM7>0,"Partial","Pending")))) | ES7: =IF($A7="","",SUMIFS('Consumable Usage'!$E:$E,'Consumable Usage'!$A:$A,$A7,'Consumable Usage'!$D:$D,15)) -> 0 | ET7: =IF($A7="","",SUMIFS('Nursing Charges'!$I:$I,'Nursing Charges'!$A:$A,$A7,'Nursing Charges'!$C:$C,15)) -> 0 | EU7: =IF($A7="","",ER7+(ET7-SUMIFS('Nursing Charges'!$J:$J,'Nursing Charges'!$A:$A,$A7,'Nursing Charges'!$C:$C,15))+(ES7-SUMIFS('Consumable Usage'!$F:$F,'Consumable Usage'!$A:$A,$A7,'Consumable Usage'!$D:$D,15))) -> 0 | EV7: =IF($A7="","",ER7+ET7+ES7) -> 0 | EX7: =IF(EV7="","",EV7-EW7) -> 0 | EY7: =IF(OR($A7="",EP7=""),"",IF(EV7=0,"No Charges",IF(EX7<=0,"Paid",IF(EW7>0,"Partial","Pending")))) | FC7: =IF($A7="","",SUMIFS('Consumable Usage'!$E:$E,'Consumable Usage'!$A:$A,$A7,'Consumable Usage'!$D:$D,16)) -> 0 | FD7: =IF($A7="","",SUMIFS('Nursing Charges'!$I:$I,'Nursing Charges'!$A:$A,$A7,'Nursing Charges'!$C:$C,16)) -> 0 | FE7: =IF($A7="","",FB7+(FD7-SUMIFS('Nursing Charges'!$J:$J,'Nursing Charges'!$A:$A,$A7,'Nursing Charges'!$C:$C,16))+(FC7-SUMIFS('Consumable Usage'!$F:$F,'Consumable Usage'!$A:$A,$A7,'Consumable Usage'!$D:$D,16))) -> 0 | FF7: =IF($A7="","",FB7+FD7+FC7) -> 0 | FH7: =IF(FF7="","",FF7-FG7) -> 0 | FI7: =IF(OR($A7="",EZ7=""),"",IF(FF7=0,"No Charges",IF(FH7<=0,"Paid",IF(FG7>0,"Partial","Pending")))) | FM7: =IF($A7="","",SUMIFS('Consumable Usage'!$E:$E,'Consumable Usage'!$A:$A,$A7,'Consumable Usage'!$D:$D,16)) -> 0 | FN7: =IF($A7="","",SUMIFS('Nursing Charges'!$I:$I,'Nursing Charges'!$A:$A,$A7,'Nursing Charges'!$C:$C,16)) -> 0 | FO7: =IF($A7="","",FL7+(FN7-SUMIFS('Nursing Charges'!$J:$J,'Nursing Charges'!$A:$A,$A7,'Nursing Charges'!$C:$C,16))+(FM7-SUMIFS('Consumable Usage'!$F:$F,'Consumable Usage'!$A:$A,$A7,'Consumable Usage'!$D:$D,16))) -> 0 | FP7: =IF($A7="","",FL7+FN7+FM7) -> 0 | FR7: =IF(FP7="","",FP7-FQ7) -> 0 | FS7: =IF(OR($A7="",FJ7=""),"",IF(FP7=0,"No Charges",IF(FR7<=0,"Paid",IF(FQ7>0,"Partial","Pending"))))
A8: CC2026003 | B8: Zara Morani | C8: - | D8: 98213 19074 : Karim Morani | G8: 2026-06-17 | H8: 0 | I8: =IF($A8="","",SUMIFS('Consumable Usage'!$E:$E,'Consumable Usage'!$A:$A,$A8,'Consumable Usage'!$D:$D,1)) -> 1470 | J8: =IF($A8="","",SUMIFS('Nursing Charges'!$I:$I,'Nursing Charges'!$A:$A,$A8,'Nursing Charges'!$C:$C,1)) -> 3500 | K8: =IF($A8="","",H8+(J8-SUMIFS('Nursing Charges'!$J:$J,'Nursing Charges'!$A:$A,$A8,'Nursing Charges'!$C:$C,1))+(I8-SUMIFS('Consumable Usage'!$F:$F,'Consumable Usage'!$A:$A,$A8,'Consumable Usage'!$D:$D,1))) -> 4050 | L8: =IF($A8="","",H8+J8+I8) -> 4970 | N8: =IF(L8="","",L8-M8) -> 4970 | O8: =IF(OR($A8="",F8=""),"",IF(L8=0,"No Charges",IF(N8<=0,"Paid",IF(M8>0,"Partial","Pending")))) | P8: Chemo Infusion + Nursing 24hrs | Q8: 2026-07-28 | R8: 0 | S8: =IF($A8="","",SUMIFS('Consumable Usage'!$E:$E,'Consumable Usage'!$A:$A,$A8,'Consumable Usage'!$D:$D,2)) -> 0 | T8: =IF($A8="","",SUMIFS('Nursing Charges'!$I:$I,'Nursing Charges'!$A:$A,$A8,'Nursing Charges'!$C:$C,2)) -> 3500 | U8: =IF($A8="","",R8+(T8-SUMIFS('Nursing Charges'!$J:$J,'Nursing Charges'!$A:$A,$A8,'Nursing Charges'!$C:$C,2))+(S8-SUMIFS('Consumable Usage'!$F:$F,'Consumable Usage'!$A:$A,$A8,'Consumable Usage'!$D:$D,2))) -> 3500 | V8: =IF($A8="","",R8+T8+S8) -> 3500 | X8: =IF(V8="","",V8-W8) -> 3500 | Y8: =IF(OR($A8="",P8=""),"",IF(V8=0,"No Charges",IF(X8<=0,"Paid",IF(W8>0,"Partial","Pending")))) -> Pending | AC8: =IF($A8="","",SUMIFS('Consumable Usage'!$E:$E,'Consumable Usage'!$A:$A,$A8,'Consumable Usage'!$D:$D,3)) -> 0 | AD8: =IF($A8="","",SUMIFS('Nursing Charges'!$I:$I,'Nursing Charges'!$A:$A,$A8,'Nursing Charges'!$C:$C,3)) -> 0 | AE8: =IF($A8="","",AB8+(AD8-SUMIFS('Nursing Charges'!$J:$J,'Nursing Charges'!$A:$A,$A8,'Nursing Charges'!$C:$C,3))+(AC8-SUMIFS('Consumable Usage'!$F:$F,'Consumable Usage'!$A:$A,$A8,'Consumable Usage'!$D:$D,3))) -> 0 | AF8: =IF($A8="","",AB8+AD8+AC8) -> 0 | AH8: =IF(AF8="","",AF8-AG8) -> 0 | AI8: =IF(OR($A8="",Z8=""),"",IF(AF8=0,"No Charges",IF(AH8<=0,"Paid",IF(AG8>0,"Partial","Pending")))) | AM8: =IF($A8="","",SUMIFS('Consumable Usage'!$E:$E,'Consumable Usage'!$A:$A,$A8,'Consumable Usage'!$D:$D,4)) -> 0 | AN8: =IF($A8="","",SUMIFS('Nursing Charges'!$I:$I,'Nursing Charges'!$A:$A,$A8,'Nursing Charges'!$C:$C,4)) -> 0 | AO8: =IF($A8="","",AL8+(AN8-SUMIFS('Nursing Charges'!$J:$J,'Nursing Charges'!$A:$A,$A8,'Nursing Charges'!$C:$C,4))+(AM8-SUMIFS('Consumable Usage'!$F:$F,'Consumable Usage'!$A:$A,$A8,'Consumable Usage'!$D:$D,4))) -> 0 | AP8: =IF($A8="","",AL8+AN8+AM8) -> 0 | AR8: =IF(AP8="","",AP8-AQ8) -> 0 | AS8: =IF(OR($A8="",AJ8=""),"",IF(AP8=0,"No Charges",IF(AR8<=0,"Paid",IF(AQ8>0,"Partial","Pending")))) | AW8: =IF($A8="","",SUMIFS('Consumable Usage'!$E:$E,'Consumable Usage'!$A:$A,$A8,'Consumable Usage'!$D:$D,5)) -> 0 | AX8: =IF($A8="","",SUMIFS('Nursing Charges'!$I:$I,'Nursing Charges'!$A:$A,$A8,'Nursing Charges'!$C:$C,5)) -> 0 | AY8: =IF($A8="","",AV8+(AX8-SUMIFS('Nursing Charges'!$J:$J,'Nursing Charges'!$A:$A,$A8,'Nursing Charges'!$C:$C,5))+(AW8-SUMIFS('Consumable Usage'!$F:$F,'Consumable Usage'!$A:$A,$A8,'Consumable Usage'!$D:$D,5))) -> 0 | AZ8: =IF($A8="","",AV8+AX8+AW8) -> 0 | BB8: =IF(AZ8="","",AZ8-BA8) -> 0 | BC8: =IF(OR($A8="",AT8=""),"",IF(AZ8=0,"No Charges",IF(BB8<=0,"Paid",IF(BA8>0,"Partial","Pending")))) | BG8: =IF($A8="","",SUMIFS('Consumable Usage'!$E:$E,'Consumable Usage'!$A:$A,$A8,'Consumable Usage'!$D:$D,6)) -> 0 | BH8: =IF($A8="","",SUMIFS('Nursing Charges'!$I:$I,'Nursing Charges'!$A:$A,$A8,'Nursing Charges'!$C:$C,6)) -> 0 | BI8: =IF($A8="","",BF8+(BH8-SUMIFS('Nursing Charges'!$J:$J,'Nursing Charges'!$A:$A,$A8,'Nursing Charges'!$C:$C,6))+(BG8-SUMIFS('Consumable Usage'!$F:$F,'Consumable Usage'!$A:$A,$A8,'Consumable Usage'!$D:$D,6))) -> 0 | BJ8: =IF($A8="","",BF8+BH8+BG8) -> 0 | BL8: =IF(BJ8="","",BJ8-BK8) -> 0 | BM8: =IF(OR($A8="",BD8=""),"",IF(BJ8=0,"No Charges",IF(BL8<=0,"Paid",IF(BK8>0,"Partial","Pending")))) | BQ8: =IF($A8="","",SUMIFS('Consumable Usage'!$E:$E,'Consumable Usage'!$A:$A,$A8,'Consumable Usage'!$D:$D,7)) -> 0 | BR8: =IF($A8="","",SUMIFS('Nursing Charges'!$I:$I,'Nursing Charges'!$A:$A,$A8,'Nursing Charges'!$C:$C,7)) -> 0 | BS8: =IF($A8="","",BP8+(BR8-SUMIFS('Nursing Charges'!$J:$J,'Nursing Charges'!$A:$A,$A8,'Nursing Charges'!$C:$C,7))+(BQ8-SUMIFS('Consumable Usage'!$F:$F,'Consumable Usage'!$A:$A,$A8,'Consumable Usage'!$D:$D,7))) -> 0 | BT8: =IF($A8="","",BP8+BR8+BQ8) -> 0 | BV8: =IF(BT8="","",BT8-BU8) -> 0 | BW8: =IF(OR($A8="",BN8=""),"",IF(BT8=0,"No Charges",IF(BV8<=0,"Paid",IF(BU8>0,"Partial","Pending")))) | CA8: =IF($A8="","",SUMIFS('Consumable Usage'!$E:$E,'Consumable Usage'!$A:$A,$A8,'Consumable Usage'!$D:$D,8)) -> 0 | CB8: =IF($A8="","",SUMIFS('Nursing Charges'!$I:$I,'Nursing Charges'!$A:$A,$A8,'Nursing Charges'!$C:$C,8)) -> 0 | CC8: =IF($A8="","",BZ8+(CB8-SUMIFS('Nursing Charges'!$J:$J,'Nursing Charges'!$A:$A,$A8,'Nursing Charges'!$C:$C,8))+(CA8-SUMIFS('Consumable Usage'!$F:$F,'Consumable Usage'!$A:$A,$A8,'Consumable Usage'!$D:$D,8))) -> 0 | CD8: =IF($A8="","",BZ8+CB8+CA8) -> 0 | CF8: =IF(CD8="","",CD8-CE8) -> 0 | CG8: =IF(OR($A8="",BX8=""),"",IF(CD8=0,"No Charges",IF(CF8<=0,"Paid",IF(CE8>0,"Partial","Pending")))) | CK8: =IF($A8="","",SUMIFS('Consumable Usage'!$E:$E,'Consumable Usage'!$A:$A,$A8,'Consumable Usage'!$D:$D,9)) -> 0 | CL8: =IF($A8="","",SUMIFS('Nursing Charges'!$I:$I,'Nursing Charges'!$A:$A,$A8,'Nursing Charges'!$C:$C,9)) -> 0 | CM8: =IF($A8="","",CJ8+(CL8-SUMIFS('Nursing Charges'!$J:$J,'Nursing Charges'!$A:$A,$A8,'Nursing Charges'!$C:$C,9))+(CK8-SUMIFS('Consumable Usage'!$F:$F,'Consumable Usage'!$A:$A,$A8,'Consumable Usage'!$D:$D,9))) -> 0 | CN8: =IF($A8="","",CJ8+CL8+CK8) -> 0 | CP8: =IF(CN8="","",CN8-CO8) -> 0 | CQ8: =IF(OR($A8="",CH8=""),"",IF(CN8=0,"No Charges",IF(CP8<=0,"Paid",IF(CO8>0,"Partial","Pending")))) | CU8: =IF($A8="","",SUMIFS('Consumable Usage'!$E:$E,'Consumable Usage'!$A:$A,$A8,'Consumable Usage'!$D:$D,10)) -> 0 | CV8: =IF($A8="","",SUMIFS('Nursing Charges'!$I:$I,'Nursing Charges'!$A:$A,$A8,'Nursing Charges'!$C:$C,10)) -> 0 | CW8: =IF($A8="","",CT8+(CV8-SUMIFS('Nursing Charges'!$J:$J,'Nursing Charges'!$A:$A,$A8,'Nursing Charges'!$C:$C,10))+(CU8-SUMIFS('Consumable Usage'!$F:$F,'Consumable Usage'!$A:$A,$A8,'Consumable Usage'!$D:$D,10))) -> 0 | CX8: =IF($A8="","",CT8+CV8+CU8) -> 0 | CZ8: =IF(CX8="","",CX8-CY8) -> 0 | DA8: =IF(OR($A8="",CR8=""),"",IF(CX8=0,"No Charges",IF(CZ8<=0,"Paid",IF(CY8>0,"Partial","Pending")))) | DE8: =IF($A8="","",SUMIFS('Consumable Usage'!$E:$E,'Consumable Usage'!$A:$A,$A8,'Consumable Usage'!$D:$D,11)) -> 0 | DF8: =IF($A8="","",SUMIFS('Nursing Charges'!$I:$I,'Nursing Charges'!$A:$A,$A8,'Nursing Charges'!$C:$C,11)) -> 0 | DG8: =IF($A8="","",DD8+(DF8-SUMIFS('Nursing Charges'!$J:$J,'Nursing Charges'!$A:$A,$A8,'Nursing Charges'!$C:$C,11))+(DE8-SUMIFS('Consumable Usage'!$F:$F,'Consumable Usage'!$A:$A,$A8,'Consumable Usage'!$D:$D,11))) -> 0 | DH8: =IF($A8="","",DD8+DF8+DE8) -> 0 | DJ8: =IF(DH8="","",DH8-DI8) -> 0 | DK8: =IF(OR($A8="",DB8=""),"",IF(DH8=0,"No Charges",IF(DJ8<=0,"Paid",IF(DI8>0,"Partial","Pending")))) | DO8: =IF($A8="","",SUMIFS('Consumable Usage'!$E:$E,'Consumable Usage'!$A:$A,$A8,'Consumable Usage'!$D:$D,12)) -> 0 | DP8: =IF($A8="","",SUMIFS('Nursing Charges'!$I:$I,'Nursing Charges'!$A:$A,$A8,'Nursing Charges'!$C:$C,12)) -> 0 | DQ8: =IF($A8="","",DN8+(DP8-SUMIFS('Nursing Charges'!$J:$J,'Nursing Charges'!$A:$A,$A8,'Nursing Charges'!$C:$C,12))+(DO8-SUMIFS('Consumable Usage'!$F:$F,'Consumable Usage'!$A:$A,$A8,'Consumable Usage'!$D:$D,12))) -> 0 | DR8: =IF($A8="","",DN8+DP8+DO8) -> 0 | DT8: =IF(DR8="","",DR8-DS8) -> 0 | DU8: =IF(OR($A8="",DL8=""),"",IF(DR8=0,"No Charges",IF(DT8<=0,"Paid",IF(DS8>0,"Partial","Pending")))) | DY8: =IF($A8="","",SUMIFS('Consumable Usage'!$E:$E,'Consumable Usage'!$A:$A,$A8,'Consumable Usage'!$D:$D,13)) -> 0 | DZ8: =IF($A8="","",SUMIFS('Nursing Charges'!$I:$I,'Nursing Charges'!$A:$A,$A8,'Nursing Charges'!$C:$C,13)) -> 0 | EA8: =IF($A8="","",DX8+(DZ8-SUMIFS('Nursing Charges'!$J:$J,'Nursing Charges'!$A:$A,$A8,'Nursing Charges'!$C:$C,13))+(DY8-SUMIFS('Consumable Usage'!$F:$F,'Consumable Usage'!$A:$A,$A8,'Consumable Usage'!$D:$D,13))) -> 0 | EB8: =IF($A8="","",DX8+DZ8+DY8) -> 0 | ED8: =IF(EB8="","",EB8-EC8) -> 0 | EE8: =IF(OR($A8="",DV8=""),"",IF(EB8=0,"No Charges",IF(ED8<=0,"Paid",IF(EC8>0,"Partial","Pending")))) | EI8: =IF($A8="","",SUMIFS('Consumable Usage'!$E:$E,'Consumable Usage'!$A:$A,$A8,'Consumable Usage'!$D:$D,14)) -> 0 | EJ8: =IF($A8="","",SUMIFS('Nursing Charges'!$I:$I,'Nursing Charges'!$A:$A,$A8,'Nursing Charges'!$C:$C,14)) -> 0 | EK8: =IF($A8="","",EH8+(EJ8-SUMIFS('Nursing Charges'!$J:$J,'Nursing Charges'!$A:$A,$A8,'Nursing Charges'!$C:$C,14))+(EI8-SUMIFS('Consumable Usage'!$F:$F,'Consumable Usage'!$A:$A,$A8,'Consumable Usage'!$D:$D,14))) -> 0 | EL8: =IF($A8="","",EH8+EJ8+EI8) -> 0 | EN8: =IF(EL8="","",EL8-EM8) -> 0 | EO8: =IF(OR($A8="",EF8=""),"",IF(EL8=0,"No Charges",IF(EN8<=0,"Paid",IF(EM8>0,"Partial","Pending")))) | ES8: =IF($A8="","",SUMIFS('Consumable Usage'!$E:$E,'Consumable Usage'!$A:$A,$A8,'Consumable Usage'!$D:$D,15)) -> 0 | ET8: =IF($A8="","",SUMIFS('Nursing Charges'!$I:$I,'Nursing Charges'!$A:$A,$A8,'Nursing Charges'!$C:$C,15)) -> 0 | EU8: =IF($A8="","",ER8+(ET8-SUMIFS('Nursing Charges'!$J:$J,'Nursing Charges'!$A:$A,$A8,'Nursing Charges'!$C:$C,15))+(ES8-SUMIFS('Consumable Usage'!$F:$F,'Consumable Usage'!$A:$A,$A8,'Consumable Usage'!$D:$D,15))) -> 0 | EV8: =IF($A8="","",ER8+ET8+ES8) -> 0 | EX8: =IF(EV8="","",EV8-EW8) -> 0 | EY8: =IF(OR($A8="",EP8=""),"",IF(EV8=0,"No Charges",IF(EX8<=0,"Paid",IF(EW8>0,"Partial","Pending")))) | FC8: =IF($A8="","",SUMIFS('Consumable Usage'!$E:$E,'Consumable Usage'!$A:$A,$A8,'Consumable Usage'!$D:$D,16)) -> 0 | FD8: =IF($A8="","",SUMIFS('Nursing Charges'!$I:$I,'Nursing Charges'!$A:$A,$A8,'Nursing Charges'!$C:$C,16)) -> 0 | FE8: =IF($A8="","",FB8+(FD8-SUMIFS('Nursing Charges'!$J:$J,'Nursing Charges'!$A:$A,$A8,'Nursing Charges'!$C:$C,16))+(FC8-SUMIFS('Consumable Usage'!$F:$F,'Consumable Usage'!$A:$A,$A8,'Consumable Usage'!$D:$D,16))) -> 0 | FF8: =IF($A8="","",FB8+FD8+FC8) -> 0 | FH8: =IF(FF8="","",FF8-FG8) -> 0 | FI8: =IF(OR($A8="",EZ8=""),"",IF(FF8=0,"No Charges",IF(FH8<=0,"Paid",IF(FG8>0,"Partial","Pending")))) | FM8: =IF($A8="","",SUMIFS('Consumable Usage'!$E:$E,'Consumable Usage'!$A:$A,$A8,'Consumable Usage'!$D:$D,16)) -> 0 | FN8: =IF($A8="","",SUMIFS('Nursing Charges'!$I:$I,'Nursing Charges'!$A:$A,$A8,'Nursing Charges'!$C:$C,16)) -> 0 | FO8: =IF($A8="","",FL8+(FN8-SUMIFS('Nursing Charges'!$J:$J,'Nursing Charges'!$A:$A,$A8,'Nursing Charges'!$C:$C,16))+(FM8-SUMIFS('Consumable Usage'!$F:$F,'Consumable Usage'!$A:$A,$A8,'Consumable Usage'!$D:$D,16))) -> 0 | FP8: =IF($A8="","",FL8+FN8+FM8) -> 0 | FR8: =IF(FP8="","",FP8-FQ8) -> 0 | FS8: =IF(OR($A8="",FJ8=""),"",IF(FP8=0,"No Charges",IF(FR8<=0,"Paid",IF(FQ8>0,"Partial","Pending"))))
A9: CC2026004 | B9: Sanjay Shorewala | C9: KOMAL | D9: 98208 60967 | E9: get the next dates | G9: 2026-07-23 | H9: 0 | I9: =IF($A9="","",SUMIFS('Consumable Usage'!$E:$E,'Consumable Usage'!$A:$A,$A9,'Consumable Usage'!$D:$D,1)) -> 0 | J9: =IF($A9="","",SUMIFS('Nursing Charges'!$I:$I,'Nursing Charges'!$A:$A,$A9,'Nursing Charges'!$C:$C,1)) -> 0 | K9: =IF($A9="","",H9+(J9-SUMIFS('Nursing Charges'!$J:$J,'Nursing Charges'!$A:$A,$A9,'Nursing Charges'!$C:$C,1))+(I9-SUMIFS('Consumable Usage'!$F:$F,'Consumable Usage'!$A:$A,$A9,'Consumable Usage'!$D:$D,1))) -> 0 | L9: =IF($A9="","",H9+J9+I9) -> 0 | N9: =IF(L9="","",L9-M9) -> 0 | O9: =IF(OR($A9="",F9=""),"",IF(L9=0,"No Charges",IF(N9<=0,"Paid",IF(M9>0,"Partial","Pending")))) | P9: Nursing 24hrs | Q9: 2026-07-31 | R9: 0 | S9: =IF($A9="","",SUMIFS('Consumable Usage'!$E:$E,'Consumable Usage'!$A:$A,$A9,'Consumable Usage'!$D:$D,2)) -> 0 | T9: =IF($A9="","",SUMIFS('Nursing Charges'!$I:$I,'Nursing Charges'!$A:$A,$A9,'Nursing Charges'!$C:$C,2)) -> 0 | U9: =IF($A9="","",R9+(T9-SUMIFS('Nursing Charges'!$J:$J,'Nursing Charges'!$A:$A,$A9,'Nursing Charges'!$C:$C,2))+(S9-SUMIFS('Consumable Usage'!$F:$F,'Consumable Usage'!$A:$A,$A9,'Consumable Usage'!$D:$D,2))) -> 0 | V9: =IF($A9="","",R9+T9+S9) -> 0 | X9: =IF(V9="","",V9-W9) -> 0 | Y9: =IF(OR($A9="",P9=""),"",IF(V9=0,"No Charges",IF(X9<=0,"Paid",IF(W9>0,"Partial","Pending")))) -> No Charges | Z9: Nursing 24hrs | AA9: 2026-08-01 | AB9: 0 | AC9: =IF($A9="","",SUMIFS('Consumable Usage'!$E:$E,'Consumable Usage'!$A:$A,$A9,'Consumable Usage'!$D:$D,3)) -> 0 | AD9: =IF($A9="","",SUMIFS('Nursing Charges'!$I:$I,'Nursing Charges'!$A:$A,$A9,'Nursing Charges'!$C:$C,3)) -> 0 | AE9: =IF($A9="","",AB9+(AD9-SUMIFS('Nursing Charges'!$J:$J,'Nursing Charges'!$A:$A,$A9,'Nursing Charges'!$C:$C,3))+(AC9-SUMIFS('Consumable Usage'!$F:$F,'Consumable Usage'!$A:$A,$A9,'Consumable Usage'!$D:$D,3))) -> 0 | AF9: =IF($A9="","",AB9+AD9+AC9) -> 0 | AH9: =IF(AF9="","",AF9-AG9) -> 0 | AI9: =IF(OR($A9="",Z9=""),"",IF(AF9=0,"No Charges",IF(AH9<=0,"Paid",IF(AG9>0,"Partial","Pending")))) -> No Charges | AM9: =IF($A9="","",SUMIFS('Consumable Usage'!$E:$E,'Consumable Usage'!$A:$A,$A9,'Consumable Usage'!$D:$D,4)) -> 0 | AN9: =IF($A9="","",SUMIFS('Nursing Charges'!$I:$I,'Nursing Charges'!$A:$A,$A9,'Nursing Charges'!$C:$C,4)) -> 0 | AO9: =IF($A9="","",AL9+(AN9-SUMIFS('Nursing Charges'!$J:$J,'Nursing Charges'!$A:$A,$A9,'Nursing Charges'!$C:$C,4))+(AM9-SUMIFS('Consumable Usage'!$F:$F,'Consumable Usage'!$A:$A,$A9,'Consumable Usage'!$D:$D,4))) -> 0 | AP9: =IF($A9="","",AL9+AN9+AM9) -> 0 | AR9: =IF(AP9="","",AP9-AQ9) -> 0 | AS9: =IF(OR($A9="",AJ9=""),"",IF(AP9=0,"No Charges",IF(AR9<=0,"Paid",IF(AQ9>0,"Partial","Pending")))) | AW9: =IF($A9="","",SUMIFS('Consumable Usage'!$E:$E,'Consumable Usage'!$A:$A,$A9,'Consumable Usage'!$D:$D,5)) -> 0 | AX9: =IF($A9="","",SUMIFS('Nursing Charges'!$I:$I,'Nursing Charges'!$A:$A,$A9,'Nursing Charges'!$C:$C,5)) -> 0 | AY9: =IF($A9="","",AV9+(AX9-SUMIFS('Nursing Charges'!$J:$J,'Nursing Charges'!$A:$A,$A9,'Nursing Charges'!$C:$C,5))+(AW9-SUMIFS('Consumable Usage'!$F:$F,'Consumable Usage'!$A:$A,$A9,'Consumable Usage'!$D:$D,5))) -> 0 | AZ9: =IF($A9="","",AV9+AX9+AW9) -> 0 | BB9: =IF(AZ9="","",AZ9-BA9) -> 0 | BC9: =IF(OR($A9="",AT9=""),"",IF(AZ9=0,"No Charges",IF(BB9<=0,"Paid",IF(BA9>0,"Partial","Pending")))) | BG9: =IF($A9="","",SUMIFS('Consumable Usage'!$E:$E,'Consumable Usage'!$A:$A,$A9,'Consumable Usage'!$D:$D,6)) -> 0 | BH9: =IF($A9="","",SUMIFS('Nursing Charges'!$I:$I,'Nursing Charges'!$A:$A,$A9,'Nursing Charges'!$C:$C,6)) -> 0 | BI9: =IF($A9="","",BF9+(BH9-SUMIFS('Nursing Charges'!$J:$J,'Nursing Charges'!$A:$A,$A9,'Nursing Charges'!$C:$C,6))+(BG9-SUMIFS('Consumable Usage'!$F:$F,'Consumable Usage'!$A:$A,$A9,'Consumable Usage'!$D:$D,6))) -> 0 | BJ9: =IF($A9="","",BF9+BH9+BG9) -> 0 | BL9: =IF(BJ9="","",BJ9-BK9) -> 0 | BM9: =IF(OR($A9="",BD9=""),"",IF(BJ9=0,"No Charges",IF(BL9<=0,"Paid",IF(BK9>0,"Partial","Pending")))) | BQ9: =IF($A9="","",SUMIFS('Consumable Usage'!$E:$E,'Consumable Usage'!$A:$A,$A9,'Consumable Usage'!$D:$D,7)) -> 0 | BR9: =IF($A9="","",SUMIFS('Nursing Charges'!$I:$I,'Nursing Charges'!$A:$A,$A9,'Nursing Charges'!$C:$C,7)) -> 0 | BS9: =IF($A9="","",BP9+(BR9-SUMIFS('Nursing Charges'!$J:$J,'Nursing Charges'!$A:$A,$A9,'Nursing Charges'!$C:$C,7))+(BQ9-SUMIFS('Consumable Usage'!$F:$F,'Consumable Usage'!$A:$A,$A9,'Consumable Usage'!$D:$D,7))) -> 0 | BT9: =IF($A9="","",BP9+BR9+BQ9) -> 0 | BV9: =IF(BT9="","",BT9-BU9) -> 0 | BW9: =IF(OR($A9="",BN9=""),"",IF(BT9=0,"No Charges",IF(BV9<=0,"Paid",IF(BU9>0,"Partial","Pending")))) | CA9: =IF($A9="","",SUMIFS('Consumable Usage'!$E:$E,'Consumable Usage'!$A:$A,$A9,'Consumable Usage'!$D:$D,8)) -> 0 | CB9: =IF($A9="","",SUMIFS('Nursing Charges'!$I:$I,'Nursing Charges'!$A:$A,$A9,'Nursing Charges'!$C:$C,8)) -> 0 | CC9: =IF($A9="","",BZ9+(CB9-SUMIFS('Nursing Charges'!$J:$J,'Nursing Charges'!$A:$A,$A9,'Nursing Charges'!$C:$C,8))+(CA9-SUMIFS('Consumable Usage'!$F:$F,'Consumable Usage'!$A:$A,$A9,'Consumable Usage'!$D:$D,8))) -> 0 | CD9: =IF($A9="","",BZ9+CB9+CA9) -> 0 | CF9: =IF(CD9="","",CD9-CE9) -> 0 | CG9: =IF(OR($A9="",BX9=""),"",IF(CD9=0,"No Charges",IF(CF9<=0,"Paid",IF(CE9>0,"Partial","Pending")))) | CK9: =IF($A9="","",SUMIFS('Consumable Usage'!$E:$E,'Consumable Usage'!$A:$A,$A9,'Consumable Usage'!$D:$D,9)) -> 0 | CL9: =IF($A9="","",SUMIFS('Nursing Charges'!$I:$I,'Nursing Charges'!$A:$A,$A9,'Nursing Charges'!$C:$C,9)) -> 0 | CM9: =IF($A9="","",CJ9+(CL9-SUMIFS('Nursing Charges'!$J:$J,'Nursing Charges'!$A:$A,$A9,'Nursing Charges'!$C:$C,9))+(CK9-SUMIFS('Consumable Usage'!$F:$F,'Consumable Usage'!$A:$A,$A9,'Consumable Usage'!$D:$D,9))) -> 0 | CN9: =IF($A9="","",CJ9+CL9+CK9) -> 0 | CP9: =IF(CN9="","",CN9-CO9) -> 0 | CQ9: =IF(OR($A9="",CH9=""),"",IF(CN9=0,"No Charges",IF(CP9<=0,"Paid",IF(CO9>0,"Partial","Pending")))) | CU9: =IF($A9="","",SUMIFS('Consumable Usage'!$E:$E,'Consumable Usage'!$A:$A,$A9,'Consumable Usage'!$D:$D,10)) -> 0 | CV9: =IF($A9="","",SUMIFS('Nursing Charges'!$I:$I,'Nursing Charges'!$A:$A,$A9,'Nursing Charges'!$C:$C,10)) -> 0 | CW9: =IF($A9="","",CT9+(CV9-SUMIFS('Nursing Charges'!$J:$J,'Nursing Charges'!$A:$A,$A9,'Nursing Charges'!$C:$C,10))+(CU9-SUMIFS('Consumable Usage'!$F:$F,'Consumable Usage'!$A:$A,$A9,'Consumable Usage'!$D:$D,10))) -> 0 | CX9: =IF($A9="","",CT9+CV9+CU9) -> 0 | CZ9: =IF(CX9="","",CX9-CY9) -> 0 | DA9: =IF(OR($A9="",CR9=""),"",IF(CX9=0,"No Charges",IF(CZ9<=0,"Paid",IF(CY9>0,"Partial","Pending")))) | DE9: =IF($A9="","",SUMIFS('Consumable Usage'!$E:$E,'Consumable Usage'!$A:$A,$A9,'Consumable Usage'!$D:$D,11)) -> 0 | DF9: =IF($A9="","",SUMIFS('Nursing Charges'!$I:$I,'Nursing Charges'!$A:$A,$A9,'Nursing Charges'!$C:$C,11)) -> 0 | DG9: =IF($A9="","",DD9+(DF9-SUMIFS('Nursing Charges'!$J:$J,'Nursing Charges'!$A:$A,$A9,'Nursing Charges'!$C:$C,11))+(DE9-SUMIFS('Consumable Usage'!$F:$F,'Consumable Usage'!$A:$A,$A9,'Consumable Usage'!$D:$D,11))) -> 0 | DH9: =IF($A9="","",DD9+DF9+DE9) -> 0 | DJ9: =IF(DH9="","",DH9-DI9) -> 0 | DK9: =IF(OR($A9="",DB9=""),"",IF(DH9=0,"No Charges",IF(DJ9<=0,"Paid",IF(DI9>0,"Partial","Pending")))) | DO9: =IF($A9="","",SUMIFS('Consumable Usage'!$E:$E,'Consumable Usage'!$A:$A,$A9,'Consumable Usage'!$D:$D,12)) -> 0 | DP9: =IF($A9="","",SUMIFS('Nursing Charges'!$I:$I,'Nursing Charges'!$A:$A,$A9,'Nursing Charges'!$C:$C,12)) -> 0 | DQ9: =IF($A9="","",DN9+(DP9-SUMIFS('Nursing Charges'!$J:$J,'Nursing Charges'!$A:$A,$A9,'Nursing Charges'!$C:$C,12))+(DO9-SUMIFS('Consumable Usage'!$F:$F,'Consumable Usage'!$A:$A,$A9,'Consumable Usage'!$D:$D,12))) -> 0 | DR9: =IF($A9="","",DN9+DP9+DO9) -> 0 | DT9: =IF(DR9="","",DR9-DS9) -> 0 | DU9: =IF(OR($A9="",DL9=""),"",IF(DR9=0,"No Charges",IF(DT9<=0,"Paid",IF(DS9>0,"Partial","Pending")))) | DY9: =IF($A9="","",SUMIFS('Consumable Usage'!$E:$E,'Consumable Usage'!$A:$A,$A9,'Consumable Usage'!$D:$D,13)) -> 0 | DZ9: =IF($A9="","",SUMIFS('Nursing Charges'!$I:$I,'Nursing Charges'!$A:$A,$A9,'Nursing Charges'!$C:$C,13)) -> 0 | EA9: =IF($A9="","",DX9+(DZ9-SUMIFS('Nursing Charges'!$J:$J,'Nursing Charges'!$A:$A,$A9,'Nursing Charges'!$C:$C,13))+(DY9-SUMIFS('Consumable Usage'!$F:$F,'Consumable Usage'!$A:$A,$A9,'Consumable Usage'!$D:$D,13))) -> 0 | EB9: =IF($A9="","",DX9+DZ9+DY9) -> 0 | ED9: =IF(EB9="","",EB9-EC9) -> 0 | EE9: =IF(OR($A9="",DV9=""),"",IF(EB9=0,"No Charges",IF(ED9<=0,"Paid",IF(EC9>0,"Partial","Pending")))) | EI9: =IF($A9="","",SUMIFS('Consumable Usage'!$E:$E,'Consumable Usage'!$A:$A,$A9,'Consumable Usage'!$D:$D,14)) -> 0 | EJ9: =IF($A9="","",SUMIFS('Nursing Charges'!$I:$I,'Nursing Charges'!$A:$A,$A9,'Nursing Charges'!$C:$C,14)) -> 0 | EK9: =IF($A9="","",EH9+(EJ9-SUMIFS('Nursing Charges'!$J:$J,'Nursing Charges'!$A:$A,$A9,'Nursing Charges'!$C:$C,14))+(EI9-SUMIFS('Consumable Usage'!$F:$F,'Consumable Usage'!$A:$A,$A9,'Consumable Usage'!$D:$D,14))) -> 0 | EL9: =IF($A9="","",EH9+EJ9+EI9) -> 0 | EN9: =IF(EL9="","",EL9-EM9) -> 0 | EO9: =IF(OR($A9="",EF9=""),"",IF(EL9=0,"No Charges",IF(EN9<=0,"Paid",IF(EM9>0,"Partial","Pending")))) | ES9: =IF($A9="","",SUMIFS('Consumable Usage'!$E:$E,'Consumable Usage'!$A:$A,$A9,'Consumable Usage'!$D:$D,15)) -> 0 | ET9: =IF($A9="","",SUMIFS('Nursing Charges'!$I:$I,'Nursing Charges'!$A:$A,$A9,'Nursing Charges'!$C:$C,15)) -> 0 | EU9: =IF($A9="","",ER9+(ET9-SUMIFS('Nursing Charges'!$J:$J,'Nursing Charges'!$A:$A,$A9,'Nursing Charges'!$C:$C,15))+(ES9-SUMIFS('Consumable Usage'!$F:$F,'Consumable Usage'!$A:$A,$A9,'Consumable Usage'!$D:$D,15))) -> 0 | EV9: =IF($A9="","",ER9+ET9+ES9) -> 0 | EX9: =IF(EV9="","",EV9-EW9) -> 0 | EY9: =IF(OR($A9="",EP9=""),"",IF(EV9=0,"No Charges",IF(EX9<=0,"Paid",IF(EW9>0,"Partial","Pending")))) | FC9: =IF($A9="","",SUMIFS('Consumable Usage'!$E:$E,'Consumable Usage'!$A:$A,$A9,'Consumable Usage'!$D:$D,16)) -> 0 | FD9: =IF($A9="","",SUMIFS('Nursing Charges'!$I:$I,'Nursing Charges'!$A:$A,$A9,'Nursing Charges'!$C:$C,16)) -> 0 | FE9: =IF($A9="","",FB9+(FD9-SUMIFS('Nursing Charges'!$J:$J,'Nursing Charges'!$A:$A,$A9,'Nursing Charges'!$C:$C,16))+(FC9-SUMIFS('Consumable Usage'!$F:$F,'Consumable Usage'!$A:$A,$A9,'Consumable Usage'!$D:$D,16))) -> 0 | FF9: =IF($A9="","",FB9+FD9+FC9) -> 0 | FH9: =IF(FF9="","",FF9-FG9) -> 0 | FI9: =IF(OR($A9="",EZ9=""),"",IF(FF9=0,"No Charges",IF(FH9<=0,"Paid",IF(FG9>0,"Partial","Pending")))) | FM9: =IF($A9="","",SUMIFS('Consumable Usage'!$E:$E,'Consumable Usage'!$A:$A,$A9,'Consumable Usage'!$D:$D,16)) -> 0 | FN9: =IF($A9="","",SUMIFS('Nursing Charges'!$I:$I,'Nursing Charges'!$A:$A,$A9,'Nursing Charges'!$C:$C,16)) -> 0 | FO9: =IF($A9="","",FL9+(FN9-SUMIFS('Nursing Charges'!$J:$J,'Nursing Charges'!$A:$A,$A9,'Nursing Charges'!$C:$C,16))+(FM9-SUMIFS('Consumable Usage'!$F:$F,'Consumable Usage'!$A:$A,$A9,'Consumable Usage'!$D:$D,16))) -> 0 | FP9: =IF($A9="","",FL9+FN9+FM9) -> 0 | FR9: =IF(FP9="","",FP9-FQ9) -> 0 | FS9: =IF(OR($A9="",FJ9=""),"",IF(FP9=0,"No Charges",IF(FR9<=0,"Paid",IF(FQ9>0,"Partial","Pending"))))
A10: CC2026005 | B10: Vijay Pandey | C10: KOMAL | D10: 98200 68937 : Rajesh Dubey | E10: gray colur is for the infuaion that will happen in hospital | I10: =IF($A10="","",SUMIFS('Consumable Usage'!$E:$E,'Consumable Usage'!$A:$A,$A10,'Consumable Usage'!$D:$D,1)) -> 0 | J10: =IF($A10="","",SUMIFS('Nursing Charges'!$I:$I,'Nursing Charges'!$A:$A,$A10,'Nursing Charges'!$C:$C,1)) -> 0 | K10: =IF($A10="","",H10+(J10-SUMIFS('Nursing Charges'!$J:$J,'Nursing Charges'!$A:$A,$A10,'Nursing Charges'!$C:$C,1))+(I10-SUMIFS('Consumable Usage'!$F:$F,'Consumable Usage'!$A:$A,$A10,'Consumable Usage'!$D:$D,1))) -> 0 | L10: =IF($A10="","",H10+J10+I10) -> 0 | N10: =IF(L10="","",L10-M10) -> 0 | O10: =IF(OR($A10="",F10=""),"",IF(L10=0,"No Charges",IF(N10<=0,"Paid",IF(M10>0,"Partial","Pending")))) | S10: =IF($A10="","",SUMIFS('Consumable Usage'!$E:$E,'Consumable Usage'!$A:$A,$A10,'Consumable Usage'!$D:$D,2)) -> 0 | T10: =IF($A10="","",SUMIFS('Nursing Charges'!$I:$I,'Nursing Charges'!$A:$A,$A10,'Nursing Charges'!$C:$C,2)) -> 0 | U10: =IF($A10="","",R10+(T10-SUMIFS('Nursing Charges'!$J:$J,'Nursing Charges'!$A:$A,$A10,'Nursing Charges'!$C:$C,2))+(S10-SUMIFS('Consumable Usage'!$F:$F,'Consumable Usage'!$A:$A,$A10,'Consumable Usage'!$D:$D,2))) -> 0 | V10: =IF($A10="","",R10+T10+S10) -> 0 | X10: =IF(V10="","",V10-W10) -> 0 | Y10: =IF(OR($A10="",P10=""),"",IF(V10=0,"No Charges",IF(X10<=0,"Paid",IF(W10>0,"Partial","Pending")))) | AC10: =IF($A10="","",SUMIFS('Consumable Usage'!$E:$E,'Consumable Usage'!$A:$A,$A10,'Consumable Usage'!$D:$D,3)) -> 0 | AD10: =IF($A10="","",SUMIFS('Nursing Charges'!$I:$I,'Nursing Charges'!$A:$A,$A10,'Nursing Charges'!$C:$C,3)) -> 0 | AE10: =IF($A10="","",AB10+(AD10-SUMIFS('Nursing Charges'!$J:$J,'Nursing Charges'!$A:$A,$A10,'Nursing Charges'!$C:$C,3))+(AC10-SUMIFS('Consumable Usage'!$F:$F,'Consumable Usage'!$A:$A,$A10,'Consumable Usage'!$D:$D,3))) -> 0 | AF10: =IF($A10="","",AB10+AD10+AC10) -> 0 | AH10: =IF(AF10="","",AF10-AG10) -> 0 | AI10: =IF(OR($A10="",Z10=""),"",IF(AF10=0,"No Charges",IF(AH10<=0,"Paid",IF(AG10>0,"Partial","Pending")))) | AM10: =IF($A10="","",SUMIFS('Consumable Usage'!$E:$E,'Consumable Usage'!$A:$A,$A10,'Consumable Usage'!$D:$D,4)) -> 0 | AN10: =IF($A10="","",SUMIFS('Nursing Charges'!$I:$I,'Nursing Charges'!$A:$A,$A10,'Nursing Charges'!$C:$C,4)) -> 0 | AO10: =IF($A10="","",AL10+(AN10-SUMIFS('Nursing Charges'!$J:$J,'Nursing Charges'!$A:$A,$A10,'Nursing Charges'!$C:$C,4))+(AM10-SUMIFS('Consumable Usage'!$F:$F,'Consumable Usage'!$A:$A,$A10,'Consumable Usage'!$D:$D,4))) -> 0 | AP10: =IF($A10="","",AL10+AN10+AM10) -> 0 | AR10: =IF(AP10="","",AP10-AQ10) -> 0 | AS10: =IF(OR($A10="",AJ10=""),"",IF(AP10=0,"No Charges",IF(AR10<=0,"Paid",IF(AQ10>0,"Partial","Pending")))) | AW10: =IF($A10="","",SUMIFS('Consumable Usage'!$E:$E,'Consumable Usage'!$A:$A,$A10,'Consumable Usage'!$D:$D,5)) -> 0 | AX10: =IF($A10="","",SUMIFS('Nursing Charges'!$I:$I,'Nursing Charges'!$A:$A,$A10,'Nursing Charges'!$C:$C,5)) -> 0 | AY10: =IF($A10="","",AV10+(AX10-SUMIFS('Nursing Charges'!$J:$J,'Nursing Charges'!$A:$A,$A10,'Nursing Charges'!$C:$C,5))+(AW10-SUMIFS('Consumable Usage'!$F:$F,'Consumable Usage'!$A:$A,$A10,'Consumable Usage'!$D:$D,5))) -> 0 | AZ10: =IF($A10="","",AV10+AX10+AW10) -> 0 | BB10: =IF(AZ10="","",AZ10-BA10) -> 0 | BC10: =IF(OR($A10="",AT10=""),"",IF(AZ10=0,"No Charges",IF(BB10<=0,"Paid",IF(BA10>0,"Partial","Pending")))) | BG10: =IF($A10="","",SUMIFS('Consumable Usage'!$E:$E,'Consumable Usage'!$A:$A,$A10,'Consumable Usage'!$D:$D,6)) -> 0 | BH10: =IF($A10="","",SUMIFS('Nursing Charges'!$I:$I,'Nursing Charges'!$A:$A,$A10,'Nursing Charges'!$C:$C,6)) -> 0 | BI10: =IF($A10="","",BF10+(BH10-SUMIFS('Nursing Charges'!$J:$J,'Nursing Charges'!$A:$A,$A10,'Nursing Charges'!$C:$C,6))+(BG10-SUMIFS('Consumable Usage'!$F:$F,'Consumable Usage'!$A:$A,$A10,'Consumable Usage'!$D:$D,6))) -> 0 | BJ10: =IF($A10="","",BF10+BH10+BG10) -> 0 | BL10: =IF(BJ10="","",BJ10-BK10) -> 0 | BM10: =IF(OR($A10="",BD10=""),"",IF(BJ10=0,"No Charges",IF(BL10<=0,"Paid",IF(BK10>0,"Partial","Pending")))) | BQ10: =IF($A10="","",SUMIFS('Consumable Usage'!$E:$E,'Consumable Usage'!$A:$A,$A10,'Consumable Usage'!$D:$D,7)) -> 0 | BR10: =IF($A10="","",SUMIFS('Nursing Charges'!$I:$I,'Nursing Charges'!$A:$A,$A10,'Nursing Charges'!$C:$C,7)) -> 0 | BS10: =IF($A10="","",BP10+(BR10-SUMIFS('Nursing Charges'!$J:$J,'Nursing Charges'!$A:$A,$A10,'Nursing Charges'!$C:$C,7))+(BQ10-SUMIFS('Consumable Usage'!$F:$F,'Consumable Usage'!$A:$A,$A10,'Consumable Usage'!$D:$D,7))) -> 0 | BT10: =IF($A10="","",BP10+BR10+BQ10) -> 0 | BV10: =IF(BT10="","",BT10-BU10) -> 0 | BW10: =IF(OR($A10="",BN10=""),"",IF(BT10=0,"No Charges",IF(BV10<=0,"Paid",IF(BU10>0,"Partial","Pending")))) | CA10: =IF($A10="","",SUMIFS('Consumable Usage'!$E:$E,'Consumable Usage'!$A:$A,$A10,'Consumable Usage'!$D:$D,8)) -> 0 | CB10: =IF($A10="","",SUMIFS('Nursing Charges'!$I:$I,'Nursing Charges'!$A:$A,$A10,'Nursing Charges'!$C:$C,8)) -> 0 | CC10: =IF($A10="","",BZ10+(CB10-SUMIFS('Nursing Charges'!$J:$J,'Nursing Charges'!$A:$A,$A10,'Nursing Charges'!$C:$C,8))+(CA10-SUMIFS('Consumable Usage'!$F:$F,'Consumable Usage'!$A:$A,$A10,'Consumable Usage'!$D:$D,8))) -> 0 | CD10: =IF($A10="","",BZ10+CB10+CA10) -> 0 | CF10: =IF(CD10="","",CD10-CE10) -> 0 | CG10: =IF(OR($A10="",BX10=""),"",IF(CD10=0,"No Charges",IF(CF10<=0,"Paid",IF(CE10>0,"Partial","Pending")))) | CK10: =IF($A10="","",SUMIFS('Consumable Usage'!$E:$E,'Consumable Usage'!$A:$A,$A10,'Consumable Usage'!$D:$D,9)) -> 0 | CL10: =IF($A10="","",SUMIFS('Nursing Charges'!$I:$I,'Nursing Charges'!$A:$A,$A10,'Nursing Charges'!$C:$C,9)) -> 0 | CM10: =IF($A10="","",CJ10+(CL10-SUMIFS('Nursing Charges'!$J:$J,'Nursing Charges'!$A:$A,$A10,'Nursing Charges'!$C:$C,9))+(CK10-SUMIFS('Consumable Usage'!$F:$F,'Consumable Usage'!$A:$A,$A10,'Consumable Usage'!$D:$D,9))) -> 0 | CN10: =IF($A10="","",CJ10+CL10+CK10) -> 0 | CP10: =IF(CN10="","",CN10-CO10) -> 0 | CQ10: =IF(OR($A10="",CH10=""),"",IF(CN10=0,"No Charges",IF(CP10<=0,"Paid",IF(CO10>0,"Partial","Pending")))) | CU10: =IF($A10="","",SUMIFS('Consumable Usage'!$E:$E,'Consumable Usage'!$A:$A,$A10,'Consumable Usage'!$D:$D,10)) -> 0 | CV10: =IF($A10="","",SUMIFS('Nursing Charges'!$I:$I,'Nursing Charges'!$A:$A,$A10,'Nursing Charges'!$C:$C,10)) -> 0 | CW10: =IF($A10="","",CT10+(CV10-SUMIFS('Nursing Charges'!$J:$J,'Nursing Charges'!$A:$A,$A10,'Nursing Charges'!$C:$C,10))+(CU10-SUMIFS('Consumable Usage'!$F:$F,'Consumable Usage'!$A:$A,$A10,'Consumable Usage'!$D:$D,10))) -> 0 | CX10: =IF($A10="","",CT10+CV10+CU10) -> 0 | CZ10: =IF(CX10="","",CX10-CY10) -> 0 | DA10: =IF(OR($A10="",CR10=""),"",IF(CX10=0,"No Charges",IF(CZ10<=0,"Paid",IF(CY10>0,"Partial","Pending")))) | DE10: =IF($A10="","",SUMIFS('Consumable Usage'!$E:$E,'Consumable Usage'!$A:$A,$A10,'Consumable Usage'!$D:$D,11)) -> 0 | DF10: =IF($A10="","",SUMIFS('Nursing Charges'!$I:$I,'Nursing Charges'!$A:$A,$A10,'Nursing Charges'!$C:$C,11)) -> 0 | DG10: =IF($A10="","",DD10+(DF10-SUMIFS('Nursing Charges'!$J:$J,'Nursing Charges'!$A:$A,$A10,'Nursing Charges'!$C:$C,11))+(DE10-SUMIFS('Consumable Usage'!$F:$F,'Consumable Usage'!$A:$A,$A10,'Consumable Usage'!$D:$D,11))) -> 0 | DH10: =IF($A10="","",DD10+DF10+DE10) -> 0 | DJ10: =IF(DH10="","",DH10-DI10) -> 0 | DK10: =IF(OR($A10="",DB10=""),"",IF(DH10=0,"No Charges",IF(DJ10<=0,"Paid",IF(DI10>0,"Partial","Pending")))) | DO10: =IF($A10="","",SUMIFS('Consumable Usage'!$E:$E,'Consumable Usage'!$A:$A,$A10,'Consumable Usage'!$D:$D,12)) -> 0 | DP10: =IF($A10="","",SUMIFS('Nursing Charges'!$I:$I,'Nursing Charges'!$A:$A,$A10,'Nursing Charges'!$C:$C,12)) -> 0 | DQ10: =IF($A10="","",DN10+(DP10-SUMIFS('Nursing Charges'!$J:$J,'Nursing Charges'!$A:$A,$A10,'Nursing Charges'!$C:$C,12))+(DO10-SUMIFS('Consumable Usage'!$F:$F,'Consumable Usage'!$A:$A,$A10,'Consumable Usage'!$D:$D,12))) -> 0 | DR10: =IF($A10="","",DN10+DP10+DO10) -> 0 | DT10: =IF(DR10="","",DR10-DS10) -> 0 | DU10: =IF(OR($A10="",DL10=""),"",IF(DR10=0,"No Charges",IF(DT10<=0,"Paid",IF(DS10>0,"Partial","Pending")))) | DY10: =IF($A10="","",SUMIFS('Consumable Usage'!$E:$E,'Consumable Usage'!$A:$A,$A10,'Consumable Usage'!$D:$D,13)) -> 0 | DZ10: =IF($A10="","",SUMIFS('Nursing Charges'!$I:$I,'Nursing Charges'!$A:$A,$A10,'Nursing Charges'!$C:$C,13)) -> 0 | EA10: =IF($A10="","",DX10+(DZ10-SUMIFS('Nursing Charges'!$J:$J,'Nursing Charges'!$A:$A,$A10,'Nursing Charges'!$C:$C,13))+(DY10-SUMIFS('Consumable Usage'!$F:$F,'Consumable Usage'!$A:$A,$A10,'Consumable Usage'!$D:$D,13))) -> 0 | EB10: =IF($A10="","",DX10+DZ10+DY10) -> 0 | ED10: =IF(EB10="","",EB10-EC10) -> 0 | EE10: =IF(OR($A10="",DV10=""),"",IF(EB10=0,"No Charges",IF(ED10<=0,"Paid",IF(EC10>0,"Partial","Pending")))) | EI10: =IF($A10="","",SUMIFS('Consumable Usage'!$E:$E,'Consumable Usage'!$A:$A,$A10,'Consumable Usage'!$D:$D,14)) -> 0 | EJ10: =IF($A10="","",SUMIFS('Nursing Charges'!$I:$I,'Nursing Charges'!$A:$A,$A10,'Nursing Charges'!$C:$C,14)) -> 0 | EK10: =IF($A10="","",EH10+(EJ10-SUMIFS('Nursing Charges'!$J:$J,'Nursing Charges'!$A:$A,$A10,'Nursing Charges'!$C:$C,14))+(EI10-SUMIFS('Consumable Usage'!$F:$F,'Consumable Usage'!$A:$A,$A10,'Consumable Usage'!$D:$D,14))) -> 0 | EL10: =IF($A10="","",EH10+EJ10+EI10) -> 0 | EN10: =IF(EL10="","",EL10-EM10) -> 0 | EO10: =IF(OR($A10="",EF10=""),"",IF(EL10=0,"No Charges",IF(EN10<=0,"Paid",IF(EM10>0,"Partial","Pending")))) | ES10: =IF($A10="","",SUMIFS('Consumable Usage'!$E:$E,'Consumable Usage'!$A:$A,$A10,'Consumable Usage'!$D:$D,15)) -> 0 | ET10: =IF($A10="","",SUMIFS('Nursing Charges'!$I:$I,'Nursing Charges'!$A:$A,$A10,'Nursing Charges'!$C:$C,15)) -> 0 | EU10: =IF($A10="","",ER10+(ET10-SUMIFS('Nursing Charges'!$J:$J,'Nursing Charges'!$A:$A,$A10,'Nursing Charges'!$C:$C,15))+(ES10-SUMIFS('Consumable Usage'!$F:$F,'Consumable Usage'!$A:$A,$A10,'Consumable Usage'!$D:$D,15))) -> 0 | EV10: =IF($A10="","",ER10+ET10+ES10) -> 0 | EX10: =IF(EV10="","",EV10-EW10) -> 0 | EY10: =IF(OR($A10="",EP10=""),"",IF(EV10=0,"No Charges",IF(EX10<=0,"Paid",IF(EW10>0,"Partial","Pending")))) | FC10: =IF($A10="","",SUMIFS('Consumable Usage'!$E:$E,'Consumable Usage'!$A:$A,$A10,'Consumable Usage'!$D:$D,16)) -> 0 | FD10: =IF($A10="","",SUMIFS('Nursing Charges'!$I:$I,'Nursing Charges'!$A:$A,$A10,'Nursing Charges'!$C:$C,16)) -> 0 | FE10: =IF($A10="","",FB10+(FD10-SUMIFS('Nursing Charges'!$J:$J,'Nursing Charges'!$A:$A,$A10,'Nursing Charges'!$C:$C,16))+(FC10-SUMIFS('Consumable Usage'!$F:$F,'Consumable Usage'!$A:$A,$A10,'Consumable Usage'!$D:$D,16))) -> 0 | FF10: =IF($A10="","",FB10+FD10+FC10) -> 0 | FH10: =IF(FF10="","",FF10-FG10) -> 0 | FI10: =IF(OR($A10="",EZ10=""),"",IF(FF10=0,"No Charges",IF(FH10<=0,"Paid",IF(FG10>0,"Partial","Pending")))) | FM10: =IF($A10="","",SUMIFS('Consumable Usage'!$E:$E,'Consumable Usage'!$A:$A,$A10,'Consumable Usage'!$D:$D,16)) -> 0 | FN10: =IF($A10="","",SUMIFS('Nursing Charges'!$I:$I,'Nursing Charges'!$A:$A,$A10,'Nursing Charges'!$C:$C,16)) -> 0 | FO10: =IF($A10="","",FL10+(FN10-SUMIFS('Nursing Charges'!$J:$J,'Nursing Charges'!$A:$A,$A10,'Nursing Charges'!$C:$C,16))+(FM10-SUMIFS('Consumable Usage'!$F:$F,'Consumable Usage'!$A:$A,$A10,'Consumable Usage'!$D:$D,16))) -> 0 | FP10: =IF($A10="","",FL10+FN10+FM10) -> 0 | FR10: =IF(FP10="","",FP10-FQ10) -> 0 | FS10: =IF(OR($A10="",FJ10=""),"",IF(FP10=0,"No Charges",IF(FR10<=0,"Paid",IF(FQ10>0,"Partial","Pending"))))
A11: CC2026006 | B11: Vina Pawar | C11: TANYA | D11: 70454 59692 | E11: so the patient has mentioned thatt their 6 rounds of chemo is over and the next one wil be on september and not on 12th aug we need confirmation from dr darshit | I11: =IF($A11="","",SUMIFS('Consumable Usage'!$E:$E,'Consumable Usage'!$A:$A,$A11,'Consumable Usage'!$D:$D,1)) -> 0 | J11: =IF($A11="","",SUMIFS('Nursing Charges'!$I:$I,'Nursing Charges'!$A:$A,$A11,'Nursing Charges'!$C:$C,1)) -> 0 | K11: =IF($A11="","",H11+(J11-SUMIFS('Nursing Charges'!$J:$J,'Nursing Charges'!$A:$A,$A11,'Nursing Charges'!$C:$C,1))+(I11-SUMIFS('Consumable Usage'!$F:$F,'Consumable Usage'!$A:$A,$A11,'Consumable Usage'!$D:$D,1))) -> 0 | L11: =IF($A11="","",H11+J11+I11) -> 0 | N11: =IF(L11="","",L11-M11) -> 0 | O11: =IF(OR($A11="",F11=""),"",IF(L11=0,"No Charges",IF(N11<=0,"Paid",IF(M11>0,"Partial","Pending")))) | S11: =IF($A11="","",SUMIFS('Consumable Usage'!$E:$E,'Consumable Usage'!$A:$A,$A11,'Consumable Usage'!$D:$D,2)) -> 0 | T11: =IF($A11="","",SUMIFS('Nursing Charges'!$I:$I,'Nursing Charges'!$A:$A,$A11,'Nursing Charges'!$C:$C,2)) -> 0 | U11: =IF($A11="","",R11+(T11-SUMIFS('Nursing Charges'!$J:$J,'Nursing Charges'!$A:$A,$A11,'Nursing Charges'!$C:$C,2))+(S11-SUMIFS('Consumable Usage'!$F:$F,'Consumable Usage'!$A:$A,$A11,'Consumable Usage'!$D:$D,2))) -> 0 | V11: =IF($A11="","",R11+T11+S11) -> 0 | X11: =IF(V11="","",V11-W11) -> 0 | Y11: =IF(OR($A11="",P11=""),"",IF(V11=0,"No Charges",IF(X11<=0,"Paid",IF(W11>0,"Partial","Pending")))) | AC11: =IF($A11="","",SUMIFS('Consumable Usage'!$E:$E,'Consumable Usage'!$A:$A,$A11,'Consumable Usage'!$D:$D,3)) -> 0 | AD11: =IF($A11="","",SUMIFS('Nursing Charges'!$I:$I,'Nursing Charges'!$A:$A,$A11,'Nursing Charges'!$C:$C,3)) -> 0 | AE11: =IF($A11="","",AB11+(AD11-SUMIFS('Nursing Charges'!$J:$J,'Nursing Charges'!$A:$A,$A11,'Nursing Charges'!$C:$C,3))+(AC11-SUMIFS('Consumable Usage'!$F:$F,'Consumable Usage'!$A:$A,$A11,'Consumable Usage'!$D:$D,3))) -> 0 | AF11: =IF($A11="","",AB11+AD11+AC11) -> 0 | AH11: =IF(AF11="","",AF11-AG11) -> 0 | AI11: =IF(OR($A11="",Z11=""),"",IF(AF11=0,"No Charges",IF(AH11<=0,"Paid",IF(AG11>0,"Partial","Pending")))) | AM11: =IF($A11="","",SUMIFS('Consumable Usage'!$E:$E,'Consumable Usage'!$A:$A,$A11,'Consumable Usage'!$D:$D,4)) -> 0 | AN11: =IF($A11="","",SUMIFS('Nursing Charges'!$I:$I,'Nursing Charges'!$A:$A,$A11,'Nursing Charges'!$C:$C,4)) -> 0 | AO11: =IF($A11="","",AL11+(AN11-SUMIFS('Nursing Charges'!$J:$J,'Nursing Charges'!$A:$A,$A11,'Nursing Charges'!$C:$C,4))+(AM11-SUMIFS('Consumable Usage'!$F:$F,'Consumable Usage'!$A:$A,$A11,'Consumable Usage'!$D:$D,4))) -> 0 | AP11: =IF($A11="","",AL11+AN11+AM11) -> 0 | AR11: =IF(AP11="","",AP11-AQ11) -> 0 | AS11: =IF(OR($A11="",AJ11=""),"",IF(AP11=0,"No Charges",IF(AR11<=0,"Paid",IF(AQ11>0,"Partial","Pending")))) | AW11: =IF($A11="","",SUMIFS('Consumable Usage'!$E:$E,'Consumable Usage'!$A:$A,$A11,'Consumable Usage'!$D:$D,5)) -> 0 | AX11: =IF($A11="","",SUMIFS('Nursing Charges'!$I:$I,'Nursing Charges'!$A:$A,$A11,'Nursing Charges'!$C:$C,5)) -> 0 | AY11: =IF($A11="","",AV11+(AX11-SUMIFS('Nursing Charges'!$J:$J,'Nursing Charges'!$A:$A,$A11,'Nursing Charges'!$C:$C,5))+(AW11-SUMIFS('Consumable Usage'!$F:$F,'Consumable Usage'!$A:$A,$A11,'Consumable Usage'!$D:$D,5))) -> 0 | AZ11: =IF($A11="","",AV11+AX11+AW11) -> 0 | BB11: =IF(AZ11="","",AZ11-BA11) -> 0 | BC11: =IF(OR($A11="",AT11=""),"",IF(AZ11=0,"No Charges",IF(BB11<=0,"Paid",IF(BA11>0,"Partial","Pending")))) | BG11: =IF($A11="","",SUMIFS('Consumable Usage'!$E:$E,'Consumable Usage'!$A:$A,$A11,'Consumable Usage'!$D:$D,6)) -> 0 | BH11: =IF($A11="","",SUMIFS('Nursing Charges'!$I:$I,'Nursing Charges'!$A:$A,$A11,'Nursing Charges'!$C:$C,6)) -> 0 | BI11: =IF($A11="","",BF11+(BH11-SUMIFS('Nursing Charges'!$J:$J,'Nursing Charges'!$A:$A,$A11,'Nursing Charges'!$C:$C,6))+(BG11-SUMIFS('Consumable Usage'!$F:$F,'Consumable Usage'!$A:$A,$A11,'Consumable Usage'!$D:$D,6))) -> 0 | BJ11: =IF($A11="","",BF11+BH11+BG11) -> 0 | BL11: =IF(BJ11="","",BJ11-BK11) -> 0 | BM11: =IF(OR($A11="",BD11=""),"",IF(BJ11=0,"No Charges",IF(BL11<=0,"Paid",IF(BK11>0,"Partial","Pending")))) | BQ11: =IF($A11="","",SUMIFS('Consumable Usage'!$E:$E,'Consumable Usage'!$A:$A,$A11,'Consumable Usage'!$D:$D,7)) -> 0 | BR11: =IF($A11="","",SUMIFS('Nursing Charges'!$I:$I,'Nursing Charges'!$A:$A,$A11,'Nursing Charges'!$C:$C,7)) -> 0 | BS11: =IF($A11="","",BP11+(BR11-SUMIFS('Nursing Charges'!$J:$J,'Nursing Charges'!$A:$A,$A11,'Nursing Charges'!$C:$C,7))+(BQ11-SUMIFS('Consumable Usage'!$F:$F,'Consumable Usage'!$A:$A,$A11,'Consumable Usage'!$D:$D,7))) -> 0 | BT11: =IF($A11="","",BP11+BR11+BQ11) -> 0 | BV11: =IF(BT11="","",BT11-BU11) -> 0 | BW11: =IF(OR($A11="",BN11=""),"",IF(BT11=0,"No Charges",IF(BV11<=0,"Paid",IF(BU11>0,"Partial","Pending")))) | CA11: =IF($A11="","",SUMIFS('Consumable Usage'!$E:$E,'Consumable Usage'!$A:$A,$A11,'Consumable Usage'!$D:$D,8)) -> 0 | CB11: =IF($A11="","",SUMIFS('Nursing Charges'!$I:$I,'Nursing Charges'!$A:$A,$A11,'Nursing Charges'!$C:$C,8)) -> 0 | CC11: =IF($A11="","",BZ11+(CB11-SUMIFS('Nursing Charges'!$J:$J,'Nursing Charges'!$A:$A,$A11,'Nursing Charges'!$C:$C,8))+(CA11-SUMIFS('Consumable Usage'!$F:$F,'Consumable Usage'!$A:$A,$A11,'Consumable Usage'!$D:$D,8))) -> 0 | CD11: =IF($A11="","",BZ11+CB11+CA11) -> 0 | CF11: =IF(CD11="","",CD11-CE11) -> 0 | CG11: =IF(OR($A11="",BX11=""),"",IF(CD11=0,"No Charges",IF(CF11<=0,"Paid",IF(CE11>0,"Partial","Pending")))) | CK11: =IF($A11="","",SUMIFS('Consumable Usage'!$E:$E,'Consumable Usage'!$A:$A,$A11,'Consumable Usage'!$D:$D,9)) -> 0 | CL11: =IF($A11="","",SUMIFS('Nursing Charges'!$I:$I,'Nursing Charges'!$A:$A,$A11,'Nursing Charges'!$C:$C,9)) -> 0 | CM11: =IF($A11="","",CJ11+(CL11-SUMIFS('Nursing Charges'!$J:$J,'Nursing Charges'!$A:$A,$A11,'Nursing Charges'!$C:$C,9))+(CK11-SUMIFS('Consumable Usage'!$F:$F,'Consumable Usage'!$A:$A,$A11,'Consumable Usage'!$D:$D,9))) -> 0 | CN11: =IF($A11="","",CJ11+CL11+CK11) -> 0 | CP11: =IF(CN11="","",CN11-CO11) -> 0 | CQ11: =IF(OR($A11="",CH11=""),"",IF(CN11=0,"No Charges",IF(CP11<=0,"Paid",IF(CO11>0,"Partial","Pending")))) | CU11: =IF($A11="","",SUMIFS('Consumable Usage'!$E:$E,'Consumable Usage'!$A:$A,$A11,'Consumable Usage'!$D:$D,10)) -> 0 | CV11: =IF($A11="","",SUMIFS('Nursing Charges'!$I:$I,'Nursing Charges'!$A:$A,$A11,'Nursing Charges'!$C:$C,10)) -> 0 | CW11: =IF($A11="","",CT11+(CV11-SUMIFS('Nursing Charges'!$J:$J,'Nursing Charges'!$A:$A,$A11,'Nursing Charges'!$C:$C,10))+(CU11-SUMIFS('Consumable Usage'!$F:$F,'Consumable Usage'!$A:$A,$A11,'Consumable Usage'!$D:$D,10))) -> 0 | CX11: =IF($A11="","",CT11+CV11+CU11) -> 0 | CZ11: =IF(CX11="","",CX11-CY11) -> 0 | DA11: =IF(OR($A11="",CR11=""),"",IF(CX11=0,"No Charges",IF(CZ11<=0,"Paid",IF(CY11>0,"Partial","Pending")))) | DE11: =IF($A11="","",SUMIFS('Consumable Usage'!$E:$E,'Consumable Usage'!$A:$A,$A11,'Consumable Usage'!$D:$D,11)) -> 0 | DF11: =IF($A11="","",SUMIFS('Nursing Charges'!$I:$I,'Nursing Charges'!$A:$A,$A11,'Nursing Charges'!$C:$C,11)) -> 0 | DG11: =IF($A11="","",DD11+(DF11-SUMIFS('Nursing Charges'!$J:$J,'Nursing Charges'!$A:$A,$A11,'Nursing Charges'!$C:$C,11))+(DE11-SUMIFS('Consumable Usage'!$F:$F,'Consumable Usage'!$A:$A,$A11,'Consumable Usage'!$D:$D,11))) -> 0 | DH11: =IF($A11="","",DD11+DF11+DE11) -> 0 | DJ11: =IF(DH11="","",DH11-DI11) -> 0 | DK11: =IF(OR($A11="",DB11=""),"",IF(DH11=0,"No Charges",IF(DJ11<=0,"Paid",IF(DI11>0,"Partial","Pending")))) | DO11: =IF($A11="","",SUMIFS('Consumable Usage'!$E:$E,'Consumable Usage'!$A:$A,$A11,'Consumable Usage'!$D:$D,12)) -> 0 | DP11: =IF($A11="","",SUMIFS('Nursing Charges'!$I:$I,'Nursing Charges'!$A:$A,$A11,'Nursing Charges'!$C:$C,12)) -> 0 | DQ11: =IF($A11="","",DN11+(DP11-SUMIFS('Nursing Charges'!$J:$J,'Nursing Charges'!$A:$A,$A11,'Nursing Charges'!$C:$C,12))+(DO11-SUMIFS('Consumable Usage'!$F:$F,'Consumable Usage'!$A:$A,$A11,'Consumable Usage'!$D:$D,12))) -> 0 | DR11: =IF($A11="","",DN11+DP11+DO11) -> 0 | DT11: =IF(DR11="","",DR11-DS11) -> 0 | DU11: =IF(OR($A11="",DL11=""),"",IF(DR11=0,"No Charges",IF(DT11<=0,"Paid",IF(DS11>0,"Partial","Pending")))) | DY11: =IF($A11="","",SUMIFS('Consumable Usage'!$E:$E,'Consumable Usage'!$A:$A,$A11,'Consumable Usage'!$D:$D,13)) -> 0 | DZ11: =IF($A11="","",SUMIFS('Nursing Charges'!$I:$I,'Nursing Charges'!$A:$A,$A11,'Nursing Charges'!$C:$C,13)) -> 0 | EA11: =IF($A11="","",DX11+(DZ11-SUMIFS('Nursing Charges'!$J:$J,'Nursing Charges'!$A:$A,$A11,'Nursing Charges'!$C:$C,13))+(DY11-SUMIFS('Consumable Usage'!$F:$F,'Consumable Usage'!$A:$A,$A11,'Consumable Usage'!$D:$D,13))) -> 0 | EB11: =IF($A11="","",DX11+DZ11+DY11) -> 0 | ED11: =IF(EB11="","",EB11-EC11) -> 0 | EE11: =IF(OR($A11="",DV11=""),"",IF(EB11=0,"No Charges",IF(ED11<=0,"Paid",IF(EC11>0,"Partial","Pending")))) | EI11: =IF($A11="","",SUMIFS('Consumable Usage'!$E:$E,'Consumable Usage'!$A:$A,$A11,'Consumable Usage'!$D:$D,14)) -> 0 | EJ11: =IF($A11="","",SUMIFS('Nursing Charges'!$I:$I,'Nursing Charges'!$A:$A,$A11,'Nursing Charges'!$C:$C,14)) -> 0 | EK11: =IF($A11="","",EH11+(EJ11-SUMIFS('Nursing Charges'!$J:$J,'Nursing Charges'!$A:$A,$A11,'Nursing Charges'!$C:$C,14))+(EI11-SUMIFS('Consumable Usage'!$F:$F,'Consumable Usage'!$A:$A,$A11,'Consumable Usage'!$D:$D,14))) -> 0 | EL11: =IF($A11="","",EH11+EJ11+EI11) -> 0 | EN11: =IF(EL11="","",EL11-EM11) -> 0 | EO11: =IF(OR($A11="",EF11=""),"",IF(EL11=0,"No Charges",IF(EN11<=0,"Paid",IF(EM11>0,"Partial","Pending")))) | ES11: =IF($A11="","",SUMIFS('Consumable Usage'!$E:$E,'Consumable Usage'!$A:$A,$A11,'Consumable Usage'!$D:$D,15)) -> 0 | ET11: =IF($A11="","",SUMIFS('Nursing Charges'!$I:$I,'Nursing Charges'!$A:$A,$A11,'Nursing Charges'!$C:$C,15)) -> 0 | EU11: =IF($A11="","",ER11+(ET11-SUMIFS('Nursing Charges'!$J:$J,'Nursing Charges'!$A:$A,$A11,'Nursing Charges'!$C:$C,15))+(ES11-SUMIFS('Consumable Usage'!$F:$F,'Consumable Usage'!$A:$A,$A11,'Consumable Usage'!$D:$D,15))) -> 0 | EV11: =IF($A11="","",ER11+ET11+ES11) -> 0 | EX11: =IF(EV11="","",EV11-EW11) -> 0 | EY11: =IF(OR($A11="",EP11=""),"",IF(EV11=0,"No Charges",IF(EX11<=0,"Paid",IF(EW11>0,"Partial","Pending")))) | FC11: =IF($A11="","",SUMIFS('Consumable Usage'!$E:$E,'Consumable Usage'!$A:$A,$A11,'Consumable Usage'!$D:$D,16)) -> 0 | FD11: =IF($A11="","",SUMIFS('Nursing Charges'!$I:$I,'Nursing Charges'!$A:$A,$A11,'Nursing Charges'!$C:$C,16)) -> 0 | FE11: =IF($A11="","",FB11+(FD11-SUMIFS('Nursing Charges'!$J:$J,'Nursing Charges'!$A:$A,$A11,'Nursing Charges'!$C:$C,16))+(FC11-SUMIFS('Consumable Usage'!$F:$F,'Consumable Usage'!$A:$A,$A11,'Consumable Usage'!$D:$D,16))) -> 0 | FF11: =IF($A11="","",FB11+FD11+FC11) -> 0 | FH11: =IF(FF11="","",FF11-FG11) -> 0 | FI11: =IF(OR($A11="",EZ11=""),"",IF(FF11=0,"No Charges",IF(FH11<=0,"Paid",IF(FG11>0,"Partial","Pending")))) | FM11: =IF($A11="","",SUMIFS('Consumable Usage'!$E:$E,'Consumable Usage'!$A:$A,$A11,'Consumable Usage'!$D:$D,16)) -> 0 | FN11: =IF($A11="","",SUMIFS('Nursing Charges'!$I:$I,'Nursing Charges'!$A:$A,$A11,'Nursing Charges'!$C:$C,16)) -> 0 | FO11: =IF($A11="","",FL11+(FN11-SUMIFS('Nursing Charges'!$J:$J,'Nursing Charges'!$A:$A,$A11,'Nursing Charges'!$C:$C,16))+(FM11-SUMIFS('Consumable Usage'!$F:$F,'Consumable Usage'!$A:$A,$A11,'Consumable Usage'!$D:$D,16))) -> 0 | FP11: =IF($A11="","",FL11+FN11+FM11) -> 0 | FR11: =IF(FP11="","",FP11-FQ11) -> 0 | FS11: =IF(OR($A11="",FJ11=""),"",IF(FP11=0,"No Charges",IF(FR11<=0,"Paid",IF(FQ11>0,"Partial","Pending"))))
A12: CC2026007 | B12: Kamaladevi Jain | C12: SHOURYA | D12: 98671 44591 | E12: have paid till 10 aug | I12: =IF($A12="","",SUMIFS('Consumable Usage'!$E:$E,'Consumable Usage'!$A:$A,$A12,'Consumable Usage'!$D:$D,1)) -> 0 | J12: =IF($A12="","",SUMIFS('Nursing Charges'!$I:$I,'Nursing Charges'!$A:$A,$A12,'Nursing Charges'!$C:$C,1)) -> 3500 | K12: =IF($A12="","",H12+(J12-SUMIFS('Nursing Charges'!$J:$J,'Nursing Charges'!$A:$A,$A12,'Nursing Charges'!$C:$C,1))+(I12-SUMIFS('Consumable Usage'!$F:$F,'Consumable Usage'!$A:$A,$A12,'Consumable Usage'!$D:$D,1))) -> 3500 | L12: =IF($A12="","",H12+J12+I12) -> 3500 | N12: =IF(L12="","",L12-M12) -> 3500 | O12: =IF(OR($A12="",F12=""),"",IF(L12=0,"No Charges",IF(N12<=0,"Paid",IF(M12>0,"Partial","Pending")))) | S12: =IF($A12="","",SUMIFS('Consumable Usage'!$E:$E,'Consumable Usage'!$A:$A,$A12,'Consumable Usage'!$D:$D,2)) -> 0 | T12: =IF($A12="","",SUMIFS('Nursing Charges'!$I:$I,'Nursing Charges'!$A:$A,$A12,'Nursing Charges'!$C:$C,2)) -> 0 | U12: =IF($A12="","",R12+(T12-SUMIFS('Nursing Charges'!$J:$J,'Nursing Charges'!$A:$A,$A12,'Nursing Charges'!$C:$C,2))+(S12-SUMIFS('Consumable Usage'!$F:$F,'Consumable Usage'!$A:$A,$A12,'Consumable Usage'!$D:$D,2))) -> 0 | V12: =IF($A12="","",R12+T12+S12) -> 0 | X12: =IF(V12="","",V12-W12) -> 0 | Y12: =IF(OR($A12="",P12=""),"",IF(V12=0,"No Charges",IF(X12<=0,"Paid",IF(W12>0,"Partial","Pending")))) | AC12: =IF($A12="","",SUMIFS('Consumable Usage'!$E:$E,'Consumable Usage'!$A:$A,$A12,'Consumable Usage'!$D:$D,3)) -> 0 | AD12: =IF($A12="","",SUMIFS('Nursing Charges'!$I:$I,'Nursing Charges'!$A:$A,$A12,'Nursing Charges'!$C:$C,3)) -> 0 | AE12: =IF($A12="","",AB12+(AD12-SUMIFS('Nursing Charges'!$J:$J,'Nursing Charges'!$A:$A,$A12,'Nursing Charges'!$C:$C,3))+(AC12-SUMIFS('Consumable Usage'!$F:$F,'Consumable Usage'!$A:$A,$A12,'Consumable Usage'!$D:$D,3))) -> 0 | AF12: =IF($A12="","",AB12+AD12+AC12) -> 0 | AH12: =IF(AF12="","",AF12-AG12) -> 0 | AI12: =IF(OR($A12="",Z12=""),"",IF(AF12=0,"No Charges",IF(AH12<=0,"Paid",IF(AG12>0,"Partial","Pending")))) | AM12: =IF($A12="","",SUMIFS('Consumable Usage'!$E:$E,'Consumable Usage'!$A:$A,$A12,'Consumable Usage'!$D:$D,4)) -> 0 | AN12: =IF($A12="","",SUMIFS('Nursing Charges'!$I:$I,'Nursing Charges'!$A:$A,$A12,'Nursing Charges'!$C:$C,4)) -> 0 | AO12: =IF($A12="","",AL12+(AN12-SUMIFS('Nursing Charges'!$J:$J,'Nursing Charges'!$A:$A,$A12,'Nursing Charges'!$C:$C,4))+(AM12-SUMIFS('Consumable Usage'!$F:$F,'Consumable Usage'!$A:$A,$A12,'Consumable Usage'!$D:$D,4))) -> 0 | AP12: =IF($A12="","",AL12+AN12+AM12) -> 0 | AR12: =IF(AP12="","",AP12-AQ12) -> 0 | AS12: =IF(OR($A12="",AJ12=""),"",IF(AP12=0,"No Charges",IF(AR12<=0,"Paid",IF(AQ12>0,"Partial","Pending")))) | AW12: =IF($A12="","",SUMIFS('Consumable Usage'!$E:$E,'Consumable Usage'!$A:$A,$A12,'Consumable Usage'!$D:$D,5)) -> 0 | AX12: =IF($A12="","",SUMIFS('Nursing Charges'!$I:$I,'Nursing Charges'!$A:$A,$A12,'Nursing Charges'!$C:$C,5)) -> 0 | AY12: =IF($A12="","",AV12+(AX12-SUMIFS('Nursing Charges'!$J:$J,'Nursing Charges'!$A:$A,$A12,'Nursing Charges'!$C:$C,5))+(AW12-SUMIFS('Consumable Usage'!$F:$F,'Consumable Usage'!$A:$A,$A12,'Consumable Usage'!$D:$D,5))) -> 0 | AZ12: =IF($A12="","",AV12+AX12+AW12) -> 0 | BB12: =IF(AZ12="","",AZ12-BA12) -> 0 | BC12: =IF(OR($A12="",AT12=""),"",IF(AZ12=0,"No Charges",IF(BB12<=0,"Paid",IF(BA12>0,"Partial","Pending")))) | BG12: =IF($A12="","",SUMIFS('Consumable Usage'!$E:$E,'Consumable Usage'!$A:$A,$A12,'Consumable Usage'!$D:$D,6)) -> 0 | BH12: =IF($A12="","",SUMIFS('Nursing Charges'!$I:$I,'Nursing Charges'!$A:$A,$A12,'Nursing Charges'!$C:$C,6)) -> 0 | BI12: =IF($A12="","",BF12+(BH12-SUMIFS('Nursing Charges'!$J:$J,'Nursing Charges'!$A:$A,$A12,'Nursing Charges'!$C:$C,6))+(BG12-SUMIFS('Consumable Usage'!$F:$F,'Consumable Usage'!$A:$A,$A12,'Consumable Usage'!$D:$D,6))) -> 0 | BJ12: =IF($A12="","",BF12+BH12+BG12) -> 0 | BL12: =IF(BJ12="","",BJ12-BK12) -> 0 | BM12: =IF(OR($A12="",BD12=""),"",IF(BJ12=0,"No Charges",IF(BL12<=0,"Paid",IF(BK12>0,"Partial","Pending")))) | BQ12: =IF($A12="","",SUMIFS('Consumable Usage'!$E:$E,'Consumable Usage'!$A:$A,$A12,'Consumable Usage'!$D:$D,7)) -> 0 | BR12: =IF($A12="","",SUMIFS('Nursing Charges'!$I:$I,'Nursing Charges'!$A:$A,$A12,'Nursing Charges'!$C:$C,7)) -> 0 | BS12: =IF($A12="","",BP12+(BR12-SUMIFS('Nursing Charges'!$J:$J,'Nursing Charges'!$A:$A,$A12,'Nursing Charges'!$C:$C,7))+(BQ12-SUMIFS('Consumable Usage'!$F:$F,'Consumable Usage'!$A:$A,$A12,'Consumable Usage'!$D:$D,7))) -> 0 | BT12: =IF($A12="","",BP12+BR12+BQ12) -> 0 | BV12: =IF(BT12="","",BT12-BU12) -> 0 | BW12: =IF(OR($A12="",BN12=""),"",IF(BT12=0,"No Charges",IF(BV12<=0,"Paid",IF(BU12>0,"Partial","Pending")))) | CA12: =IF($A12="","",SUMIFS('Consumable Usage'!$E:$E,'Consumable Usage'!$A:$A,$A12,'Consumable Usage'!$D:$D,8)) -> 0 | CB12: =IF($A12="","",SUMIFS('Nursing Charges'!$I:$I,'Nursing Charges'!$A:$A,$A12,'Nursing Charges'!$C:$C,8)) -> 0 | CC12: =IF($A12="","",BZ12+(CB12-SUMIFS('Nursing Charges'!$J:$J,'Nursing Charges'!$A:$A,$A12,'Nursing Charges'!$C:$C,8))+(CA12-SUMIFS('Consumable Usage'!$F:$F,'Consumable Usage'!$A:$A,$A12,'Consumable Usage'!$D:$D,8))) -> 0 | CD12: =IF($A12="","",BZ12+CB12+CA12) -> 0 | CF12: =IF(CD12="","",CD12-CE12) -> 0 | CG12: =IF(OR($A12="",BX12=""),"",IF(CD12=0,"No Charges",IF(CF12<=0,"Paid",IF(CE12>0,"Partial","Pending")))) | CK12: =IF($A12="","",SUMIFS('Consumable Usage'!$E:$E,'Consumable Usage'!$A:$A,$A12,'Consumable Usage'!$D:$D,9)) -> 0 | CL12: =IF($A12="","",SUMIFS('Nursing Charges'!$I:$I,'Nursing Charges'!$A:$A,$A12,'Nursing Charges'!$C:$C,9)) -> 0 | CM12: =IF($A12="","",CJ12+(CL12-SUMIFS('Nursing Charges'!$J:$J,'Nursing Charges'!$A:$A,$A12,'Nursing Charges'!$C:$C,9))+(CK12-SUMIFS('Consumable Usage'!$F:$F,'Consumable Usage'!$A:$A,$A12,'Consumable Usage'!$D:$D,9))) -> 0 | CN12: =IF($A12="","",CJ12+CL12+CK12) -> 0 | CP12: =IF(CN12="","",CN12-CO12) -> 0 | CQ12: =IF(OR($A12="",CH12=""),"",IF(CN12=0,"No Charges",IF(CP12<=0,"Paid",IF(CO12>0,"Partial","Pending")))) | CU12: =IF($A12="","",SUMIFS('Consumable Usage'!$E:$E,'Consumable Usage'!$A:$A,$A12,'Consumable Usage'!$D:$D,10)) -> 0 | CV12: =IF($A12="","",SUMIFS('Nursing Charges'!$I:$I,'Nursing Charges'!$A:$A,$A12,'Nursing Charges'!$C:$C,10)) -> 0 | CW12: =IF($A12="","",CT12+(CV12-SUMIFS('Nursing Charges'!$J:$J,'Nursing Charges'!$A:$A,$A12,'Nursing Charges'!$C:$C,10))+(CU12-SUMIFS('Consumable Usage'!$F:$F,'Consumable Usage'!$A:$A,$A12,'Consumable Usage'!$D:$D,10))) -> 0 | CX12: =IF($A12="","",CT12+CV12+CU12) -> 0 | CZ12: =IF(CX12="","",CX12-CY12) -> 0 | DA12: =IF(OR($A12="",CR12=""),"",IF(CX12=0,"No Charges",IF(CZ12<=0,"Paid",IF(CY12>0,"Partial","Pending")))) | DE12: =IF($A12="","",SUMIFS('Consumable Usage'!$E:$E,'Consumable Usage'!$A:$A,$A12,'Consumable Usage'!$D:$D,11)) -> 0 | DF12: =IF($A12="","",SUMIFS('Nursing Charges'!$I:$I,'Nursing Charges'!$A:$A,$A12,'Nursing Charges'!$C:$C,11)) -> 0 | DG12: =IF($A12="","",DD12+(DF12-SUMIFS('Nursing Charges'!$J:$J,'Nursing Charges'!$A:$A,$A12,'Nursing Charges'!$C:$C,11))+(DE12-SUMIFS('Consumable Usage'!$F:$F,'Consumable Usage'!$A:$A,$A12,'Consumable Usage'!$D:$D,11))) -> 0 | DH12: =IF($A12="","",DD12+DF12+DE12) -> 0 | DJ12: =IF(DH12="","",DH12-DI12) -> 0 | DK12: =IF(OR($A12="",DB12=""),"",IF(DH12=0,"No Charges",IF(DJ12<=0,"Paid",IF(DI12>0,"Partial","Pending")))) | DO12: =IF($A12="","",SUMIFS('Consumable Usage'!$E:$E,'Consumable Usage'!$A:$A,$A12,'Consumable Usage'!$D:$D,12)) -> 0 | DP12: =IF($A12="","",SUMIFS('Nursing Charges'!$I:$I,'Nursing Charges'!$A:$A,$A12,'Nursing Charges'!$C:$C,12)) -> 0 | DQ12: =IF($A12="","",DN12+(DP12-SUMIFS('Nursing Charges'!$J:$J,'Nursing Charges'!$A:$A,$A12,'Nursing Charges'!$C:$C,12))+(DO12-SUMIFS('Consumable Usage'!$F:$F,'Consumable Usage'!$A:$A,$A12,'Consumable Usage'!$D:$D,12))) -> 0 | DR12: =IF($A12="","",DN12+DP12+DO12) -> 0 | DT12: =IF(DR12="","",DR12-DS12) -> 0 | DU12: =IF(OR($A12="",DL12=""),"",IF(DR12=0,"No Charges",IF(DT12<=0,"Paid",IF(DS12>0,"Partial","Pending")))) | DY12: =IF($A12="","",SUMIFS('Consumable Usage'!$E:$E,'Consumable Usage'!$A:$A,$A12,'Consumable Usage'!$D:$D,13)) -> 0 | DZ12: =IF($A12="","",SUMIFS('Nursing Charges'!$I:$I,'Nursing Charges'!$A:$A,$A12,'Nursing Charges'!$C:$C,13)) -> 0 | EA12: =IF($A12="","",DX12+(DZ12-SUMIFS('Nursing Charges'!$J:$J,'Nursing Charges'!$A:$A,$A12,'Nursing Charges'!$C:$C,13))+(DY12-SUMIFS('Consumable Usage'!$F:$F,'Consumable Usage'!$A:$A,$A12,'Consumable Usage'!$D:$D,13))) -> 0 | EB12: =IF($A12="","",DX12+DZ12+DY12) -> 0 | ED12: =IF(EB12="","",EB12-EC12) -> 0 | EE12: =IF(OR($A12="",DV12=""),"",IF(EB12=0,"No Charges",IF(ED12<=0,"Paid",IF(EC12>0,"Partial","Pending")))) | EI12: =IF($A12="","",SUMIFS('Consumable Usage'!$E:$E,'Consumable Usage'!$A:$A,$A12,'Consumable Usage'!$D:$D,14)) -> 0 | EJ12: =IF($A12="","",SUMIFS('Nursing Charges'!$I:$I,'Nursing Charges'!$A:$A,$A12,'Nursing Charges'!$C:$C,14)) -> 0 | EK12: =IF($A12="","",EH12+(EJ12-SUMIFS('Nursing Charges'!$J:$J,'Nursing Charges'!$A:$A,$A12,'Nursing Charges'!$C:$C,14))+(EI12-SUMIFS('Consumable Usage'!$F:$F,'Consumable Usage'!$A:$A,$A12,'Consumable Usage'!$D:$D,14))) -> 0 | EL12: =IF($A12="","",EH12+EJ12+EI12) -> 0 | EN12: =IF(EL12="","",EL12-EM12) -> 0 | EO12: =IF(OR($A12="",EF12=""),"",IF(EL12=0,"No Charges",IF(EN12<=0,"Paid",IF(EM12>0,"Partial","Pending")))) | ES12: =IF($A12="","",SUMIFS('Consumable Usage'!$E:$E,'Consumable Usage'!$A:$A,$A12,'Consumable Usage'!$D:$D,15)) -> 0 | ET12: =IF($A12="","",SUMIFS('Nursing Charges'!$I:$I,'Nursing Charges'!$A:$A,$A12,'Nursing Charges'!$C:$C,15)) -> 0 | EU12: =IF($A12="","",ER12+(ET12-SUMIFS('Nursing Charges'!$J:$J,'Nursing Charges'!$A:$A,$A12,'Nursing Charges'!$C:$C,15))+(ES12-SUMIFS('Consumable Usage'!$F:$F,'Consumable Usage'!$A:$A,$A12,'Consumable Usage'!$D:$D,15))) -> 0 | EV12: =IF($A12="","",ER12+ET12+ES12) -> 0 | EX12: =IF(EV12="","",EV12-EW12) -> 0 | EY12: =IF(OR($A12="",EP12=""),"",IF(EV12=0,"No Charges",IF(EX12<=0,"Paid",IF(EW12>0,"Partial","Pending")))) | FC12: =IF($A12="","",SUMIFS('Consumable Usage'!$E:$E,'Consumable Usage'!$A:$A,$A12,'Consumable Usage'!$D:$D,16)) -> 0 | FD12: =IF($A12="","",SUMIFS('Nursing Charges'!$I:$I,'Nursing Charges'!$A:$A,$A12,'Nursing Charges'!$C:$C,16)) -> 0 | FE12: =IF($A12="","",FB12+(FD12-SUMIFS('Nursing Charges'!$J:$J,'Nursing Charges'!$A:$A,$A12,'Nursing Charges'!$C:$C,16))+(FC12-SUMIFS('Consumable Usage'!$F:$F,'Consumable Usage'!$A:$A,$A12,'Consumable Usage'!$D:$D,16))) -> 0 | FF12: =IF($A12="","",FB12+FD12+FC12) -> 0 | FH12: =IF(FF12="","",FF12-FG12) -> 0 | FI12: =IF(OR($A12="",EZ12=""),"",IF(FF12=0,"No Charges",IF(FH12<=0,"Paid",IF(FG12>0,"Partial","Pending")))) | FM12: =IF($A12="","",SUMIFS('Consumable Usage'!$E:$E,'Consumable Usage'!$A:$A,$A12,'Consumable Usage'!$D:$D,16)) -> 0 | FN12: =IF($A12="","",SUMIFS('Nursing Charges'!$I:$I,'Nursing Charges'!$A:$A,$A12,'Nursing Charges'!$C:$C,16)) -> 0 | FO12: =IF($A12="","",FL12+(FN12-SUMIFS('Nursing Charges'!$J:$J,'Nursing Charges'!$A:$A,$A12,'Nursing Charges'!$C:$C,16))+(FM12-SUMIFS('Consumable Usage'!$F:$F,'Consumable Usage'!$A:$A,$A12,'Consumable Usage'!$D:$D,16))) -> 0 | FP12: =IF($A12="","",FL12+FN12+FM12) -> 0 | FR12: =IF(FP12="","",FP12-FQ12) -> 0 | FS12: =IF(OR($A12="",FJ12=""),"",IF(FP12=0,"No Charges",IF(FR12<=0,"Paid",IF(FQ12>0,"Partial","Pending"))))
A13: CC2026008 | B13: Sushila Sarkar | C13: ADYA | D13: 90044 63261 : Dannie | E13: the bill needs to be shared and the next infusion dates | I13: =IF($A13="","",SUMIFS('Consumable Usage'!$E:$E,'Consumable Usage'!$A:$A,$A13,'Consumable Usage'!$D:$D,1)) -> 0 | J13: =IF($A13="","",SUMIFS('Nursing Charges'!$I:$I,'Nursing Charges'!$A:$A,$A13,'Nursing Charges'!$C:$C,1)) -> 0 | K13: =IF($A13="","",H13+(J13-SUMIFS('Nursing Charges'!$J:$J,'Nursing Charges'!$A:$A,$A13,'Nursing Charges'!$C:$C,1))+(I13-SUMIFS('Consumable Usage'!$F:$F,'Consumable Usage'!$A:$A,$A13,'Consumable Usage'!$D:$D,1))) -> 0 | L13: =IF($A13="","",H13+J13+I13) -> 0 | N13: =IF(L13="","",L13-M13) -> 0 | O13: =IF(OR($A13="",F13=""),"",IF(L13=0,"No Charges",IF(N13<=0,"Paid",IF(M13>0,"Partial","Pending")))) | S13: =IF($A13="","",SUMIFS('Consumable Usage'!$E:$E,'Consumable Usage'!$A:$A,$A13,'Consumable Usage'!$D:$D,2)) -> 0 | T13: =IF($A13="","",SUMIFS('Nursing Charges'!$I:$I,'Nursing Charges'!$A:$A,$A13,'Nursing Charges'!$C:$C,2)) -> 0 | U13: =IF($A13="","",R13+(T13-SUMIFS('Nursing Charges'!$J:$J,'Nursing Charges'!$A:$A,$A13,'Nursing Charges'!$C:$C,2))+(S13-SUMIFS('Consumable Usage'!$F:$F,'Consumable Usage'!$A:$A,$A13,'Consumable Usage'!$D:$D,2))) -> 0 | V13: =IF($A13="","",R13+T13+S13) -> 0 | X13: =IF(V13="","",V13-W13) -> 0 | Y13: =IF(OR($A13="",P13=""),"",IF(V13=0,"No Charges",IF(X13<=0,"Paid",IF(W13>0,"Partial","Pending")))) | AC13: =IF($A13="","",SUMIFS('Consumable Usage'!$E:$E,'Consumable Usage'!$A:$A,$A13,'Consumable Usage'!$D:$D,3)) -> 0 | AD13: =IF($A13="","",SUMIFS('Nursing Charges'!$I:$I,'Nursing Charges'!$A:$A,$A13,'Nursing Charges'!$C:$C,3)) -> 0 | AE13: =IF($A13="","",AB13+(AD13-SUMIFS('Nursing Charges'!$J:$J,'Nursing Charges'!$A:$A,$A13,'Nursing Charges'!$C:$C,3))+(AC13-SUMIFS('Consumable Usage'!$F:$F,'Consumable Usage'!$A:$A,$A13,'Consumable Usage'!$D:$D,3))) -> 0 | AF13: =IF($A13="","",AB13+AD13+AC13) -> 0 | AH13: =IF(AF13="","",AF13-AG13) -> 0 | AI13: =IF(OR($A13="",Z13=""),"",IF(AF13=0,"No Charges",IF(AH13<=0,"Paid",IF(AG13>0,"Partial","Pending")))) | AM13: =IF($A13="","",SUMIFS('Consumable Usage'!$E:$E,'Consumable Usage'!$A:$A,$A13,'Consumable Usage'!$D:$D,4)) -> 0 | AN13: =IF($A13="","",SUMIFS('Nursing Charges'!$I:$I,'Nursing Charges'!$A:$A,$A13,'Nursing Charges'!$C:$C,4)) -> 0 | AO13: =IF($A13="","",AL13+(AN13-SUMIFS('Nursing Charges'!$J:$J,'Nursing Charges'!$A:$A,$A13,'Nursing Charges'!$C:$C,4))+(AM13-SUMIFS('Consumable Usage'!$F:$F,'Consumable Usage'!$A:$A,$A13,'Consumable Usage'!$D:$D,4))) -> 0 | AP13: =IF($A13="","",AL13+AN13+AM13) -> 0 | AR13: =IF(AP13="","",AP13-AQ13) -> 0 | AS13: =IF(OR($A13="",AJ13=""),"",IF(AP13=0,"No Charges",IF(AR13<=0,"Paid",IF(AQ13>0,"Partial","Pending")))) | AW13: =IF($A13="","",SUMIFS('Consumable Usage'!$E:$E,'Consumable Usage'!$A:$A,$A13,'Consumable Usage'!$D:$D,5)) -> 0 | AX13: =IF($A13="","",SUMIFS('Nursing Charges'!$I:$I,'Nursing Charges'!$A:$A,$A13,'Nursing Charges'!$C:$C,5)) -> 0 | AY13: =IF($A13="","",AV13+(AX13-SUMIFS('Nursing Charges'!$J:$J,'Nursing Charges'!$A:$A,$A13,'Nursing Charges'!$C:$C,5))+(AW13-SUMIFS('Consumable Usage'!$F:$F,'Consumable Usage'!$A:$A,$A13,'Consumable Usage'!$D:$D,5))) -> 0 | AZ13: =IF($A13="","",AV13+AX13+AW13) -> 0 | BB13: =IF(AZ13="","",AZ13-BA13) -> 0 | BC13: =IF(OR($A13="",AT13=""),"",IF(AZ13=0,"No Charges",IF(BB13<=0,"Paid",IF(BA13>0,"Partial","Pending")))) | BG13: =IF($A13="","",SUMIFS('Consumable Usage'!$E:$E,'Consumable Usage'!$A:$A,$A13,'Consumable Usage'!$D:$D,6)) -> 0 | BH13: =IF($A13="","",SUMIFS('Nursing Charges'!$I:$I,'Nursing Charges'!$A:$A,$A13,'Nursing Charges'!$C:$C,6)) -> 0 | BI13: =IF($A13="","",BF13+(BH13-SUMIFS('Nursing Charges'!$J:$J,'Nursing Charges'!$A:$A,$A13,'Nursing Charges'!$C:$C,6))+(BG13-SUMIFS('Consumable Usage'!$F:$F,'Consumable Usage'!$A:$A,$A13,'Consumable Usage'!$D:$D,6))) -> 0 | BJ13: =IF($A13="","",BF13+BH13+BG13) -> 0 | BL13: =IF(BJ13="","",BJ13-BK13) -> 0 | BM13: =IF(OR($A13="",BD13=""),"",IF(BJ13=0,"No Charges",IF(BL13<=0,"Paid",IF(BK13>0,"Partial","Pending")))) | BQ13: =IF($A13="","",SUMIFS('Consumable Usage'!$E:$E,'Consumable Usage'!$A:$A,$A13,'Consumable Usage'!$D:$D,7)) -> 0 | BR13: =IF($A13="","",SUMIFS('Nursing Charges'!$I:$I,'Nursing Charges'!$A:$A,$A13,'Nursing Charges'!$C:$C,7)) -> 0 | BS13: =IF($A13="","",BP13+(BR13-SUMIFS('Nursing Charges'!$J:$J,'Nursing Charges'!$A:$A,$A13,'Nursing Charges'!$C:$C,7))+(BQ13-SUMIFS('Consumable Usage'!$F:$F,'Consumable Usage'!$A:$A,$A13,'Consumable Usage'!$D:$D,7))) -> 0 | BT13: =IF($A13="","",BP13+BR13+BQ13) -> 0 | BV13: =IF(BT13="","",BT13-BU13) -> 0 | BW13: =IF(OR($A13="",BN13=""),"",IF(BT13=0,"No Charges",IF(BV13<=0,"Paid",IF(BU13>0,"Partial","Pending")))) | CA13: =IF($A13="","",SUMIFS('Consumable Usage'!$E:$E,'Consumable Usage'!$A:$A,$A13,'Consumable Usage'!$D:$D,8)) -> 0 | CB13: =IF($A13="","",SUMIFS('Nursing Charges'!$I:$I,'Nursing Charges'!$A:$A,$A13,'Nursing Charges'!$C:$C,8)) -> 0 | CC13: =IF($A13="","",BZ13+(CB13-SUMIFS('Nursing Charges'!$J:$J,'Nursing Charges'!$A:$A,$A13,'Nursing Charges'!$C:$C,8))+(CA13-SUMIFS('Consumable Usage'!$F:$F,'Consumable Usage'!$A:$A,$A13,'Consumable Usage'!$D:$D,8))) -> 0 | CD13: =IF($A13="","",BZ13+CB13+CA13) -> 0 | CF13: =IF(CD13="","",CD13-CE13) -> 0 | CG13: =IF(OR($A13="",BX13=""),"",IF(CD13=0,"No Charges",IF(CF13<=0,"Paid",IF(CE13>0,"Partial","Pending")))) | CK13: =IF($A13="","",SUMIFS('Consumable Usage'!$E:$E,'Consumable Usage'!$A:$A,$A13,'Consumable Usage'!$D:$D,9)) -> 0 | CL13: =IF($A13="","",SUMIFS('Nursing Charges'!$I:$I,'Nursing Charges'!$A:$A,$A13,'Nursing Charges'!$C:$C,9)) -> 0 | CM13: =IF($A13="","",CJ13+(CL13-SUMIFS('Nursing Charges'!$J:$J,'Nursing Charges'!$A:$A,$A13,'Nursing Charges'!$C:$C,9))+(CK13-SUMIFS('Consumable Usage'!$F:$F,'Consumable Usage'!$A:$A,$A13,'Consumable Usage'!$D:$D,9))) -> 0 | CN13: =IF($A13="","",CJ13+CL13+CK13) -> 0 | CP13: =IF(CN13="","",CN13-CO13) -> 0 | CQ13: =IF(OR($A13="",CH13=""),"",IF(CN13=0,"No Charges",IF(CP13<=0,"Paid",IF(CO13>0,"Partial","Pending")))) | CU13: =IF($A13="","",SUMIFS('Consumable Usage'!$E:$E,'Consumable Usage'!$A:$A,$A13,'Consumable Usage'!$D:$D,10)) -> 0 | CV13: =IF($A13="","",SUMIFS('Nursing Charges'!$I:$I,'Nursing Charges'!$A:$A,$A13,'Nursing Charges'!$C:$C,10)) -> 0 | CW13: =IF($A13="","",CT13+(CV13-SUMIFS('Nursing Charges'!$J:$J,'Nursing Charges'!$A:$A,$A13,'Nursing Charges'!$C:$C,10))+(CU13-SUMIFS('Consumable Usage'!$F:$F,'Consumable Usage'!$A:$A,$A13,'Consumable Usage'!$D:$D,10))) -> 0 | CX13: =IF($A13="","",CT13+CV13+CU13) -> 0 | CZ13: =IF(CX13="","",CX13-CY13) -> 0 | DA13: =IF(OR($A13="",CR13=""),"",IF(CX13=0,"No Charges",IF(CZ13<=0,"Paid",IF(CY13>0,"Partial","Pending")))) | DE13: =IF($A13="","",SUMIFS('Consumable Usage'!$E:$E,'Consumable Usage'!$A:$A,$A13,'Consumable Usage'!$D:$D,11)) -> 0 | DF13: =IF($A13="","",SUMIFS('Nursing Charges'!$I:$I,'Nursing Charges'!$A:$A,$A13,'Nursing Charges'!$C:$C,11)) -> 0 | DG13: =IF($A13="","",DD13+(DF13-SUMIFS('Nursing Charges'!$J:$J,'Nursing Charges'!$A:$A,$A13,'Nursing Charges'!$C:$C,11))+(DE13-SUMIFS('Consumable Usage'!$F:$F,'Consumable Usage'!$A:$A,$A13,'Consumable Usage'!$D:$D,11))) -> 0 | DH13: =IF($A13="","",DD13+DF13+DE13) -> 0 | DJ13: =IF(DH13="","",DH13-DI13) -> 0 | DK13: =IF(OR($A13="",DB13=""),"",IF(DH13=0,"No Charges",IF(DJ13<=0,"Paid",IF(DI13>0,"Partial","Pending")))) | DO13: =IF($A13="","",SUMIFS('Consumable Usage'!$E:$E,'Consumable Usage'!$A:$A,$A13,'Consumable Usage'!$D:$D,12)) -> 0 | DP13: =IF($A13="","",SUMIFS('Nursing Charges'!$I:$I,'Nursing Charges'!$A:$A,$A13,'Nursing Charges'!$C:$C,12)) -> 0 | DQ13: =IF($A13="","",DN13+(DP13-SUMIFS('Nursing Charges'!$J:$J,'Nursing Charges'!$A:$A,$A13,'Nursing Charges'!$C:$C,12))+(DO13-SUMIFS('Consumable Usage'!$F:$F,'Consumable Usage'!$A:$A,$A13,'Consumable Usage'!$D:$D,12))) -> 0 | DR13: =IF($A13="","",DN13+DP13+DO13) -> 0 | DT13: =IF(DR13="","",DR13-DS13) -> 0 | DU13: =IF(OR($A13="",DL13=""),"",IF(DR13=0,"No Charges",IF(DT13<=0,"Paid",IF(DS13>0,"Partial","Pending")))) | DY13: =IF($A13="","",SUMIFS('Consumable Usage'!$E:$E,'Consumable Usage'!$A:$A,$A13,'Consumable Usage'!$D:$D,13)) -> 0 | DZ13: =IF($A13="","",SUMIFS('Nursing Charges'!$I:$I,'Nursing Charges'!$A:$A,$A13,'Nursing Charges'!$C:$C,13)) -> 0 | EA13: =IF($A13="","",DX13+(DZ13-SUMIFS('Nursing Charges'!$J:$J,'Nursing Charges'!$A:$A,$A13,'Nursing Charges'!$C:$C,13))+(DY13-SUMIFS('Consumable Usage'!$F:$F,'Consumable Usage'!$A:$A,$A13,'Consumable Usage'!$D:$D,13))) -> 0 | EB13: =IF($A13="","",DX13+DZ13+DY13) -> 0 | ED13: =IF(EB13="","",EB13-EC13) -> 0 | EE13: =IF(OR($A13="",DV13=""),"",IF(EB13=0,"No Charges",IF(ED13<=0,"Paid",IF(EC13>0,"Partial","Pending")))) | EI13: =IF($A13="","",SUMIFS('Consumable Usage'!$E:$E,'Consumable Usage'!$A:$A,$A13,'Consumable Usage'!$D:$D,14)) -> 0 | EJ13: =IF($A13="","",SUMIFS('Nursing Charges'!$I:$I,'Nursing Charges'!$A:$A,$A13,'Nursing Charges'!$C:$C,14)) -> 0 | EK13: =IF($A13="","",EH13+(EJ13-SUMIFS('Nursing Charges'!$J:$J,'Nursing Charges'!$A:$A,$A13,'Nursing Charges'!$C:$C,14))+(EI13-SUMIFS('Consumable Usage'!$F:$F,'Consumable Usage'!$A:$A,$A13,'Consumable Usage'!$D:$D,14))) -> 0 | EL13: =IF($A13="","",EH13+EJ13+EI13) -> 0 | EN13: =IF(EL13="","",EL13-EM13) -> 0 | EO13: =IF(OR($A13="",EF13=""),"",IF(EL13=0,"No Charges",IF(EN13<=0,"Paid",IF(EM13>0,"Partial","Pending")))) | ES13: =IF($A13="","",SUMIFS('Consumable Usage'!$E:$E,'Consumable Usage'!$A:$A,$A13,'Consumable Usage'!$D:$D,15)) -> 0 | ET13: =IF($A13="","",SUMIFS('Nursing Charges'!$I:$I,'Nursing Charges'!$A:$A,$A13,'Nursing Charges'!$C:$C,15)) -> 0 | EU13: =IF($A13="","",ER13+(ET13-SUMIFS('Nursing Charges'!$J:$J,'Nursing Charges'!$A:$A,$A13,'Nursing Charges'!$C:$C,15))+(ES13-SUMIFS('Consumable Usage'!$F:$F,'Consumable Usage'!$A:$A,$A13,'Consumable Usage'!$D:$D,15))) -> 0 | EV13: =IF($A13="","",ER13+ET13+ES13) -> 0 | EX13: =IF(EV13="","",EV13-EW13) -> 0 | EY13: =IF(OR($A13="",EP13=""),"",IF(EV13=0,"No Charges",IF(EX13<=0,"Paid",IF(EW13>0,"Partial","Pending")))) | FC13: =IF($A13="","",SUMIFS('Consumable Usage'!$E:$E,'Consumable Usage'!$A:$A,$A13,'Consumable Usage'!$D:$D,16)) -> 0 | FD13: =IF($A13="","",SUMIFS('Nursing Charges'!$I:$I,'Nursing Charges'!$A:$A,$A13,'Nursing Charges'!$C:$C,16)) -> 0 | FE13: =IF($A13="","",FB13+(FD13-SUMIFS('Nursing Charges'!$J:$J,'Nursing Charges'!$A:$A,$A13,'Nursing Charges'!$C:$C,16))+(FC13-SUMIFS('Consumable Usage'!$F:$F,'Consumable Usage'!$A:$A,$A13,'Consumable Usage'!$D:$D,16))) -> 0 | FF13: =IF($A13="","",FB13+FD13+FC13) -> 0 | FH13: =IF(FF13="","",FF13-FG13) -> 0 | FI13: =IF(OR($A13="",EZ13=""),"",IF(FF13=0,"No Charges",IF(FH13<=0,"Paid",IF(FG13>0,"Partial","Pending")))) | FM13: =IF($A13="","",SUMIFS('Consumable Usage'!$E:$E,'Consumable Usage'!$A:$A,$A13,'Consumable Usage'!$D:$D,16)) -> 0 | FN13: =IF($A13="","",SUMIFS('Nursing Charges'!$I:$I,'Nursing Charges'!$A:$A,$A13,'Nursing Charges'!$C:$C,16)) -> 0 | FO13: =IF($A13="","",FL13+(FN13-SUMIFS('Nursing Charges'!$J:$J,'Nursing Charges'!$A:$A,$A13,'Nursing Charges'!$C:$C,16))+(FM13-SUMIFS('Consumable Usage'!$F:$F,'Consumable Usage'!$A:$A,$A13,'Consumable Usage'!$D:$D,16))) -> 0 | FP13: =IF($A13="","",FL13+FN13+FM13) -> 0 | FR13: =IF(FP13="","",FP13-FQ13) -> 0 | FS13: =IF(OR($A13="",FJ13=""),"",IF(FP13=0,"No Charges",IF(FR13<=0,"Paid",IF(FQ13>0,"Partial","Pending"))))
B14: Anju Gupta | I14: =IF($A14="","",SUMIFS('Consumable Usage'!$E:$E,'Consumable Usage'!$A:$A,$A14,'Consumable Usage'!$D:$D,1)) | J14: =IF($A14="","",SUMIFS('Nursing Charges'!$I:$I,'Nursing Charges'!$A:$A,$A14,'Nursing Charges'!$C:$C,1)) | K14: =IF($A14="","",H14+(J14-SUMIFS('Nursing Charges'!$J:$J,'Nursing Charges'!$A:$A,$A14,'Nursing Charges'!$C:$C,1))+(I14-SUMIFS('Consumable Usage'!$F:$F,'Consumable Usage'!$A:$A,$A14,'Consumable Usage'!$D:$D,1))) | L14: =IF($A14="","",H14+J14+I14) | N14: =IF(L14="","",L14-M14) | O14: =IF(OR($A14="",F14=""),"",IF(L14=0,"No Charges",IF(N14<=0,"Paid",IF(M14>0,"Partial","Pending")))) | S14: =IF($A14="","",SUMIFS('Consumable Usage'!$E:$E,'Consumable Usage'!$A:$A,$A14,'Consumable Usage'!$D:$D,2)) | T14: =IF($A14="","",SUMIFS('Nursing Charges'!$I:$I,'Nursing Charges'!$A:$A,$A14,'Nursing Charges'!$C:$C,2)) | U14: =IF($A14="","",R14+(T14-SUMIFS('Nursing Charges'!$J:$J,'Nursing Charges'!$A:$A,$A14,'Nursing Charges'!$C:$C,2))+(S14-SUMIFS('Consumable Usage'!$F:$F,'Consumable Usage'!$A:$A,$A14,'Consumable Usage'!$D:$D,2))) | V14: =IF($A14="","",R14+T14+S14) | X14: =IF(V14="","",V14-W14) | Y14: =IF(OR($A14="",P14=""),"",IF(V14=0,"No Charges",IF(X14<=0,"Paid",IF(W14>0,"Partial","Pending")))) | AC14: =IF($A14="","",SUMIFS('Consumable Usage'!$E:$E,'Consumable Usage'!$A:$A,$A14,'Consumable Usage'!$D:$D,3)) | AD14: =IF($A14="","",SUMIFS('Nursing Charges'!$I:$I,'Nursing Charges'!$A:$A,$A14,'Nursing Charges'!$C:$C,3)) | AE14: =IF($A14="","",AB14+(AD14-SUMIFS('Nursing Charges'!$J:$J,'Nursing Charges'!$A:$A,$A14,'Nursing Charges'!$C:$C,3))+(AC14-SUMIFS('Consumable Usage'!$F:$F,'Consumable Usage'!$A:$A,$A14,'Consumable Usage'!$D:$D,3))) | AF14: =IF($A14="","",AB14+AD14+AC14) | AH14: =IF(AF14="","",AF14-AG14) | AI14: =IF(OR($A14="",Z14=""),"",IF(AF14=0,"No Charges",IF(AH14<=0,"Paid",IF(AG14>0,"Partial","Pending")))) | AM14: =IF($A14="","",SUMIFS('Consumable Usage'!$E:$E,'Consumable Usage'!$A:$A,$A14,'Consumable Usage'!$D:$D,4)) | AN14: =IF($A14="","",SUMIFS('Nursing Charges'!$I:$I,'Nursing Charges'!$A:$A,$A14,'Nursing Charges'!$C:$C,4)) | AO14: =IF($A14="","",AL14+(AN14-SUMIFS('Nursing Charges'!$J:$J,'Nursing Charges'!$A:$A,$A14,'Nursing Charges'!$C:$C,4))+(AM14-SUMIFS('Consumable Usage'!$F:$F,'Consumable Usage'!$A:$A,$A14,'Consumable Usage'!$D:$D,4))) | AP14: =IF($A14="","",AL14+AN14+AM14) | AR14: =IF(AP14="","",AP14-AQ14) | AS14: =IF(OR($A14="",AJ14=""),"",IF(AP14=0,"No Charges",IF(AR14<=0,"Paid",IF(AQ14>0,"Partial","Pending")))) | AW14: =IF($A14="","",SUMIFS('Consumable Usage'!$E:$E,'Consumable Usage'!$A:$A,$A14,'Consumable Usage'!$D:$D,5)) | AX14: =IF($A14="","",SUMIFS('Nursing Charges'!$I:$I,'Nursing Charges'!$A:$A,$A14,'Nursing Charges'!$C:$C,5)) | AY14: =IF($A14="","",AV14+(AX14-SUMIFS('Nursing Charges'!$J:$J,'Nursing Charges'!$A:$A,$A14,'Nursing Charges'!$C:$C,5))+(AW14-SUMIFS('Consumable Usage'!$F:$F,'Consumable Usage'!$A:$A,$A14,'Consumable Usage'!$D:$D,5))) | AZ14: =IF($A14="","",AV14+AX14+AW14) | BB14: =IF(AZ14="","",AZ14-BA14) | BC14: =IF(OR($A14="",AT14=""),"",IF(AZ14=0,"No Charges",IF(BB14<=0,"Paid",IF(BA14>0,"Partial","Pending")))) | BG14: =IF($A14="","",SUMIFS('Consumable Usage'!$E:$E,'Consumable Usage'!$A:$A,$A14,'Consumable Usage'!$D:$D,6)) | BH14: =IF($A14="","",SUMIFS('Nursing Charges'!$I:$I,'Nursing Charges'!$A:$A,$A14,'Nursing Charges'!$C:$C,6)) | BI14: =IF($A14="","",BF14+(BH14-SUMIFS('Nursing Charges'!$J:$J,'Nursing Charges'!$A:$A,$A14,'Nursing Charges'!$C:$C,6))+(BG14-SUMIFS('Consumable Usage'!$F:$F,'Consumable Usage'!$A:$A,$A14,'Consumable Usage'!$D:$D,6))) | BJ14: =IF($A14="","",BF14+BH14+BG14) | BL14: =IF(BJ14="","",BJ14-BK14) | BM14: =IF(OR($A14="",BD14=""),"",IF(BJ14=0,"No Charges",IF(BL14<=0,"Paid",IF(BK14>0,"Partial","Pending")))) | BQ14: =IF($A14="","",SUMIFS('Consumable Usage'!$E:$E,'Consumable Usage'!$A:$A,$A14,'Consumable Usage'!$D:$D,7)) | BR14: =IF($A14="","",SUMIFS('Nursing Charges'!$I:$I,'Nursing Charges'!$A:$A,$A14,'Nursing Charges'!$C:$C,7)) | BS14: =IF($A14="","",BP14+(BR14-SUMIFS('Nursing Charges'!$J:$J,'Nursing Charges'!$A:$A,$A14,'Nursing Charges'!$C:$C,7))+(BQ14-SUMIFS('Consumable Usage'!$F:$F,'Consumable Usage'!$A:$A,$A14,'Consumable Usage'!$D:$D,7))) | BT14: =IF($A14="","",BP14+BR14+BQ14) | BV14: =IF(BT14="","",BT14-BU14) | BW14: =IF(OR($A14="",BN14=""),"",IF(BT14=0,"No Charges",IF(BV14<=0,"Paid",IF(BU14>0,"Partial","Pending")))) | CA14: =IF($A14="","",SUMIFS('Consumable Usage'!$E:$E,'Consumable Usage'!$A:$A,$A14,'Consumable Usage'!$D:$D,8)) | CB14: =IF($A14="","",SUMIFS('Nursing Charges'!$I:$I,'Nursing Charges'!$A:$A,$A14,'Nursing Charges'!$C:$C,8)) | CC14: =IF($A14="","",BZ14+(CB14-SUMIFS('Nursing Charges'!$J:$J,'Nursing Charges'!$A:$A,$A14,'Nursing Charges'!$C:$C,8))+(CA14-SUMIFS('Consumable Usage'!$F:$F,'Consumable Usage'!$A:$A,$A14,'Consumable Usage'!$D:$D,8))) | CD14: =IF($A14="","",BZ14+CB14+CA14) | CF14: =IF(CD14="","",CD14-CE14) | CG14: =IF(OR($A14="",BX14=""),"",IF(CD14=0,"No Charges",IF(CF14<=0,"Paid",IF(CE14>0,"Partial","Pending")))) | CK14: =IF($A14="","",SUMIFS('Consumable Usage'!$E:$E,'Consumable Usage'!$A:$A,$A14,'Consumable Usage'!$D:$D,9)) | CL14: =IF($A14="","",SUMIFS('Nursing Charges'!$I:$I,'Nursing Charges'!$A:$A,$A14,'Nursing Charges'!$C:$C,9)) | CM14: =IF($A14="","",CJ14+(CL14-SUMIFS('Nursing Charges'!$J:$J,'Nursing Charges'!$A:$A,$A14,'Nursing Charges'!$C:$C,9))+(CK14-SUMIFS('Consumable Usage'!$F:$F,'Consumable Usage'!$A:$A,$A14,'Consumable Usage'!$D:$D,9))) | CN14: =IF($A14="","",CJ14+CL14+CK14) | CP14: =IF(CN14="","",CN14-CO14) | CQ14: =IF(OR($A14="",CH14=""),"",IF(CN14=0,"No Charges",IF(CP14<=0,"Paid",IF(CO14>0,"Partial","Pending")))) | CU14: =IF($A14="","",SUMIFS('Consumable Usage'!$E:$E,'Consumable Usage'!$A:$A,$A14,'Consumable Usage'!$D:$D,10)) | CV14: =IF($A14="","",SUMIFS('Nursing Charges'!$I:$I,'Nursing Charges'!$A:$A,$A14,'Nursing Charges'!$C:$C,10)) | CW14: =IF($A14="","",CT14+(CV14-SUMIFS('Nursing Charges'!$J:$J,'Nursing Charges'!$A:$A,$A14,'Nursing Charges'!$C:$C,10))+(CU14-SUMIFS('Consumable Usage'!$F:$F,'Consumable Usage'!$A:$A,$A14,'Consumable Usage'!$D:$D,10))) | CX14: =IF($A14="","",CT14+CV14+CU14) | CZ14: =IF(CX14="","",CX14-CY14) | DA14: =IF(OR($A14="",CR14=""),"",IF(CX14=0,"No Charges",IF(CZ14<=0,"Paid",IF(CY14>0,"Partial","Pending")))) | DE14: =IF($A14="","",SUMIFS('Consumable Usage'!$E:$E,'Consumable Usage'!$A:$A,$A14,'Consumable Usage'!$D:$D,11)) | DF14: =IF($A14="","",SUMIFS('Nursing Charges'!$I:$I,'Nursing Charges'!$A:$A,$A14,'Nursing Charges'!$C:$C,11)) | DG14: =IF($A14="","",DD14+(DF14-SUMIFS('Nursing Charges'!$J:$J,'Nursing Charges'!$A:$A,$A14,'Nursing Charges'!$C:$C,11))+(DE14-SUMIFS('Consumable Usage'!$F:$F,'Consumable Usage'!$A:$A,$A14,'Consumable Usage'!$D:$D,11))) | DH14: =IF($A14="","",DD14+DF14+DE14) | DJ14: =IF(DH14="","",DH14-DI14) | DK14: =IF(OR($A14="",DB14=""),"",IF(DH14=0,"No Charges",IF(DJ14<=0,"Paid",IF(DI14>0,"Partial","Pending")))) | DO14: =IF($A14="","",SUMIFS('Consumable Usage'!$E:$E,'Consumable Usage'!$A:$A,$A14,'Consumable Usage'!$D:$D,12)) | DP14: =IF($A14="","",SUMIFS('Nursing Charges'!$I:$I,'Nursing Charges'!$A:$A,$A14,'Nursing Charges'!$C:$C,12)) | DQ14: =IF($A14="","",DN14+(DP14-SUMIFS('Nursing Charges'!$J:$J,'Nursing Charges'!$A:$A,$A14,'Nursing Charges'!$C:$C,12))+(DO14-SUMIFS('Consumable Usage'!$F:$F,'Consumable Usage'!$A:$A,$A14,'Consumable Usage'!$D:$D,12))) | DR14: =IF($A14="","",DN14+DP14+DO14) | DT14: =IF(DR14="","",DR14-DS14) | DU14: =IF(OR($A14="",DL14=""),"",IF(DR14=0,"No Charges",IF(DT14<=0,"Paid",IF(DS14>0,"Partial","Pending")))) | DY14: =IF($A14="","",SUMIFS('Consumable Usage'!$E:$E,'Consumable Usage'!$A:$A,$A14,'Consumable Usage'!$D:$D,13)) | DZ14: =IF($A14="","",SUMIFS('Nursing Charges'!$I:$I,'Nursing Charges'!$A:$A,$A14,'Nursing Charges'!$C:$C,13)) | EA14: =IF($A14="","",DX14+(DZ14-SUMIFS('Nursing Charges'!$J:$J,'Nursing Charges'!$A:$A,$A14,'Nursing Charges'!$C:$C,13))+(DY14-SUMIFS('Consumable Usage'!$F:$F,'Consumable Usage'!$A:$A,$A14,'Consumable Usage'!$D:$D,13))) | EB14: =IF($A14="","",DX14+DZ14+DY14) | ED14: =IF(EB14="","",EB14-EC14) | EE14: =IF(OR($A14="",DV14=""),"",IF(EB14=0,"No Charges",IF(ED14<=0,"Paid",IF(EC14>0,"Partial","Pending")))) | EI14: =IF($A14="","",SUMIFS('Consumable Usage'!$E:$E,'Consumable Usage'!$A:$A,$A14,'Consumable Usage'!$D:$D,14)) | EJ14: =IF($A14="","",SUMIFS('Nursing Charges'!$I:$I,'Nursing Charges'!$A:$A,$A14,'Nursing Charges'!$C:$C,14)) | EK14: =IF($A14="","",EH14+(EJ14-SUMIFS('Nursing Charges'!$J:$J,'Nursing Charges'!$A:$A,$A14,'Nursing Charges'!$C:$C,14))+(EI14-SUMIFS('Consumable Usage'!$F:$F,'Consumable Usage'!$A:$A,$A14,'Consumable Usage'!$D:$D,14))) | EL14: =IF($A14="","",EH14+EJ14+EI14) | EN14: =IF(EL14="","",EL14-EM14) | EO14: =IF(OR($A14="",EF14=""),"",IF(EL14=0,"No Charges",IF(EN14<=0,"Paid",IF(EM14>0,"Partial","Pending")))) | ES14: =IF($A14="","",SUMIFS('Consumable Usage'!$E:$E,'Consumable Usage'!$A:$A,$A14,'Consumable Usage'!$D:$D,15)) | ET14: =IF($A14="","",SUMIFS('Nursing Charges'!$I:$I,'Nursing Charges'!$A:$A,$A14,'Nursing Charges'!$C:$C,15)) | EU14: =IF($A14="","",ER14+(ET14-SUMIFS('Nursing Charges'!$J:$J,'Nursing Charges'!$A:$A,$A14,'Nursing Charges'!$C:$C,15))+(ES14-SUMIFS('Consumable Usage'!$F:$F,'Consumable Usage'!$A:$A,$A14,'Consumable Usage'!$D:$D,15))) | EV14: =IF($A14="","",ER14+ET14+ES14) | EX14: =IF(EV14="","",EV14-EW14) | EY14: =IF(OR($A14="",EP14=""),"",IF(EV14=0,"No Charges",IF(EX14<=0,"Paid",IF(EW14>0,"Partial","Pending")))) | FC14: =IF($A14="","",SUMIFS('Consumable Usage'!$E:$E,'Consumable Usage'!$A:$A,$A14,'Consumable Usage'!$D:$D,16)) | FD14: =IF($A14="","",SUMIFS('Nursing Charges'!$I:$I,'Nursing Charges'!$A:$A,$A14,'Nursing Charges'!$C:$C,16)) | FE14: =IF($A14="","",FB14+(FD14-SUMIFS('Nursing Charges'!$J:$J,'Nursing Charges'!$A:$A,$A14,'Nursing Charges'!$C:$C,16))+(FC14-SUMIFS('Consumable Usage'!$F:$F,'Consumable Usage'!$A:$A,$A14,'Consumable Usage'!$D:$D,16))) | FF14: =IF($A14="","",FB14+FD14+FC14) | FH14: =IF(FF14="","",FF14-FG14) | FI14: =IF(OR($A14="",EZ14=""),"",IF(FF14=0,"No Charges",IF(FH14<=0,"Paid",IF(FG14>0,"Partial","Pending")))) | FM14: =IF($A14="","",SUMIFS('Consumable Usage'!$E:$E,'Consumable Usage'!$A:$A,$A14,'Consumable Usage'!$D:$D,16)) | FN14: =IF($A14="","",SUMIFS('Nursing Charges'!$I:$I,'Nursing Charges'!$A:$A,$A14,'Nursing Charges'!$C:$C,16)) | FO14: =IF($A14="","",FL14+(FN14-SUMIFS('Nursing Charges'!$J:$J,'Nursing Charges'!$A:$A,$A14,'Nursing Charges'!$C:$C,16))+(FM14-SUMIFS('Consumable Usage'!$F:$F,'Consumable Usage'!$A:$A,$A14,'Consumable Usage'!$D:$D,16))) | FP14: =IF($A14="","",FL14+FN14+FM14) | FR14: =IF(FP14="","",FP14-FQ14) | FS14: =IF(OR($A14="",FJ14=""),"",IF(FP14=0,"No Charges",IF(FR14<=0,"Paid",IF(FQ14>0,"Partial","Pending"))))
A15: CC2026010 | B15: ganga prasad joshi | C15: VIJAY | D15: 98191 23750 : Chetan Joshi | E15: needs a week once followup | I15: =IF($A15="","",SUMIFS('Consumable Usage'!$E:$E,'Consumable Usage'!$A:$A,$A15,'Consumable Usage'!$D:$D,1)) -> 0 | J15: =IF($A15="","",SUMIFS('Nursing Charges'!$I:$I,'Nursing Charges'!$A:$A,$A15,'Nursing Charges'!$C:$C,1)) -> 0 | K15: =IF($A15="","",H15+(J15-SUMIFS('Nursing Charges'!$J:$J,'Nursing Charges'!$A:$A,$A15,'Nursing Charges'!$C:$C,1))+(I15-SUMIFS('Consumable Usage'!$F:$F,'Consumable Usage'!$A:$A,$A15,'Consumable Usage'!$D:$D,1))) -> 0 | L15: =IF($A15="","",H15+J15+I15) -> 0 | N15: =IF(L15="","",L15-M15) -> 0 | O15: =IF(OR($A15="",F15=""),"",IF(L15=0,"No Charges",IF(N15<=0,"Paid",IF(M15>0,"Partial","Pending")))) | S15: =IF($A15="","",SUMIFS('Consumable Usage'!$E:$E,'Consumable Usage'!$A:$A,$A15,'Consumable Usage'!$D:$D,2)) -> 0 | T15: =IF($A15="","",SUMIFS('Nursing Charges'!$I:$I,'Nursing Charges'!$A:$A,$A15,'Nursing Charges'!$C:$C,2)) -> 0 | U15: =IF($A15="","",R15+(T15-SUMIFS('Nursing Charges'!$J:$J,'Nursing Charges'!$A:$A,$A15,'Nursing Charges'!$C:$C,2))+(S15-SUMIFS('Consumable Usage'!$F:$F,'Consumable Usage'!$A:$A,$A15,'Consumable Usage'!$D:$D,2))) -> 0 | V15: =IF($A15="","",R15+T15+S15) -> 0 | X15: =IF(V15="","",V15-W15) -> 0 | Y15: =IF(OR($A15="",P15=""),"",IF(V15=0,"No Charges",IF(X15<=0,"Paid",IF(W15>0,"Partial","Pending")))) | AC15: =IF($A15="","",SUMIFS('Consumable Usage'!$E:$E,'Consumable Usage'!$A:$A,$A15,'Consumable Usage'!$D:$D,3)) -> 0 | AD15: =IF($A15="","",SUMIFS('Nursing Charges'!$I:$I,'Nursing Charges'!$A:$A,$A15,'Nursing Charges'!$C:$C,3)) -> 0 | AE15: =IF($A15="","",AB15+(AD15-SUMIFS('Nursing Charges'!$J:$J,'Nursing Charges'!$A:$A,$A15,'Nursing Charges'!$C:$C,3))+(AC15-SUMIFS('Consumable Usage'!$F:$F,'Consumable Usage'!$A:$A,$A15,'Consumable Usage'!$D:$D,3))) -> 0 | AF15: =IF($A15="","",AB15+AD15+AC15) -> 0 | AH15: =IF(AF15="","",AF15-AG15) -> 0 | AI15: =IF(OR($A15="",Z15=""),"",IF(AF15=0,"No Charges",IF(AH15<=0,"Paid",IF(AG15>0,"Partial","Pending")))) | AM15: =IF($A15="","",SUMIFS('Consumable Usage'!$E:$E,'Consumable Usage'!$A:$A,$A15,'Consumable Usage'!$D:$D,4)) -> 0 | AN15: =IF($A15="","",SUMIFS('Nursing Charges'!$I:$I,'Nursing Charges'!$A:$A,$A15,'Nursing Charges'!$C:$C,4)) -> 0 | AO15: =IF($A15="","",AL15+(AN15-SUMIFS('Nursing Charges'!$J:$J,'Nursing Charges'!$A:$A,$A15,'Nursing Charges'!$C:$C,4))+(AM15-SUMIFS('Consumable Usage'!$F:$F,'Consumable Usage'!$A:$A,$A15,'Consumable Usage'!$D:$D,4))) -> 0 | AP15: =IF($A15="","",AL15+AN15+AM15) -> 0 | AR15: =IF(AP15="","",AP15-AQ15) -> 0 | AS15: =IF(OR($A15="",AJ15=""),"",IF(AP15=0,"No Charges",IF(AR15<=0,"Paid",IF(AQ15>0,"Partial","Pending")))) | AW15: =IF($A15="","",SUMIFS('Consumable Usage'!$E:$E,'Consumable Usage'!$A:$A,$A15,'Consumable Usage'!$D:$D,5)) -> 0 | AX15: =IF($A15="","",SUMIFS('Nursing Charges'!$I:$I,'Nursing Charges'!$A:$A,$A15,'Nursing Charges'!$C:$C,5)) -> 0 | AY15: =IF($A15="","",AV15+(AX15-SUMIFS('Nursing Charges'!$J:$J,'Nursing Charges'!$A:$A,$A15,'Nursing Charges'!$C:$C,5))+(AW15-SUMIFS('Consumable Usage'!$F:$F,'Consumable Usage'!$A:$A,$A15,'Consumable Usage'!$D:$D,5))) -> 0 | AZ15: =IF($A15="","",AV15+AX15+AW15) -> 0 | BB15: =IF(AZ15="","",AZ15-BA15) -> 0 | BC15: =IF(OR($A15="",AT15=""),"",IF(AZ15=0,"No Charges",IF(BB15<=0,"Paid",IF(BA15>0,"Partial","Pending")))) | BG15: =IF($A15="","",SUMIFS('Consumable Usage'!$E:$E,'Consumable Usage'!$A:$A,$A15,'Consumable Usage'!$D:$D,6)) -> 0 | BH15: =IF($A15="","",SUMIFS('Nursing Charges'!$I:$I,'Nursing Charges'!$A:$A,$A15,'Nursing Charges'!$C:$C,6)) -> 0 | BI15: =IF($A15="","",BF15+(BH15-SUMIFS('Nursing Charges'!$J:$J,'Nursing Charges'!$A:$A,$A15,'Nursing Charges'!$C:$C,6))+(BG15-SUMIFS('Consumable Usage'!$F:$F,'Consumable Usage'!$A:$A,$A15,'Consumable Usage'!$D:$D,6))) -> 0 | BJ15: =IF($A15="","",BF15+BH15+BG15) -> 0 | BL15: =IF(BJ15="","",BJ15-BK15) -> 0 | BM15: =IF(OR($A15="",BD15=""),"",IF(BJ15=0,"No Charges",IF(BL15<=0,"Paid",IF(BK15>0,"Partial","Pending")))) | BQ15: =IF($A15="","",SUMIFS('Consumable Usage'!$E:$E,'Consumable Usage'!$A:$A,$A15,'Consumable Usage'!$D:$D,7)) -> 0 | BR15: =IF($A15="","",SUMIFS('Nursing Charges'!$I:$I,'Nursing Charges'!$A:$A,$A15,'Nursing Charges'!$C:$C,7)) -> 0 | BS15: =IF($A15="","",BP15+(BR15-SUMIFS('Nursing Charges'!$J:$J,'Nursing Charges'!$A:$A,$A15,'Nursing Charges'!$C:$C,7))+(BQ15-SUMIFS('Consumable Usage'!$F:$F,'Consumable Usage'!$A:$A,$A15,'Consumable Usage'!$D:$D,7))) -> 0 | BT15: =IF($A15="","",BP15+BR15+BQ15) -> 0 | BV15: =IF(BT15="","",BT15-BU15) -> 0 | BW15: =IF(OR($A15="",BN15=""),"",IF(BT15=0,"No Charges",IF(BV15<=0,"Paid",IF(BU15>0,"Partial","Pending")))) | CA15: =IF($A15="","",SUMIFS('Consumable Usage'!$E:$E,'Consumable Usage'!$A:$A,$A15,'Consumable Usage'!$D:$D,8)) -> 0 | CB15: =IF($A15="","",SUMIFS('Nursing Charges'!$I:$I,'Nursing Charges'!$A:$A,$A15,'Nursing Charges'!$C:$C,8)) -> 0 | CC15: =IF($A15="","",BZ15+(CB15-SUMIFS('Nursing Charges'!$J:$J,'Nursing Charges'!$A:$A,$A15,'Nursing Charges'!$C:$C,8))+(CA15-SUMIFS('Consumable Usage'!$F:$F,'Consumable Usage'!$A:$A,$A15,'Consumable Usage'!$D:$D,8))) -> 0 | CD15: =IF($A15="","",BZ15+CB15+CA15) -> 0 | CF15: =IF(CD15="","",CD15-CE15) -> 0 | CG15: =IF(OR($A15="",BX15=""),"",IF(CD15=0,"No Charges",IF(CF15<=0,"Paid",IF(CE15>0,"Partial","Pending")))) | CK15: =IF($A15="","",SUMIFS('Consumable Usage'!$E:$E,'Consumable Usage'!$A:$A,$A15,'Consumable Usage'!$D:$D,9)) -> 0 | CL15: =IF($A15="","",SUMIFS('Nursing Charges'!$I:$I,'Nursing Charges'!$A:$A,$A15,'Nursing Charges'!$C:$C,9)) -> 0 | CM15: =IF($A15="","",CJ15+(CL15-SUMIFS('Nursing Charges'!$J:$J,'Nursing Charges'!$A:$A,$A15,'Nursing Charges'!$C:$C,9))+(CK15-SUMIFS('Consumable Usage'!$F:$F,'Consumable Usage'!$A:$A,$A15,'Consumable Usage'!$D:$D,9))) -> 0 | CN15: =IF($A15="","",CJ15+CL15+CK15) -> 0 | CP15: =IF(CN15="","",CN15-CO15) -> 0 | CQ15: =IF(OR($A15="",CH15=""),"",IF(CN15=0,"No Charges",IF(CP15<=0,"Paid",IF(CO15>0,"Partial","Pending")))) | CU15: =IF($A15="","",SUMIFS('Consumable Usage'!$E:$E,'Consumable Usage'!$A:$A,$A15,'Consumable Usage'!$D:$D,10)) -> 0 | CV15: =IF($A15="","",SUMIFS('Nursing Charges'!$I:$I,'Nursing Charges'!$A:$A,$A15,'Nursing Charges'!$C:$C,10)) -> 0 | CW15: =IF($A15="","",CT15+(CV15-SUMIFS('Nursing Charges'!$J:$J,'Nursing Charges'!$A:$A,$A15,'Nursing Charges'!$C:$C,10))+(CU15-SUMIFS('Consumable Usage'!$F:$F,'Consumable Usage'!$A:$A,$A15,'Consumable Usage'!$D:$D,10))) -> 0 | CX15: =IF($A15="","",CT15+CV15+CU15) -> 0 | CZ15: =IF(CX15="","",CX15-CY15) -> 0 | DA15: =IF(OR($A15="",CR15=""),"",IF(CX15=0,"No Charges",IF(CZ15<=0,"Paid",IF(CY15>0,"Partial","Pending")))) | DE15: =IF($A15="","",SUMIFS('Consumable Usage'!$E:$E,'Consumable Usage'!$A:$A,$A15,'Consumable Usage'!$D:$D,11)) -> 0 | DF15: =IF($A15="","",SUMIFS('Nursing Charges'!$I:$I,'Nursing Charges'!$A:$A,$A15,'Nursing Charges'!$C:$C,11)) -> 0 | DG15: =IF($A15="","",DD15+(DF15-SUMIFS('Nursing Charges'!$J:$J,'Nursing Charges'!$A:$A,$A15,'Nursing Charges'!$C:$C,11))+(DE15-SUMIFS('Consumable Usage'!$F:$F,'Consumable Usage'!$A:$A,$A15,'Consumable Usage'!$D:$D,11))) -> 0 | DH15: =IF($A15="","",DD15+DF15+DE15) -> 0 | DJ15: =IF(DH15="","",DH15-DI15) -> 0 | DK15: =IF(OR($A15="",DB15=""),"",IF(DH15=0,"No Charges",IF(DJ15<=0,"Paid",IF(DI15>0,"Partial","Pending")))) | DO15: =IF($A15="","",SUMIFS('Consumable Usage'!$E:$E,'Consumable Usage'!$A:$A,$A15,'Consumable Usage'!$D:$D,12)) -> 0 | DP15: =IF($A15="","",SUMIFS('Nursing Charges'!$I:$I,'Nursing Charges'!$A:$A,$A15,'Nursing Charges'!$C:$C,12)) -> 0 | DQ15: =IF($A15="","",DN15+(DP15-SUMIFS('Nursing Charges'!$J:$J,'Nursing Charges'!$A:$A,$A15,'Nursing Charges'!$C:$C,12))+(DO15-SUMIFS('Consumable Usage'!$F:$F,'Consumable Usage'!$A:$A,$A15,'Consumable Usage'!$D:$D,12))) -> 0 | DR15: =IF($A15="","",DN15+DP15+DO15) -> 0 | DT15: =IF(DR15="","",DR15-DS15) -> 0 | DU15: =IF(OR($A15="",DL15=""),"",IF(DR15=0,"No Charges",IF(DT15<=0,"Paid",IF(DS15>0,"Partial","Pending")))) | DY15: =IF($A15="","",SUMIFS('Consumable Usage'!$E:$E,'Consumable Usage'!$A:$A,$A15,'Consumable Usage'!$D:$D,13)) -> 0 | DZ15: =IF($A15="","",SUMIFS('Nursing Charges'!$I:$I,'Nursing Charges'!$A:$A,$A15,'Nursing Charges'!$C:$C,13)) -> 0 | EA15: =IF($A15="","",DX15+(DZ15-SUMIFS('Nursing Charges'!$J:$J,'Nursing Charges'!$A:$A,$A15,'Nursing Charges'!$C:$C,13))+(DY15-SUMIFS('Consumable Usage'!$F:$F,'Consumable Usage'!$A:$A,$A15,'Consumable Usage'!$D:$D,13))) -> 0 | EB15: =IF($A15="","",DX15+DZ15+DY15) -> 0 | ED15: =IF(EB15="","",EB15-EC15) -> 0 | EE15: =IF(OR($A15="",DV15=""),"",IF(EB15=0,"No Charges",IF(ED15<=0,"Paid",IF(EC15>0,"Partial","Pending")))) | EI15: =IF($A15="","",SUMIFS('Consumable Usage'!$E:$E,'Consumable Usage'!$A:$A,$A15,'Consumable Usage'!$D:$D,14)) -> 0 | EJ15: =IF($A15="","",SUMIFS('Nursing Charges'!$I:$I,'Nursing Charges'!$A:$A,$A15,'Nursing Charges'!$C:$C,14)) -> 0 | EK15: =IF($A15="","",EH15+(EJ15-SUMIFS('Nursing Charges'!$J:$J,'Nursing Charges'!$A:$A,$A15,'Nursing Charges'!$C:$C,14))+(EI15-SUMIFS('Consumable Usage'!$F:$F,'Consumable Usage'!$A:$A,$A15,'Consumable Usage'!$D:$D,14))) -> 0 | EL15: =IF($A15="","",EH15+EJ15+EI15) -> 0 | EN15: =IF(EL15="","",EL15-EM15) -> 0 | EO15: =IF(OR($A15="",EF15=""),"",IF(EL15=0,"No Charges",IF(EN15<=0,"Paid",IF(EM15>0,"Partial","Pending")))) | ES15: =IF($A15="","",SUMIFS('Consumable Usage'!$E:$E,'Consumable Usage'!$A:$A,$A15,'Consumable Usage'!$D:$D,15)) -> 0 | ET15: =IF($A15="","",SUMIFS('Nursing Charges'!$I:$I,'Nursing Charges'!$A:$A,$A15,'Nursing Charges'!$C:$C,15)) -> 0 | EU15: =IF($A15="","",ER15+(ET15-SUMIFS('Nursing Charges'!$J:$J,'Nursing Charges'!$A:$A,$A15,'Nursing Charges'!$C:$C,15))+(ES15-SUMIFS('Consumable Usage'!$F:$F,'Consumable Usage'!$A:$A,$A15,'Consumable Usage'!$D:$D,15))) -> 0 | EV15: =IF($A15="","",ER15+ET15+ES15) -> 0 | EX15: =IF(EV15="","",EV15-EW15) -> 0 | EY15: =IF(OR($A15="",EP15=""),"",IF(EV15=0,"No Charges",IF(EX15<=0,"Paid",IF(EW15>0,"Partial","Pending")))) | FC15: =IF($A15="","",SUMIFS('Consumable Usage'!$E:$E,'Consumable Usage'!$A:$A,$A15,'Consumable Usage'!$D:$D,16)) -> 0 | FD15: =IF($A15="","",SUMIFS('Nursing Charges'!$I:$I,'Nursing Charges'!$A:$A,$A15,'Nursing Charges'!$C:$C,16)) -> 0 | FE15: =IF($A15="","",FB15+(FD15-SUMIFS('Nursing Charges'!$J:$J,'Nursing Charges'!$A:$A,$A15,'Nursing Charges'!$C:$C,16))+(FC15-SUMIFS('Consumable Usage'!$F:$F,'Consumable Usage'!$A:$A,$A15,'Consumable Usage'!$D:$D,16))) -> 0 | FF15: =IF($A15="","",FB15+FD15+FC15) -> 0 | FH15: =IF(FF15="","",FF15-FG15) -> 0 | FI15: =IF(OR($A15="",EZ15=""),"",IF(FF15=0,"No Charges",IF(FH15<=0,"Paid",IF(FG15>0,"Partial","Pending")))) | FM15: =IF($A15="","",SUMIFS('Consumable Usage'!$E:$E,'Consumable Usage'!$A:$A,$A15,'Consumable Usage'!$D:$D,16)) -> 0 | FN15: =IF($A15="","",SUMIFS('Nursing Charges'!$I:$I,'Nursing Charges'!$A:$A,$A15,'Nursing Charges'!$C:$C,16)) -> 0 | FO15: =IF($A15="","",FL15+(FN15-SUMIFS('Nursing Charges'!$J:$J,'Nursing Charges'!$A:$A,$A15,'Nursing Charges'!$C:$C,16))+(FM15-SUMIFS('Consumable Usage'!$F:$F,'Consumable Usage'!$A:$A,$A15,'Consumable Usage'!$D:$D,16))) -> 0 | FP15: =IF($A15="","",FL15+FN15+FM15) -> 0 | FR15: =IF(FP15="","",FP15-FQ15) -> 0 | FS15: =IF(OR($A15="",FJ15=""),"",IF(FP15=0,"No Charges",IF(FR15<=0,"Paid",IF(FQ15>0,"Partial","Pending"))))
A16: CC2026011 | B16: vanitha suthar | C16: ADYA | D16: 98334 43611 | E16: confirmed dates | I16: =IF($A16="","",SUMIFS('Consumable Usage'!$E:$E,'Consumable Usage'!$A:$A,$A16,'Consumable Usage'!$D:$D,1)) -> 0 | J16: =IF($A16="","",SUMIFS('Nursing Charges'!$I:$I,'Nursing Charges'!$A:$A,$A16,'Nursing Charges'!$C:$C,1)) -> 0 | K16: =IF($A16="","",H16+(J16-SUMIFS('Nursing Charges'!$J:$J,'Nursing Charges'!$A:$A,$A16,'Nursing Charges'!$C:$C,1))+(I16-SUMIFS('Consumable Usage'!$F:$F,'Consumable Usage'!$A:$A,$A16,'Consumable Usage'!$D:$D,1))) -> 0 | L16: =IF($A16="","",H16+J16+I16) -> 0 | N16: =IF(L16="","",L16-M16) -> 0 | O16: =IF(OR($A16="",F16=""),"",IF(L16=0,"No Charges",IF(N16<=0,"Paid",IF(M16>0,"Partial","Pending")))) | S16: =IF($A16="","",SUMIFS('Consumable Usage'!$E:$E,'Consumable Usage'!$A:$A,$A16,'Consumable Usage'!$D:$D,2)) -> 0 | T16: =IF($A16="","",SUMIFS('Nursing Charges'!$I:$I,'Nursing Charges'!$A:$A,$A16,'Nursing Charges'!$C:$C,2)) -> 0 | U16: =IF($A16="","",R16+(T16-SUMIFS('Nursing Charges'!$J:$J,'Nursing Charges'!$A:$A,$A16,'Nursing Charges'!$C:$C,2))+(S16-SUMIFS('Consumable Usage'!$F:$F,'Consumable Usage'!$A:$A,$A16,'Consumable Usage'!$D:$D,2))) -> 0 | V16: =IF($A16="","",R16+T16+S16) -> 0 | X16: =IF(V16="","",V16-W16) -> 0 | Y16: =IF(OR($A16="",P16=""),"",IF(V16=0,"No Charges",IF(X16<=0,"Paid",IF(W16>0,"Partial","Pending")))) | AC16: =IF($A16="","",SUMIFS('Consumable Usage'!$E:$E,'Consumable Usage'!$A:$A,$A16,'Consumable Usage'!$D:$D,3)) -> 0 | AD16: =IF($A16="","",SUMIFS('Nursing Charges'!$I:$I,'Nursing Charges'!$A:$A,$A16,'Nursing Charges'!$C:$C,3)) -> 0 | AE16: =IF($A16="","",AB16+(AD16-SUMIFS('Nursing Charges'!$J:$J,'Nursing Charges'!$A:$A,$A16,'Nursing Charges'!$C:$C,3))+(AC16-SUMIFS('Consumable Usage'!$F:$F,'Consumable Usage'!$A:$A,$A16,'Consumable Usage'!$D:$D,3))) -> 0 | AF16: =IF($A16="","",AB16+AD16+AC16) -> 0 | AH16: =IF(AF16="","",AF16-AG16) -> 0 | AI16: =IF(OR($A16="",Z16=""),"",IF(AF16=0,"No Charges",IF(AH16<=0,"Paid",IF(AG16>0,"Partial","Pending")))) | AM16: =IF($A16="","",SUMIFS('Consumable Usage'!$E:$E,'Consumable Usage'!$A:$A,$A16,'Consumable Usage'!$D:$D,4)) -> 0 | AN16: =IF($A16="","",SUMIFS('Nursing Charges'!$I:$I,'Nursing Charges'!$A:$A,$A16,'Nursing Charges'!$C:$C,4)) -> 0 | AO16: =IF($A16="","",AL16+(AN16-SUMIFS('Nursing Charges'!$J:$J,'Nursing Charges'!$A:$A,$A16,'Nursing Charges'!$C:$C,4))+(AM16-SUMIFS('Consumable Usage'!$F:$F,'Consumable Usage'!$A:$A,$A16,'Consumable Usage'!$D:$D,4))) -> 0 | AP16: =IF($A16="","",AL16+AN16+AM16) -> 0 | AR16: =IF(AP16="","",AP16-AQ16) -> 0 | AS16: =IF(OR($A16="",AJ16=""),"",IF(AP16=0,"No Charges",IF(AR16<=0,"Paid",IF(AQ16>0,"Partial","Pending")))) | AW16: =IF($A16="","",SUMIFS('Consumable Usage'!$E:$E,'Consumable Usage'!$A:$A,$A16,'Consumable Usage'!$D:$D,5)) -> 0 | AX16: =IF($A16="","",SUMIFS('Nursing Charges'!$I:$I,'Nursing Charges'!$A:$A,$A16,'Nursing Charges'!$C:$C,5)) -> 0 | AY16: =IF($A16="","",AV16+(AX16-SUMIFS('Nursing Charges'!$J:$J,'Nursing Charges'!$A:$A,$A16,'Nursing Charges'!$C:$C,5))+(AW16-SUMIFS('Consumable Usage'!$F:$F,'Consumable Usage'!$A:$A,$A16,'Consumable Usage'!$D:$D,5))) -> 0 | AZ16: =IF($A16="","",AV16+AX16+AW16) -> 0 | BB16: =IF(AZ16="","",AZ16-BA16) -> 0 | BC16: =IF(OR($A16="",AT16=""),"",IF(AZ16=0,"No Charges",IF(BB16<=0,"Paid",IF(BA16>0,"Partial","Pending")))) | BG16: =IF($A16="","",SUMIFS('Consumable Usage'!$E:$E,'Consumable Usage'!$A:$A,$A16,'Consumable Usage'!$D:$D,6)) -> 0 | BH16: =IF($A16="","",SUMIFS('Nursing Charges'!$I:$I,'Nursing Charges'!$A:$A,$A16,'Nursing Charges'!$C:$C,6)) -> 0 | BI16: =IF($A16="","",BF16+(BH16-SUMIFS('Nursing Charges'!$J:$J,'Nursing Charges'!$A:$A,$A16,'Nursing Charges'!$C:$C,6))+(BG16-SUMIFS('Consumable Usage'!$F:$F,'Consumable Usage'!$A:$A,$A16,'Consumable Usage'!$D:$D,6))) -> 0 | BJ16: =IF($A16="","",BF16+BH16+BG16) -> 0 | BL16: =IF(BJ16="","",BJ16-BK16) -> 0 | BM16: =IF(OR($A16="",BD16=""),"",IF(BJ16=0,"No Charges",IF(BL16<=0,"Paid",IF(BK16>0,"Partial","Pending")))) | BQ16: =IF($A16="","",SUMIFS('Consumable Usage'!$E:$E,'Consumable Usage'!$A:$A,$A16,'Consumable Usage'!$D:$D,7)) -> 0 | BR16: =IF($A16="","",SUMIFS('Nursing Charges'!$I:$I,'Nursing Charges'!$A:$A,$A16,'Nursing Charges'!$C:$C,7)) -> 0 | BS16: =IF($A16="","",BP16+(BR16-SUMIFS('Nursing Charges'!$J:$J,'Nursing Charges'!$A:$A,$A16,'Nursing Charges'!$C:$C,7))+(BQ16-SUMIFS('Consumable Usage'!$F:$F,'Consumable Usage'!$A:$A,$A16,'Consumable Usage'!$D:$D,7))) -> 0 | BT16: =IF($A16="","",BP16+BR16+BQ16) -> 0 | BV16: =IF(BT16="","",BT16-BU16) -> 0 | BW16: =IF(OR($A16="",BN16=""),"",IF(BT16=0,"No Charges",IF(BV16<=0,"Paid",IF(BU16>0,"Partial","Pending")))) | CA16: =IF($A16="","",SUMIFS('Consumable Usage'!$E:$E,'Consumable Usage'!$A:$A,$A16,'Consumable Usage'!$D:$D,8)) -> 0 | CB16: =IF($A16="","",SUMIFS('Nursing Charges'!$I:$I,'Nursing Charges'!$A:$A,$A16,'Nursing Charges'!$C:$C,8)) -> 0 | CC16: =IF($A16="","",BZ16+(CB16-SUMIFS('Nursing Charges'!$J:$J,'Nursing Charges'!$A:$A,$A16,'Nursing Charges'!$C:$C,8))+(CA16-SUMIFS('Consumable Usage'!$F:$F,'Consumable Usage'!$A:$A,$A16,'Consumable Usage'!$D:$D,8))) -> 0 | CD16: =IF($A16="","",BZ16+CB16+CA16) -> 0 | CF16: =IF(CD16="","",CD16-CE16) -> 0 | CG16: =IF(OR($A16="",BX16=""),"",IF(CD16=0,"No Charges",IF(CF16<=0,"Paid",IF(CE16>0,"Partial","Pending")))) | CK16: =IF($A16="","",SUMIFS('Consumable Usage'!$E:$E,'Consumable Usage'!$A:$A,$A16,'Consumable Usage'!$D:$D,9)) -> 0 | CL16: =IF($A16="","",SUMIFS('Nursing Charges'!$I:$I,'Nursing Charges'!$A:$A,$A16,'Nursing Charges'!$C:$C,9)) -> 0 | CM16: =IF($A16="","",CJ16+(CL16-SUMIFS('Nursing Charges'!$J:$J,'Nursing Charges'!$A:$A,$A16,'Nursing Charges'!$C:$C,9))+(CK16-SUMIFS('Consumable Usage'!$F:$F,'Consumable Usage'!$A:$A,$A16,'Consumable Usage'!$D:$D,9))) -> 0 | CN16: =IF($A16="","",CJ16+CL16+CK16) -> 0 | CP16: =IF(CN16="","",CN16-CO16) -> 0 | CQ16: =IF(OR($A16="",CH16=""),"",IF(CN16=0,"No Charges",IF(CP16<=0,"Paid",IF(CO16>0,"Partial","Pending")))) | CU16: =IF($A16="","",SUMIFS('Consumable Usage'!$E:$E,'Consumable Usage'!$A:$A,$A16,'Consumable Usage'!$D:$D,10)) -> 0 | CV16: =IF($A16="","",SUMIFS('Nursing Charges'!$I:$I,'Nursing Charges'!$A:$A,$A16,'Nursing Charges'!$C:$C,10)) -> 0 | CW16: =IF($A16="","",CT16+(CV16-SUMIFS('Nursing Charges'!$J:$J,'Nursing Charges'!$A:$A,$A16,'Nursing Charges'!$C:$C,10))+(CU16-SUMIFS('Consumable Usage'!$F:$F,'Consumable Usage'!$A:$A,$A16,'Consumable Usage'!$D:$D,10))) -> 0 | CX16: =IF($A16="","",CT16+CV16+CU16) -> 0 | CZ16: =IF(CX16="","",CX16-CY16) -> 0 | DA16: =IF(OR($A16="",CR16=""),"",IF(CX16=0,"No Charges",IF(CZ16<=0,"Paid",IF(CY16>0,"Partial","Pending")))) | DE16: =IF($A16="","",SUMIFS('Consumable Usage'!$E:$E,'Consumable Usage'!$A:$A,$A16,'Consumable Usage'!$D:$D,11)) -> 0 | DF16: =IF($A16="","",SUMIFS('Nursing Charges'!$I:$I,'Nursing Charges'!$A:$A,$A16,'Nursing Charges'!$C:$C,11)) -> 0 | DG16: =IF($A16="","",DD16+(DF16-SUMIFS('Nursing Charges'!$J:$J,'Nursing Charges'!$A:$A,$A16,'Nursing Charges'!$C:$C,11))+(DE16-SUMIFS('Consumable Usage'!$F:$F,'Consumable Usage'!$A:$A,$A16,'Consumable Usage'!$D:$D,11))) -> 0 | DH16: =IF($A16="","",DD16+DF16+DE16) -> 0 | DJ16: =IF(DH16="","",DH16-DI16) -> 0 | DK16: =IF(OR($A16="",DB16=""),"",IF(DH16=0,"No Charges",IF(DJ16<=0,"Paid",IF(DI16>0,"Partial","Pending")))) | DO16: =IF($A16="","",SUMIFS('Consumable Usage'!$E:$E,'Consumable Usage'!$A:$A,$A16,'Consumable Usage'!$D:$D,12)) -> 0 | DP16: =IF($A16="","",SUMIFS('Nursing Charges'!$I:$I,'Nursing Charges'!$A:$A,$A16,'Nursing Charges'!$C:$C,12)) -> 0 | DQ16: =IF($A16="","",DN16+(DP16-SUMIFS('Nursing Charges'!$J:$J,'Nursing Charges'!$A:$A,$A16,'Nursing Charges'!$C:$C,12))+(DO16-SUMIFS('Consumable Usage'!$F:$F,'Consumable Usage'!$A:$A,$A16,'Consumable Usage'!$D:$D,12))) -> 0 | DR16: =IF($A16="","",DN16+DP16+DO16) -> 0 | DT16: =IF(DR16="","",DR16-DS16) -> 0 | DU16: =IF(OR($A16="",DL16=""),"",IF(DR16=0,"No Charges",IF(DT16<=0,"Paid",IF(DS16>0,"Partial","Pending")))) | DY16: =IF($A16="","",SUMIFS('Consumable Usage'!$E:$E,'Consumable Usage'!$A:$A,$A16,'Consumable Usage'!$D:$D,13)) -> 0 | DZ16: =IF($A16="","",SUMIFS('Nursing Charges'!$I:$I,'Nursing Charges'!$A:$A,$A16,'Nursing Charges'!$C:$C,13)) -> 0 | EA16: =IF($A16="","",DX16+(DZ16-SUMIFS('Nursing Charges'!$J:$J,'Nursing Charges'!$A:$A,$A16,'Nursing Charges'!$C:$C,13))+(DY16-SUMIFS('Consumable Usage'!$F:$F,'Consumable Usage'!$A:$A,$A16,'Consumable Usage'!$D:$D,13))) -> 0 | EB16: =IF($A16="","",DX16+DZ16+DY16) -> 0 | ED16: =IF(EB16="","",EB16-EC16) -> 0 | EE16: =IF(OR($A16="",DV16=""),"",IF(EB16=0,"No Charges",IF(ED16<=0,"Paid",IF(EC16>0,"Partial","Pending")))) | EI16: =IF($A16="","",SUMIFS('Consumable Usage'!$E:$E,'Consumable Usage'!$A:$A,$A16,'Consumable Usage'!$D:$D,14)) -> 0 | EJ16: =IF($A16="","",SUMIFS('Nursing Charges'!$I:$I,'Nursing Charges'!$A:$A,$A16,'Nursing Charges'!$C:$C,14)) -> 0 | EK16: =IF($A16="","",EH16+(EJ16-SUMIFS('Nursing Charges'!$J:$J,'Nursing Charges'!$A:$A,$A16,'Nursing Charges'!$C:$C,14))+(EI16-SUMIFS('Consumable Usage'!$F:$F,'Consumable Usage'!$A:$A,$A16,'Consumable Usage'!$D:$D,14))) -> 0 | EL16: =IF($A16="","",EH16+EJ16+EI16) -> 0 | EN16: =IF(EL16="","",EL16-EM16) -> 0 | EO16: =IF(OR($A16="",EF16=""),"",IF(EL16=0,"No Charges",IF(EN16<=0,"Paid",IF(EM16>0,"Partial","Pending")))) | ES16: =IF($A16="","",SUMIFS('Consumable Usage'!$E:$E,'Consumable Usage'!$A:$A,$A16,'Consumable Usage'!$D:$D,15)) -> 0 | ET16: =IF($A16="","",SUMIFS('Nursing Charges'!$I:$I,'Nursing Charges'!$A:$A,$A16,'Nursing Charges'!$C:$C,15)) -> 0 | EU16: =IF($A16="","",ER16+(ET16-SUMIFS('Nursing Charges'!$J:$J,'Nursing Charges'!$A:$A,$A16,'Nursing Charges'!$C:$C,15))+(ES16-SUMIFS('Consumable Usage'!$F:$F,'Consumable Usage'!$A:$A,$A16,'Consumable Usage'!$D:$D,15))) -> 0 | EV16: =IF($A16="","",ER16+ET16+ES16) -> 0 | EX16: =IF(EV16="","",EV16-EW16) -> 0 | EY16: =IF(OR($A16="",EP16=""),"",IF(EV16=0,"No Charges",IF(EX16<=0,"Paid",IF(EW16>0,"Partial","Pending")))) | FC16: =IF($A16="","",SUMIFS('Consumable Usage'!$E:$E,'Consumable Usage'!$A:$A,$A16,'Consumable Usage'!$D:$D,16)) -> 0 | FD16: =IF($A16="","",SUMIFS('Nursing Charges'!$I:$I,'Nursing Charges'!$A:$A,$A16,'Nursing Charges'!$C:$C,16)) -> 0 | FE16: =IF($A16="","",FB16+(FD16-SUMIFS('Nursing Charges'!$J:$J,'Nursing Charges'!$A:$A,$A16,'Nursing Charges'!$C:$C,16))+(FC16-SUMIFS('Consumable Usage'!$F:$F,'Consumable Usage'!$A:$A,$A16,'Consumable Usage'!$D:$D,16))) -> 0 | FF16: =IF($A16="","",FB16+FD16+FC16) -> 0 | FH16: =IF(FF16="","",FF16-FG16) -> 0 | FI16: =IF(OR($A16="",EZ16=""),"",IF(FF16=0,"No Charges",IF(FH16<=0,"Paid",IF(FG16>0,"Partial","Pending")))) | FM16: =IF($A16="","",SUMIFS('Consumable Usage'!$E:$E,'Consumable Usage'!$A:$A,$A16,'Consumable Usage'!$D:$D,16)) -> 0 | FN16: =IF($A16="","",SUMIFS('Nursing Charges'!$I:$I,'Nursing Charges'!$A:$A,$A16,'Nursing Charges'!$C:$C,16)) -> 0 | FO16: =IF($A16="","",FL16+(FN16-SUMIFS('Nursing Charges'!$J:$J,'Nursing Charges'!$A:$A,$A16,'Nursing Charges'!$C:$C,16))+(FM16-SUMIFS('Consumable Usage'!$F:$F,'Consumable Usage'!$A:$A,$A16,'Consumable Usage'!$D:$D,16))) -> 0 | FP16: =IF($A16="","",FL16+FN16+FM16) -> 0 | FR16: =IF(FP16="","",FP16-FQ16) -> 0 | FS16: =IF(OR($A16="",FJ16=""),"",IF(FP16=0,"No Charges",IF(FR16<=0,"Paid",IF(FQ16>0,"Partial","Pending"))))
A17: CC2026012 | B17: Suresh Rathod | C17: VIJAY AND SHOURYA | E17: next date needed need to know the payment status | I17: =IF($A17="","",SUMIFS('Consumable Usage'!$E:$E,'Consumable Usage'!$A:$A,$A17,'Consumable Usage'!$D:$D,1)) -> 0 | J17: =IF($A17="","",SUMIFS('Nursing Charges'!$I:$I,'Nursing Charges'!$A:$A,$A17,'Nursing Charges'!$C:$C,1)) -> 0 | K17: =IF($A17="","",H17+(J17-SUMIFS('Nursing Charges'!$J:$J,'Nursing Charges'!$A:$A,$A17,'Nursing Charges'!$C:$C,1))+(I17-SUMIFS('Consumable Usage'!$F:$F,'Consumable Usage'!$A:$A,$A17,'Consumable Usage'!$D:$D,1))) -> 0 | L17: =IF($A17="","",H17+J17+I17) -> 0 | N17: =IF(L17="","",L17-M17) -> 0 | O17: =IF(OR($A17="",F17=""),"",IF(L17=0,"No Charges",IF(N17<=0,"Paid",IF(M17>0,"Partial","Pending")))) | S17: =IF($A17="","",SUMIFS('Consumable Usage'!$E:$E,'Consumable Usage'!$A:$A,$A17,'Consumable Usage'!$D:$D,2)) -> 0 | T17: =IF($A17="","",SUMIFS('Nursing Charges'!$I:$I,'Nursing Charges'!$A:$A,$A17,'Nursing Charges'!$C:$C,2)) -> 0 | U17: =IF($A17="","",R17+(T17-SUMIFS('Nursing Charges'!$J:$J,'Nursing Charges'!$A:$A,$A17,'Nursing Charges'!$C:$C,2))+(S17-SUMIFS('Consumable Usage'!$F:$F,'Consumable Usage'!$A:$A,$A17,'Consumable Usage'!$D:$D,2))) -> 0 | V17: =IF($A17="","",R17+T17+S17) -> 0 | X17: =IF(V17="","",V17-W17) -> 0 | Y17: =IF(OR($A17="",P17=""),"",IF(V17=0,"No Charges",IF(X17<=0,"Paid",IF(W17>0,"Partial","Pending")))) | AC17: =IF($A17="","",SUMIFS('Consumable Usage'!$E:$E,'Consumable Usage'!$A:$A,$A17,'Consumable Usage'!$D:$D,3)) -> 0 | AD17: =IF($A17="","",SUMIFS('Nursing Charges'!$I:$I,'Nursing Charges'!$A:$A,$A17,'Nursing Charges'!$C:$C,3)) -> 0 | AE17: =IF($A17="","",AB17+(AD17-SUMIFS('Nursing Charges'!$J:$J,'Nursing Charges'!$A:$A,$A17,'Nursing Charges'!$C:$C,3))+(AC17-SUMIFS('Consumable Usage'!$F:$F,'Consumable Usage'!$A:$A,$A17,'Consumable Usage'!$D:$D,3))) -> 0 | AF17: =IF($A17="","",AB17+AD17+AC17) -> 0 | AH17: =IF(AF17="","",AF17-AG17) -> 0 | AI17: =IF(OR($A17="",Z17=""),"",IF(AF17=0,"No Charges",IF(AH17<=0,"Paid",IF(AG17>0,"Partial","Pending")))) | AM17: =IF($A17="","",SUMIFS('Consumable Usage'!$E:$E,'Consumable Usage'!$A:$A,$A17,'Consumable Usage'!$D:$D,4)) -> 0 | AN17: =IF($A17="","",SUMIFS('Nursing Charges'!$I:$I,'Nursing Charges'!$A:$A,$A17,'Nursing Charges'!$C:$C,4)) -> 0 | AO17: =IF($A17="","",AL17+(AN17-SUMIFS('Nursing Charges'!$J:$J,'Nursing Charges'!$A:$A,$A17,'Nursing Charges'!$C:$C,4))+(AM17-SUMIFS('Consumable Usage'!$F:$F,'Consumable Usage'!$A:$A,$A17,'Consumable Usage'!$D:$D,4))) -> 0 | AP17: =IF($A17="","",AL17+AN17+AM17) -> 0 | AR17: =IF(AP17="","",AP17-AQ17) -> 0 | AS17: =IF(OR($A17="",AJ17=""),"",IF(AP17=0,"No Charges",IF(AR17<=0,"Paid",IF(AQ17>0,"Partial","Pending")))) | AW17: =IF($A17="","",SUMIFS('Consumable Usage'!$E:$E,'Consumable Usage'!$A:$A,$A17,'Consumable Usage'!$D:$D,5)) -> 0 | AX17: =IF($A17="","",SUMIFS('Nursing Charges'!$I:$I,'Nursing Charges'!$A:$A,$A17,'Nursing Charges'!$C:$C,5)) -> 0 | AY17: =IF($A17="","",AV17+(AX17-SUMIFS('Nursing Charges'!$J:$J,'Nursing Charges'!$A:$A,$A17,'Nursing Charges'!$C:$C,5))+(AW17-SUMIFS('Consumable Usage'!$F:$F,'Consumable Usage'!$A:$A,$A17,'Consumable Usage'!$D:$D,5))) -> 0 | AZ17: =IF($A17="","",AV17+AX17+AW17) -> 0 | BB17: =IF(AZ17="","",AZ17-BA17) -> 0 | BC17: =IF(OR($A17="",AT17=""),"",IF(AZ17=0,"No Charges",IF(BB17<=0,"Paid",IF(BA17>0,"Partial","Pending")))) | BG17: =IF($A17="","",SUMIFS('Consumable Usage'!$E:$E,'Consumable Usage'!$A:$A,$A17,'Consumable Usage'!$D:$D,6)) -> 0 | BH17: =IF($A17="","",SUMIFS('Nursing Charges'!$I:$I,'Nursing Charges'!$A:$A,$A17,'Nursing Charges'!$C:$C,6)) -> 0 | BI17: =IF($A17="","",BF17+(BH17-SUMIFS('Nursing Charges'!$J:$J,'Nursing Charges'!$A:$A,$A17,'Nursing Charges'!$C:$C,6))+(BG17-SUMIFS('Consumable Usage'!$F:$F,'Consumable Usage'!$A:$A,$A17,'Consumable Usage'!$D:$D,6))) -> 0 | BJ17: =IF($A17="","",BF17+BH17+BG17) -> 0 | BL17: =IF(BJ17="","",BJ17-BK17) -> 0 | BM17: =IF(OR($A17="",BD17=""),"",IF(BJ17=0,"No Charges",IF(BL17<=0,"Paid",IF(BK17>0,"Partial","Pending")))) | BQ17: =IF($A17="","",SUMIFS('Consumable Usage'!$E:$E,'Consumable Usage'!$A:$A,$A17,'Consumable Usage'!$D:$D,7)) -> 0 | BR17: =IF($A17="","",SUMIFS('Nursing Charges'!$I:$I,'Nursing Charges'!$A:$A,$A17,'Nursing Charges'!$C:$C,7)) -> 0 | BS17: =IF($A17="","",BP17+(BR17-SUMIFS('Nursing Charges'!$J:$J,'Nursing Charges'!$A:$A,$A17,'Nursing Charges'!$C:$C,7))+(BQ17-SUMIFS('Consumable Usage'!$F:$F,'Consumable Usage'!$A:$A,$A17,'Consumable Usage'!$D:$D,7))) -> 0 | BT17: =IF($A17="","",BP17+BR17+BQ17) -> 0 | BV17: =IF(BT17="","",BT17-BU17) -> 0 | BW17: =IF(OR($A17="",BN17=""),"",IF(BT17=0,"No Charges",IF(BV17<=0,"Paid",IF(BU17>0,"Partial","Pending")))) | CA17: =IF($A17="","",SUMIFS('Consumable Usage'!$E:$E,'Consumable Usage'!$A:$A,$A17,'Consumable Usage'!$D:$D,8)) -> 0 | CB17: =IF($A17="","",SUMIFS('Nursing Charges'!$I:$I,'Nursing Charges'!$A:$A,$A17,'Nursing Charges'!$C:$C,8)) -> 0 | CC17: =IF($A17="","",BZ17+(CB17-SUMIFS('Nursing Charges'!$J:$J,'Nursing Charges'!$A:$A,$A17,'Nursing Charges'!$C:$C,8))+(CA17-SUMIFS('Consumable Usage'!$F:$F,'Consumable Usage'!$A:$A,$A17,'Consumable Usage'!$D:$D,8))) -> 0 | CD17: =IF($A17="","",BZ17+CB17+CA17) -> 0 | CF17: =IF(CD17="","",CD17-CE17) -> 0 | CG17: =IF(OR($A17="",BX17=""),"",IF(CD17=0,"No Charges",IF(CF17<=0,"Paid",IF(CE17>0,"Partial","Pending")))) | CK17: =IF($A17="","",SUMIFS('Consumable Usage'!$E:$E,'Consumable Usage'!$A:$A,$A17,'Consumable Usage'!$D:$D,9)) -> 0 | CL17: =IF($A17="","",SUMIFS('Nursing Charges'!$I:$I,'Nursing Charges'!$A:$A,$A17,'Nursing Charges'!$C:$C,9)) -> 0 | CM17: =IF($A17="","",CJ17+(CL17-SUMIFS('Nursing Charges'!$J:$J,'Nursing Charges'!$A:$A,$A17,'Nursing Charges'!$C:$C,9))+(CK17-SUMIFS('Consumable Usage'!$F:$F,'Consumable Usage'!$A:$A,$A17,'Consumable Usage'!$D:$D,9))) -> 0 | CN17: =IF($A17="","",CJ17+CL17+CK17) -> 0 | CP17: =IF(CN17="","",CN17-CO17) -> 0 | CQ17: =IF(OR($A17="",CH17=""),"",IF(CN17=0,"No Charges",IF(CP17<=0,"Paid",IF(CO17>0,"Partial","Pending")))) | CU17: =IF($A17="","",SUMIFS('Consumable Usage'!$E:$E,'Consumable Usage'!$A:$A,$A17,'Consumable Usage'!$D:$D,10)) -> 0 | CV17: =IF($A17="","",SUMIFS('Nursing Charges'!$I:$I,'Nursing Charges'!$A:$A,$A17,'Nursing Charges'!$C:$C,10)) -> 0 | CW17: =IF($A17="","",CT17+(CV17-SUMIFS('Nursing Charges'!$J:$J,'Nursing Charges'!$A:$A,$A17,'Nursing Charges'!$C:$C,10))+(CU17-SUMIFS('Consumable Usage'!$F:$F,'Consumable Usage'!$A:$A,$A17,'Consumable Usage'!$D:$D,10))) -> 0 | CX17: =IF($A17="","",CT17+CV17+CU17) -> 0 | CZ17: =IF(CX17="","",CX17-CY17) -> 0 | DA17: =IF(OR($A17="",CR17=""),"",IF(CX17=0,"No Charges",IF(CZ17<=0,"Paid",IF(CY17>0,"Partial","Pending")))) | DE17: =IF($A17="","",SUMIFS('Consumable Usage'!$E:$E,'Consumable Usage'!$A:$A,$A17,'Consumable Usage'!$D:$D,11)) -> 0 | DF17: =IF($A17="","",SUMIFS('Nursing Charges'!$I:$I,'Nursing Charges'!$A:$A,$A17,'Nursing Charges'!$C:$C,11)) -> 0 | DG17: =IF($A17="","",DD17+(DF17-SUMIFS('Nursing Charges'!$J:$J,'Nursing Charges'!$A:$A,$A17,'Nursing Charges'!$C:$C,11))+(DE17-SUMIFS('Consumable Usage'!$F:$F,'Consumable Usage'!$A:$A,$A17,'Consumable Usage'!$D:$D,11))) -> 0 | DH17: =IF($A17="","",DD17+DF17+DE17) -> 0 | DJ17: =IF(DH17="","",DH17-DI17) -> 0 | DK17: =IF(OR($A17="",DB17=""),"",IF(DH17=0,"No Charges",IF(DJ17<=0,"Paid",IF(DI17>0,"Partial","Pending")))) | DO17: =IF($A17="","",SUMIFS('Consumable Usage'!$E:$E,'Consumable Usage'!$A:$A,$A17,'Consumable Usage'!$D:$D,12)) -> 0 | DP17: =IF($A17="","",SUMIFS('Nursing Charges'!$I:$I,'Nursing Charges'!$A:$A,$A17,'Nursing Charges'!$C:$C,12)) -> 0 | DQ17: =IF($A17="","",DN17+(DP17-SUMIFS('Nursing Charges'!$J:$J,'Nursing Charges'!$A:$A,$A17,'Nursing Charges'!$C:$C,12))+(DO17-SUMIFS('Consumable Usage'!$F:$F,'Consumable Usage'!$A:$A,$A17,'Consumable Usage'!$D:$D,12))) -> 0 | DR17: =IF($A17="","",DN17+DP17+DO17) -> 0 | DT17: =IF(DR17="","",DR17-DS17) -> 0 | DU17: =IF(OR($A17="",DL17=""),"",IF(DR17=0,"No Charges",IF(DT17<=0,"Paid",IF(DS17>0,"Partial","Pending")))) | DY17: =IF($A17="","",SUMIFS('Consumable Usage'!$E:$E,'Consumable Usage'!$A:$A,$A17,'Consumable Usage'!$D:$D,13)) -> 0 | DZ17: =IF($A17="","",SUMIFS('Nursing Charges'!$I:$I,'Nursing Charges'!$A:$A,$A17,'Nursing Charges'!$C:$C,13)) -> 0 | EA17: =IF($A17="","",DX17+(DZ17-SUMIFS('Nursing Charges'!$J:$J,'Nursing Charges'!$A:$A,$A17,'Nursing Charges'!$C:$C,13))+(DY17-SUMIFS('Consumable Usage'!$F:$F,'Consumable Usage'!$A:$A,$A17,'Consumable Usage'!$D:$D,13))) -> 0 | EB17: =IF($A17="","",DX17+DZ17+DY17) -> 0 | ED17: =IF(EB17="","",EB17-EC17) -> 0 | EE17: =IF(OR($A17="",DV17=""),"",IF(EB17=0,"No Charges",IF(ED17<=0,"Paid",IF(EC17>0,"Partial","Pending")))) | EI17: =IF($A17="","",SUMIFS('Consumable Usage'!$E:$E,'Consumable Usage'!$A:$A,$A17,'Consumable Usage'!$D:$D,14)) -> 0 | EJ17: =IF($A17="","",SUMIFS('Nursing Charges'!$I:$I,'Nursing Charges'!$A:$A,$A17,'Nursing Charges'!$C:$C,14)) -> 0 | EK17: =IF($A17="","",EH17+(EJ17-SUMIFS('Nursing Charges'!$J:$J,'Nursing Charges'!$A:$A,$A17,'Nursing Charges'!$C:$C,14))+(EI17-SUMIFS('Consumable Usage'!$F:$F,'Consumable Usage'!$A:$A,$A17,'Consumable Usage'!$D:$D,14))) -> 0 | EL17: =IF($A17="","",EH17+EJ17+EI17) -> 0 | EN17: =IF(EL17="","",EL17-EM17) -> 0 | EO17: =IF(OR($A17="",EF17=""),"",IF(EL17=0,"No Charges",IF(EN17<=0,"Paid",IF(EM17>0,"Partial","Pending")))) | ES17: =IF($A17="","",SUMIFS('Consumable Usage'!$E:$E,'Consumable Usage'!$A:$A,$A17,'Consumable Usage'!$D:$D,15)) -> 0 | ET17: =IF($A17="","",SUMIFS('Nursing Charges'!$I:$I,'Nursing Charges'!$A:$A,$A17,'Nursing Charges'!$C:$C,15)) -> 0 | EU17: =IF($A17="","",ER17+(ET17-SUMIFS('Nursing Charges'!$J:$J,'Nursing Charges'!$A:$A,$A17,'Nursing Charges'!$C:$C,15))+(ES17-SUMIFS('Consumable Usage'!$F:$F,'Consumable Usage'!$A:$A,$A17,'Consumable Usage'!$D:$D,15))) -> 0 | EV17: =IF($A17="","",ER17+ET17+ES17) -> 0 | EX17: =IF(EV17="","",EV17-EW17) -> 0 | EY17: =IF(OR($A17="",EP17=""),"",IF(EV17=0,"No Charges",IF(EX17<=0,"Paid",IF(EW17>0,"Partial","Pending")))) | FC17: =IF($A17="","",SUMIFS('Consumable Usage'!$E:$E,'Consumable Usage'!$A:$A,$A17,'Consumable Usage'!$D:$D,16)) -> 0 | FD17: =IF($A17="","",SUMIFS('Nursing Charges'!$I:$I,'Nursing Charges'!$A:$A,$A17,'Nursing Charges'!$C:$C,16)) -> 0 | FE17: =IF($A17="","",FB17+(FD17-SUMIFS('Nursing Charges'!$J:$J,'Nursing Charges'!$A:$A,$A17,'Nursing Charges'!$C:$C,16))+(FC17-SUMIFS('Consumable Usage'!$F:$F,'Consumable Usage'!$A:$A,$A17,'Consumable Usage'!$D:$D,16))) -> 0 | FF17: =IF($A17="","",FB17+FD17+FC17) -> 0 | FH17: =IF(FF17="","",FF17-FG17) -> 0 | FI17: =IF(OR($A17="",EZ17=""),"",IF(FF17=0,"No Charges",IF(FH17<=0,"Paid",IF(FG17>0,"Partial","Pending")))) | FM17: =IF($A17="","",SUMIFS('Consumable Usage'!$E:$E,'Consumable Usage'!$A:$A,$A17,'Consumable Usage'!$D:$D,16)) -> 0 | FN17: =IF($A17="","",SUMIFS('Nursing Charges'!$I:$I,'Nursing Charges'!$A:$A,$A17,'Nursing Charges'!$C:$C,16)) -> 0 | FO17: =IF($A17="","",FL17+(FN17-SUMIFS('Nursing Charges'!$J:$J,'Nursing Charges'!$A:$A,$A17,'Nursing Charges'!$C:$C,16))+(FM17-SUMIFS('Consumable Usage'!$F:$F,'Consumable Usage'!$A:$A,$A17,'Consumable Usage'!$D:$D,16))) -> 0 | FP17: =IF($A17="","",FL17+FN17+FM17) -> 0 | FR17: =IF(FP17="","",FP17-FQ17) -> 0 | FS17: =IF(OR($A17="",FJ17=""),"",IF(FP17=0,"No Charges",IF(FR17<=0,"Paid",IF(FQ17>0,"Partial","Pending"))))
A18: CC2026013 | B18: Manjula Gada | C18: SHAMITA | D18: 91 90294 96488 | E18: completed | I18: =IF($A18="","",SUMIFS('Consumable Usage'!$E:$E,'Consumable Usage'!$A:$A,$A18,'Consumable Usage'!$D:$D,1)) -> 0 | J18: =IF($A18="","",SUMIFS('Nursing Charges'!$I:$I,'Nursing Charges'!$A:$A,$A18,'Nursing Charges'!$C:$C,1)) -> 0 | K18: =IF($A18="","",H18+(J18-SUMIFS('Nursing Charges'!$J:$J,'Nursing Charges'!$A:$A,$A18,'Nursing Charges'!$C:$C,1))+(I18-SUMIFS('Consumable Usage'!$F:$F,'Consumable Usage'!$A:$A,$A18,'Consumable Usage'!$D:$D,1))) -> 0 | L18: =IF($A18="","",H18+J18+I18) -> 0 | N18: =IF(L18="","",L18-M18) -> 0 | O18: =IF(OR($A18="",F18=""),"",IF(L18=0,"No Charges",IF(N18<=0,"Paid",IF(M18>0,"Partial","Pending")))) | S18: =IF($A18="","",SUMIFS('Consumable Usage'!$E:$E,'Consumable Usage'!$A:$A,$A18,'Consumable Usage'!$D:$D,2)) -> 0 | T18: =IF($A18="","",SUMIFS('Nursing Charges'!$I:$I,'Nursing Charges'!$A:$A,$A18,'Nursing Charges'!$C:$C,2)) -> 0 | U18: =IF($A18="","",R18+(T18-SUMIFS('Nursing Charges'!$J:$J,'Nursing Charges'!$A:$A,$A18,'Nursing Charges'!$C:$C,2))+(S18-SUMIFS('Consumable Usage'!$F:$F,'Consumable Usage'!$A:$A,$A18,'Consumable Usage'!$D:$D,2))) -> 0 | V18: =IF($A18="","",R18+T18+S18) -> 0 | X18: =IF(V18="","",V18-W18) -> 0 | Y18: =IF(OR($A18="",P18=""),"",IF(V18=0,"No Charges",IF(X18<=0,"Paid",IF(W18>0,"Partial","Pending")))) | AC18: =IF($A18="","",SUMIFS('Consumable Usage'!$E:$E,'Consumable Usage'!$A:$A,$A18,'Consumable Usage'!$D:$D,3)) -> 0 | AD18: =IF($A18="","",SUMIFS('Nursing Charges'!$I:$I,'Nursing Charges'!$A:$A,$A18,'Nursing Charges'!$C:$C,3)) -> 0 | AE18: =IF($A18="","",AB18+(AD18-SUMIFS('Nursing Charges'!$J:$J,'Nursing Charges'!$A:$A,$A18,'Nursing Charges'!$C:$C,3))+(AC18-SUMIFS('Consumable Usage'!$F:$F,'Consumable Usage'!$A:$A,$A18,'Consumable Usage'!$D:$D,3))) -> 0 | AF18: =IF($A18="","",AB18+AD18+AC18) -> 0 | AH18: =IF(AF18="","",AF18-AG18) -> 0 | AI18: =IF(OR($A18="",Z18=""),"",IF(AF18=0,"No Charges",IF(AH18<=0,"Paid",IF(AG18>0,"Partial","Pending")))) | AM18: =IF($A18="","",SUMIFS('Consumable Usage'!$E:$E,'Consumable Usage'!$A:$A,$A18,'Consumable Usage'!$D:$D,4)) -> 0 | AN18: =IF($A18="","",SUMIFS('Nursing Charges'!$I:$I,'Nursing Charges'!$A:$A,$A18,'Nursing Charges'!$C:$C,4)) -> 0 | AO18: =IF($A18="","",AL18+(AN18-SUMIFS('Nursing Charges'!$J:$J,'Nursing Charges'!$A:$A,$A18,'Nursing Charges'!$C:$C,4))+(AM18-SUMIFS('Consumable Usage'!$F:$F,'Consumable Usage'!$A:$A,$A18,'Consumable Usage'!$D:$D,4))) -> 0 | AP18: =IF($A18="","",AL18+AN18+AM18) -> 0 | AR18: =IF(AP18="","",AP18-AQ18) -> 0 | AS18: =IF(OR($A18="",AJ18=""),"",IF(AP18=0,"No Charges",IF(AR18<=0,"Paid",IF(AQ18>0,"Partial","Pending")))) | AW18: =IF($A18="","",SUMIFS('Consumable Usage'!$E:$E,'Consumable Usage'!$A:$A,$A18,'Consumable Usage'!$D:$D,5)) -> 0 | AX18: =IF($A18="","",SUMIFS('Nursing Charges'!$I:$I,'Nursing Charges'!$A:$A,$A18,'Nursing Charges'!$C:$C,5)) -> 0 | AY18: =IF($A18="","",AV18+(AX18-SUMIFS('Nursing Charges'!$J:$J,'Nursing Charges'!$A:$A,$A18,'Nursing Charges'!$C:$C,5))+(AW18-SUMIFS('Consumable Usage'!$F:$F,'Consumable Usage'!$A:$A,$A18,'Consumable Usage'!$D:$D,5))) -> 0 | AZ18: =IF($A18="","",AV18+AX18+AW18) -> 0 | BB18: =IF(AZ18="","",AZ18-BA18) -> 0 | BC18: =IF(OR($A18="",AT18=""),"",IF(AZ18=0,"No Charges",IF(BB18<=0,"Paid",IF(BA18>0,"Partial","Pending")))) | BG18: =IF($A18="","",SUMIFS('Consumable Usage'!$E:$E,'Consumable Usage'!$A:$A,$A18,'Consumable Usage'!$D:$D,6)) -> 0 | BH18: =IF($A18="","",SUMIFS('Nursing Charges'!$I:$I,'Nursing Charges'!$A:$A,$A18,'Nursing Charges'!$C:$C,6)) -> 0 | BI18: =IF($A18="","",BF18+(BH18-SUMIFS('Nursing Charges'!$J:$J,'Nursing Charges'!$A:$A,$A18,'Nursing Charges'!$C:$C,6))+(BG18-SUMIFS('Consumable Usage'!$F:$F,'Consumable Usage'!$A:$A,$A18,'Consumable Usage'!$D:$D,6))) -> 0 | BJ18: =IF($A18="","",BF18+BH18+BG18) -> 0 | BL18: =IF(BJ18="","",BJ18-BK18) -> 0 | BM18: =IF(OR($A18="",BD18=""),"",IF(BJ18=0,"No Charges",IF(BL18<=0,"Paid",IF(BK18>0,"Partial","Pending")))) | BQ18: =IF($A18="","",SUMIFS('Consumable Usage'!$E:$E,'Consumable Usage'!$A:$A,$A18,'Consumable Usage'!$D:$D,7)) -> 0 | BR18: =IF($A18="","",SUMIFS('Nursing Charges'!$I:$I,'Nursing Charges'!$A:$A,$A18,'Nursing Charges'!$C:$C,7)) -> 0 | BS18: =IF($A18="","",BP18+(BR18-SUMIFS('Nursing Charges'!$J:$J,'Nursing Charges'!$A:$A,$A18,'Nursing Charges'!$C:$C,7))+(BQ18-SUMIFS('Consumable Usage'!$F:$F,'Consumable Usage'!$A:$A,$A18,'Consumable Usage'!$D:$D,7))) -> 0 | BT18: =IF($A18="","",BP18+BR18+BQ18) -> 0 | BV18: =IF(BT18="","",BT18-BU18) -> 0 | BW18: =IF(OR($A18="",BN18=""),"",IF(BT18=0,"No Charges",IF(BV18<=0,"Paid",IF(BU18>0,"Partial","Pending")))) | CA18: =IF($A18="","",SUMIFS('Consumable Usage'!$E:$E,'Consumable Usage'!$A:$A,$A18,'Consumable Usage'!$D:$D,8)) -> 0 | CB18: =IF($A18="","",SUMIFS('Nursing Charges'!$I:$I,'Nursing Charges'!$A:$A,$A18,'Nursing Charges'!$C:$C,8)) -> 0 | CC18: =IF($A18="","",BZ18+(CB18-SUMIFS('Nursing Charges'!$J:$J,'Nursing Charges'!$A:$A,$A18,'Nursing Charges'!$C:$C,8))+(CA18-SUMIFS('Consumable Usage'!$F:$F,'Consumable Usage'!$A:$A,$A18,'Consumable Usage'!$D:$D,8))) -> 0 | CD18: =IF($A18="","",BZ18+CB18+CA18) -> 0 | CF18: =IF(CD18="","",CD18-CE18) -> 0 | CG18: =IF(OR($A18="",BX18=""),"",IF(CD18=0,"No Charges",IF(CF18<=0,"Paid",IF(CE18>0,"Partial","Pending")))) | CK18: =IF($A18="","",SUMIFS('Consumable Usage'!$E:$E,'Consumable Usage'!$A:$A,$A18,'Consumable Usage'!$D:$D,9)) -> 0 | CL18: =IF($A18="","",SUMIFS('Nursing Charges'!$I:$I,'Nursing Charges'!$A:$A,$A18,'Nursing Charges'!$C:$C,9)) -> 0 | CM18: =IF($A18="","",CJ18+(CL18-SUMIFS('Nursing Charges'!$J:$J,'Nursing Charges'!$A:$A,$A18,'Nursing Charges'!$C:$C,9))+(CK18-SUMIFS('Consumable Usage'!$F:$F,'Consumable Usage'!$A:$A,$A18,'Consumable Usage'!$D:$D,9))) -> 0 | CN18: =IF($A18="","",CJ18+CL18+CK18) -> 0 | CP18: =IF(CN18="","",CN18-CO18) -> 0 | CQ18: =IF(OR($A18="",CH18=""),"",IF(CN18=0,"No Charges",IF(CP18<=0,"Paid",IF(CO18>0,"Partial","Pending")))) | CU18: =IF($A18="","",SUMIFS('Consumable Usage'!$E:$E,'Consumable Usage'!$A:$A,$A18,'Consumable Usage'!$D:$D,10)) -> 0 | CV18: =IF($A18="","",SUMIFS('Nursing Charges'!$I:$I,'Nursing Charges'!$A:$A,$A18,'Nursing Charges'!$C:$C,10)) -> 0 | CW18: =IF($A18="","",CT18+(CV18-SUMIFS('Nursing Charges'!$J:$J,'Nursing Charges'!$A:$A,$A18,'Nursing Charges'!$C:$C,10))+(CU18-SUMIFS('Consumable Usage'!$F:$F,'Consumable Usage'!$A:$A,$A18,'Consumable Usage'!$D:$D,10))) -> 0 | CX18: =IF($A18="","",CT18+CV18+CU18) -> 0 | CZ18: =IF(CX18="","",CX18-CY18) -> 0 | DA18: =IF(OR($A18="",CR18=""),"",IF(CX18=0,"No Charges",IF(CZ18<=0,"Paid",IF(CY18>0,"Partial","Pending")))) | DE18: =IF($A18="","",SUMIFS('Consumable Usage'!$E:$E,'Consumable Usage'!$A:$A,$A18,'Consumable Usage'!$D:$D,11)) -> 0 | DF18: =IF($A18="","",SUMIFS('Nursing Charges'!$I:$I,'Nursing Charges'!$A:$A,$A18,'Nursing Charges'!$C:$C,11)) -> 0 | DG18: =IF($A18="","",DD18+(DF18-SUMIFS('Nursing Charges'!$J:$J,'Nursing Charges'!$A:$A,$A18,'Nursing Charges'!$C:$C,11))+(DE18-SUMIFS('Consumable Usage'!$F:$F,'Consumable Usage'!$A:$A,$A18,'Consumable Usage'!$D:$D,11))) -> 0 | DH18: =IF($A18="","",DD18+DF18+DE18) -> 0 | DJ18: =IF(DH18="","",DH18-DI18) -> 0 | DK18: =IF(OR($A18="",DB18=""),"",IF(DH18=0,"No Charges",IF(DJ18<=0,"Paid",IF(DI18>0,"Partial","Pending")))) | DO18: =IF($A18="","",SUMIFS('Consumable Usage'!$E:$E,'Consumable Usage'!$A:$A,$A18,'Consumable Usage'!$D:$D,12)) -> 0 | DP18: =IF($A18="","",SUMIFS('Nursing Charges'!$I:$I,'Nursing Charges'!$A:$A,$A18,'Nursing Charges'!$C:$C,12)) -> 0 | DQ18: =IF($A18="","",DN18+(DP18-SUMIFS('Nursing Charges'!$J:$J,'Nursing Charges'!$A:$A,$A18,'Nursing Charges'!$C:$C,12))+(DO18-SUMIFS('Consumable Usage'!$F:$F,'Consumable Usage'!$A:$A,$A18,'Consumable Usage'!$D:$D,12))) -> 0 | DR18: =IF($A18="","",DN18+DP18+DO18) -> 0 | DT18: =IF(DR18="","",DR18-DS18) -> 0 | DU18: =IF(OR($A18="",DL18=""),"",IF(DR18=0,"No Charges",IF(DT18<=0,"Paid",IF(DS18>0,"Partial","Pending")))) | DY18: =IF($A18="","",SUMIFS('Consumable Usage'!$E:$E,'Consumable Usage'!$A:$A,$A18,'Consumable Usage'!$D:$D,13)) -> 0 | DZ18: =IF($A18="","",SUMIFS('Nursing Charges'!$I:$I,'Nursing Charges'!$A:$A,$A18,'Nursing Charges'!$C:$C,13)) -> 0 | EA18: =IF($A18="","",DX18+(DZ18-SUMIFS('Nursing Charges'!$J:$J,'Nursing Charges'!$A:$A,$A18,'Nursing Charges'!$C:$C,13))+(DY18-SUMIFS('Consumable Usage'!$F:$F,'Consumable Usage'!$A:$A,$A18,'Consumable Usage'!$D:$D,13))) -> 0 | EB18: =IF($A18="","",DX18+DZ18+DY18) -> 0 | ED18: =IF(EB18="","",EB18-EC18) -> 0 | EE18: =IF(OR($A18="",DV18=""),"",IF(EB18=0,"No Charges",IF(ED18<=0,"Paid",IF(EC18>0,"Partial","Pending")))) | EI18: =IF($A18="","",SUMIFS('Consumable Usage'!$E:$E,'Consumable Usage'!$A:$A,$A18,'Consumable Usage'!$D:$D,14)) -> 0 | EJ18: =IF($A18="","",SUMIFS('Nursing Charges'!$I:$I,'Nursing Charges'!$A:$A,$A18,'Nursing Charges'!$C:$C,14)) -> 0 | EK18: =IF($A18="","",EH18+(EJ18-SUMIFS('Nursing Charges'!$J:$J,'Nursing Charges'!$A:$A,$A18,'Nursing Charges'!$C:$C,14))+(EI18-SUMIFS('Consumable Usage'!$F:$F,'Consumable Usage'!$A:$A,$A18,'Consumable Usage'!$D:$D,14))) -> 0 | EL18: =IF($A18="","",EH18+EJ18+EI18) -> 0 | EN18: =IF(EL18="","",EL18-EM18) -> 0 | EO18: =IF(OR($A18="",EF18=""),"",IF(EL18=0,"No Charges",IF(EN18<=0,"Paid",IF(EM18>0,"Partial","Pending")))) | ES18: =IF($A18="","",SUMIFS('Consumable Usage'!$E:$E,'Consumable Usage'!$A:$A,$A18,'Consumable Usage'!$D:$D,15)) -> 0 | ET18: =IF($A18="","",SUMIFS('Nursing Charges'!$I:$I,'Nursing Charges'!$A:$A,$A18,'Nursing Charges'!$C:$C,15)) -> 0 | EU18: =IF($A18="","",ER18+(ET18-SUMIFS('Nursing Charges'!$J:$J,'Nursing Charges'!$A:$A,$A18,'Nursing Charges'!$C:$C,15))+(ES18-SUMIFS('Consumable Usage'!$F:$F,'Consumable Usage'!$A:$A,$A18,'Consumable Usage'!$D:$D,15))) -> 0 | EV18: =IF($A18="","",ER18+ET18+ES18) -> 0 | EX18: =IF(EV18="","",EV18-EW18) -> 0 | EY18: =IF(OR($A18="",EP18=""),"",IF(EV18=0,"No Charges",IF(EX18<=0,"Paid",IF(EW18>0,"Partial","Pending")))) | FC18: =IF($A18="","",SUMIFS('Consumable Usage'!$E:$E,'Consumable Usage'!$A:$A,$A18,'Consumable Usage'!$D:$D,16)) -> 0 | FD18: =IF($A18="","",SUMIFS('Nursing Charges'!$I:$I,'Nursing Charges'!$A:$A,$A18,'Nursing Charges'!$C:$C,16)) -> 0 | FE18: =IF($A18="","",FB18+(FD18-SUMIFS('Nursing Charges'!$J:$J,'Nursing Charges'!$A:$A,$A18,'Nursing Charges'!$C:$C,16))+(FC18-SUMIFS('Consumable Usage'!$F:$F,'Consumable Usage'!$A:$A,$A18,'Consumable Usage'!$D:$D,16))) -> 0 | FF18: =IF($A18="","",FB18+FD18+FC18) -> 0 | FH18: =IF(FF18="","",FF18-FG18) -> 0 | FI18: =IF(OR($A18="",EZ18=""),"",IF(FF18=0,"No Charges",IF(FH18<=0,"Paid",IF(FG18>0,"Partial","Pending")))) | FM18: =IF($A18="","",SUMIFS('Consumable Usage'!$E:$E,'Consumable Usage'!$A:$A,$A18,'Consumable Usage'!$D:$D,16)) -> 0 | FN18: =IF($A18="","",SUMIFS('Nursing Charges'!$I:$I,'Nursing Charges'!$A:$A,$A18,'Nursing Charges'!$C:$C,16)) -> 0 | FO18: =IF($A18="","",FL18+(FN18-SUMIFS('Nursing Charges'!$J:$J,'Nursing Charges'!$A:$A,$A18,'Nursing Charges'!$C:$C,16))+(FM18-SUMIFS('Consumable Usage'!$F:$F,'Consumable Usage'!$A:$A,$A18,'Consumable Usage'!$D:$D,16))) -> 0 | FP18: =IF($A18="","",FL18+FN18+FM18) -> 0 | FR18: =IF(FP18="","",FP18-FQ18) -> 0 | FS18: =IF(OR($A18="",FJ18=""),"",IF(FP18=0,"No Charges",IF(FR18<=0,"Paid",IF(FQ18>0,"Partial","Pending"))))
A19: CC2026014 | B19: RAHUL JAIN | E19: nurse neeeds to be assigned | I19: =IF($A19="","",SUMIFS('Consumable Usage'!$E:$E,'Consumable Usage'!$A:$A,$A19,'Consumable Usage'!$D:$D,1)) -> 0 | J19: =IF($A19="","",SUMIFS('Nursing Charges'!$I:$I,'Nursing Charges'!$A:$A,$A19,'Nursing Charges'!$C:$C,1)) -> 0 | K19: =IF($A19="","",H19+(J19-SUMIFS('Nursing Charges'!$J:$J,'Nursing Charges'!$A:$A,$A19,'Nursing Charges'!$C:$C,1))+(I19-SUMIFS('Consumable Usage'!$F:$F,'Consumable Usage'!$A:$A,$A19,'Consumable Usage'!$D:$D,1))) -> 0 | L19: =IF($A19="","",H19+J19+I19) -> 0 | N19: =IF(L19="","",L19-M19) -> 0 | O19: =IF(OR($A19="",F19=""),"",IF(L19=0,"No Charges",IF(N19<=0,"Paid",IF(M19>0,"Partial","Pending")))) | S19: =IF($A19="","",SUMIFS('Consumable Usage'!$E:$E,'Consumable Usage'!$A:$A,$A19,'Consumable Usage'!$D:$D,2)) -> 0 | T19: =IF($A19="","",SUMIFS('Nursing Charges'!$I:$I,'Nursing Charges'!$A:$A,$A19,'Nursing Charges'!$C:$C,2)) -> 0 | U19: =IF($A19="","",R19+(T19-SUMIFS('Nursing Charges'!$J:$J,'Nursing Charges'!$A:$A,$A19,'Nursing Charges'!$C:$C,2))+(S19-SUMIFS('Consumable Usage'!$F:$F,'Consumable Usage'!$A:$A,$A19,'Consumable Usage'!$D:$D,2))) -> 0 | V19: =IF($A19="","",R19+T19+S19) -> 0 | X19: =IF(V19="","",V19-W19) -> 0 | Y19: =IF(OR($A19="",P19=""),"",IF(V19=0,"No Charges",IF(X19<=0,"Paid",IF(W19>0,"Partial","Pending")))) | AC19: =IF($A19="","",SUMIFS('Consumable Usage'!$E:$E,'Consumable Usage'!$A:$A,$A19,'Consumable Usage'!$D:$D,3)) -> 0 | AD19: =IF($A19="","",SUMIFS('Nursing Charges'!$I:$I,'Nursing Charges'!$A:$A,$A19,'Nursing Charges'!$C:$C,3)) -> 0 | AE19: =IF($A19="","",AB19+(AD19-SUMIFS('Nursing Charges'!$J:$J,'Nursing Charges'!$A:$A,$A19,'Nursing Charges'!$C:$C,3))+(AC19-SUMIFS('Consumable Usage'!$F:$F,'Consumable Usage'!$A:$A,$A19,'Consumable Usage'!$D:$D,3))) -> 0 | AF19: =IF($A19="","",AB19+AD19+AC19) -> 0 | AH19: =IF(AF19="","",AF19-AG19) -> 0 | AI19: =IF(OR($A19="",Z19=""),"",IF(AF19=0,"No Charges",IF(AH19<=0,"Paid",IF(AG19>0,"Partial","Pending")))) | AM19: =IF($A19="","",SUMIFS('Consumable Usage'!$E:$E,'Consumable Usage'!$A:$A,$A19,'Consumable Usage'!$D:$D,4)) -> 0 | AN19: =IF($A19="","",SUMIFS('Nursing Charges'!$I:$I,'Nursing Charges'!$A:$A,$A19,'Nursing Charges'!$C:$C,4)) -> 0 | AO19: =IF($A19="","",AL19+(AN19-SUMIFS('Nursing Charges'!$J:$J,'Nursing Charges'!$A:$A,$A19,'Nursing Charges'!$C:$C,4))+(AM19-SUMIFS('Consumable Usage'!$F:$F,'Consumable Usage'!$A:$A,$A19,'Consumable Usage'!$D:$D,4))) -> 0 | AP19: =IF($A19="","",AL19+AN19+AM19) -> 0 | AR19: =IF(AP19="","",AP19-AQ19) -> 0 | AS19: =IF(OR($A19="",AJ19=""),"",IF(AP19=0,"No Charges",IF(AR19<=0,"Paid",IF(AQ19>0,"Partial","Pending")))) | AW19: =IF($A19="","",SUMIFS('Consumable Usage'!$E:$E,'Consumable Usage'!$A:$A,$A19,'Consumable Usage'!$D:$D,5)) -> 0 | AX19: =IF($A19="","",SUMIFS('Nursing Charges'!$I:$I,'Nursing Charges'!$A:$A,$A19,'Nursing Charges'!$C:$C,5)) -> 0 | AY19: =IF($A19="","",AV19+(AX19-SUMIFS('Nursing Charges'!$J:$J,'Nursing Charges'!$A:$A,$A19,'Nursing Charges'!$C:$C,5))+(AW19-SUMIFS('Consumable Usage'!$F:$F,'Consumable Usage'!$A:$A,$A19,'Consumable Usage'!$D:$D,5))) -> 0 | AZ19: =IF($A19="","",AV19+AX19+AW19) -> 0 | BB19: =IF(AZ19="","",AZ19-BA19) -> 0 | BC19: =IF(OR($A19="",AT19=""),"",IF(AZ19=0,"No Charges",IF(BB19<=0,"Paid",IF(BA19>0,"Partial","Pending")))) | BG19: =IF($A19="","",SUMIFS('Consumable Usage'!$E:$E,'Consumable Usage'!$A:$A,$A19,'Consumable Usage'!$D:$D,6)) -> 0 | BH19: =IF($A19="","",SUMIFS('Nursing Charges'!$I:$I,'Nursing Charges'!$A:$A,$A19,'Nursing Charges'!$C:$C,6)) -> 0 | BI19: =IF($A19="","",BF19+(BH19-SUMIFS('Nursing Charges'!$J:$J,'Nursing Charges'!$A:$A,$A19,'Nursing Charges'!$C:$C,6))+(BG19-SUMIFS('Consumable Usage'!$F:$F,'Consumable Usage'!$A:$A,$A19,'Consumable Usage'!$D:$D,6))) -> 0 | BJ19: =IF($A19="","",BF19+BH19+BG19) -> 0 | BL19: =IF(BJ19="","",BJ19-BK19) -> 0 | BM19: =IF(OR($A19="",BD19=""),"",IF(BJ19=0,"No Charges",IF(BL19<=0,"Paid",IF(BK19>0,"Partial","Pending")))) | BQ19: =IF($A19="","",SUMIFS('Consumable Usage'!$E:$E,'Consumable Usage'!$A:$A,$A19,'Consumable Usage'!$D:$D,7)) -> 0 | BR19: =IF($A19="","",SUMIFS('Nursing Charges'!$I:$I,'Nursing Charges'!$A:$A,$A19,'Nursing Charges'!$C:$C,7)) -> 0 | BS19: =IF($A19="","",BP19+(BR19-SUMIFS('Nursing Charges'!$J:$J,'Nursing Charges'!$A:$A,$A19,'Nursing Charges'!$C:$C,7))+(BQ19-SUMIFS('Consumable Usage'!$F:$F,'Consumable Usage'!$A:$A,$A19,'Consumable Usage'!$D:$D,7))) -> 0 | BT19: =IF($A19="","",BP19+BR19+BQ19) -> 0 | BV19: =IF(BT19="","",BT19-BU19) -> 0 | BW19: =IF(OR($A19="",BN19=""),"",IF(BT19=0,"No Charges",IF(BV19<=0,"Paid",IF(BU19>0,"Partial","Pending")))) | CA19: =IF($A19="","",SUMIFS('Consumable Usage'!$E:$E,'Consumable Usage'!$A:$A,$A19,'Consumable Usage'!$D:$D,8)) -> 0 | CB19: =IF($A19="","",SUMIFS('Nursing Charges'!$I:$I,'Nursing Charges'!$A:$A,$A19,'Nursing Charges'!$C:$C,8)) -> 0 | CC19: =IF($A19="","",BZ19+(CB19-SUMIFS('Nursing Charges'!$J:$J,'Nursing Charges'!$A:$A,$A19,'Nursing Charges'!$C:$C,8))+(CA19-SUMIFS('Consumable Usage'!$F:$F,'Consumable Usage'!$A:$A,$A19,'Consumable Usage'!$D:$D,8))) -> 0 | CD19: =IF($A19="","",BZ19+CB19+CA19) -> 0 | CF19: =IF(CD19="","",CD19-CE19) -> 0 | CG19: =IF(OR($A19="",BX19=""),"",IF(CD19=0,"No Charges",IF(CF19<=0,"Paid",IF(CE19>0,"Partial","Pending")))) | CK19: =IF($A19="","",SUMIFS('Consumable Usage'!$E:$E,'Consumable Usage'!$A:$A,$A19,'Consumable Usage'!$D:$D,9)) -> 0 | CL19: =IF($A19="","",SUMIFS('Nursing Charges'!$I:$I,'Nursing Charges'!$A:$A,$A19,'Nursing Charges'!$C:$C,9)) -> 0 | CM19: =IF($A19="","",CJ19+(CL19-SUMIFS('Nursing Charges'!$J:$J,'Nursing Charges'!$A:$A,$A19,'Nursing Charges'!$C:$C,9))+(CK19-SUMIFS('Consumable Usage'!$F:$F,'Consumable Usage'!$A:$A,$A19,'Consumable Usage'!$D:$D,9))) -> 0 | CN19: =IF($A19="","",CJ19+CL19+CK19) -> 0 | CP19: =IF(CN19="","",CN19-CO19) -> 0 | CQ19: =IF(OR($A19="",CH19=""),"",IF(CN19=0,"No Charges",IF(CP19<=0,"Paid",IF(CO19>0,"Partial","Pending")))) | CU19: =IF($A19="","",SUMIFS('Consumable Usage'!$E:$E,'Consumable Usage'!$A:$A,$A19,'Consumable Usage'!$D:$D,10)) -> 0 | CV19: =IF($A19="","",SUMIFS('Nursing Charges'!$I:$I,'Nursing Charges'!$A:$A,$A19,'Nursing Charges'!$C:$C,10)) -> 0 | CW19: =IF($A19="","",CT19+(CV19-SUMIFS('Nursing Charges'!$J:$J,'Nursing Charges'!$A:$A,$A19,'Nursing Charges'!$C:$C,10))+(CU19-SUMIFS('Consumable Usage'!$F:$F,'Consumable Usage'!$A:$A,$A19,'Consumable Usage'!$D:$D,10))) -> 0 | CX19: =IF($A19="","",CT19+CV19+CU19) -> 0 | CZ19: =IF(CX19="","",CX19-CY19) -> 0 | DA19: =IF(OR($A19="",CR19=""),"",IF(CX19=0,"No Charges",IF(CZ19<=0,"Paid",IF(CY19>0,"Partial","Pending")))) | DE19: =IF($A19="","",SUMIFS('Consumable Usage'!$E:$E,'Consumable Usage'!$A:$A,$A19,'Consumable Usage'!$D:$D,11)) -> 0 | DF19: =IF($A19="","",SUMIFS('Nursing Charges'!$I:$I,'Nursing Charges'!$A:$A,$A19,'Nursing Charges'!$C:$C,11)) -> 0 | DG19: =IF($A19="","",DD19+(DF19-SUMIFS('Nursing Charges'!$J:$J,'Nursing Charges'!$A:$A,$A19,'Nursing Charges'!$C:$C,11))+(DE19-SUMIFS('Consumable Usage'!$F:$F,'Consumable Usage'!$A:$A,$A19,'Consumable Usage'!$D:$D,11))) -> 0 | DH19: =IF($A19="","",DD19+DF19+DE19) -> 0 | DJ19: =IF(DH19="","",DH19-DI19) -> 0 | DK19: =IF(OR($A19="",DB19=""),"",IF(DH19=0,"No Charges",IF(DJ19<=0,"Paid",IF(DI19>0,"Partial","Pending")))) | DO19: =IF($A19="","",SUMIFS('Consumable Usage'!$E:$E,'Consumable Usage'!$A:$A,$A19,'Consumable Usage'!$D:$D,12)) -> 0 | DP19: =IF($A19="","",SUMIFS('Nursing Charges'!$I:$I,'Nursing Charges'!$A:$A,$A19,'Nursing Charges'!$C:$C,12)) -> 0 | DQ19: =IF($A19="","",DN19+(DP19-SUMIFS('Nursing Charges'!$J:$J,'Nursing Charges'!$A:$A,$A19,'Nursing Charges'!$C:$C,12))+(DO19-SUMIFS('Consumable Usage'!$F:$F,'Consumable Usage'!$A:$A,$A19,'Consumable Usage'!$D:$D,12))) -> 0 | DR19: =IF($A19="","",DN19+DP19+DO19) -> 0 | DT19: =IF(DR19="","",DR19-DS19) -> 0 | DU19: =IF(OR($A19="",DL19=""),"",IF(DR19=0,"No Charges",IF(DT19<=0,"Paid",IF(DS19>0,"Partial","Pending")))) | DY19: =IF($A19="","",SUMIFS('Consumable Usage'!$E:$E,'Consumable Usage'!$A:$A,$A19,'Consumable Usage'!$D:$D,13)) -> 0 | DZ19: =IF($A19="","",SUMIFS('Nursing Charges'!$I:$I,'Nursing Charges'!$A:$A,$A19,'Nursing Charges'!$C:$C,13)) -> 0 | EA19: =IF($A19="","",DX19+(DZ19-SUMIFS('Nursing Charges'!$J:$J,'Nursing Charges'!$A:$A,$A19,'Nursing Charges'!$C:$C,13))+(DY19-SUMIFS('Consumable Usage'!$F:$F,'Consumable Usage'!$A:$A,$A19,'Consumable Usage'!$D:$D,13))) -> 0 | EB19: =IF($A19="","",DX19+DZ19+DY19) -> 0 | ED19: =IF(EB19="","",EB19-EC19) -> 0 | EE19: =IF(OR($A19="",DV19=""),"",IF(EB19=0,"No Charges",IF(ED19<=0,"Paid",IF(EC19>0,"Partial","Pending")))) | EI19: =IF($A19="","",SUMIFS('Consumable Usage'!$E:$E,'Consumable Usage'!$A:$A,$A19,'Consumable Usage'!$D:$D,14)) -> 0 | EJ19: =IF($A19="","",SUMIFS('Nursing Charges'!$I:$I,'Nursing Charges'!$A:$A,$A19,'Nursing Charges'!$C:$C,14)) -> 0 | EK19: =IF($A19="","",EH19+(EJ19-SUMIFS('Nursing Charges'!$J:$J,'Nursing Charges'!$A:$A,$A19,'Nursing Charges'!$C:$C,14))+(EI19-SUMIFS('Consumable Usage'!$F:$F,'Consumable Usage'!$A:$A,$A19,'Consumable Usage'!$D:$D,14))) -> 0 | EL19: =IF($A19="","",EH19+EJ19+EI19) -> 0 | EN19: =IF(EL19="","",EL19-EM19) -> 0 | EO19: =IF(OR($A19="",EF19=""),"",IF(EL19=0,"No Charges",IF(EN19<=0,"Paid",IF(EM19>0,"Partial","Pending")))) | ES19: =IF($A19="","",SUMIFS('Consumable Usage'!$E:$E,'Consumable Usage'!$A:$A,$A19,'Consumable Usage'!$D:$D,15)) -> 0 | ET19: =IF($A19="","",SUMIFS('Nursing Charges'!$I:$I,'Nursing Charges'!$A:$A,$A19,'Nursing Charges'!$C:$C,15)) -> 0 | EU19: =IF($A19="","",ER19+(ET19-SUMIFS('Nursing Charges'!$J:$J,'Nursing Charges'!$A:$A,$A19,'Nursing Charges'!$C:$C,15))+(ES19-SUMIFS('Consumable Usage'!$F:$F,'Consumable Usage'!$A:$A,$A19,'Consumable Usage'!$D:$D,15))) -> 0 | EV19: =IF($A19="","",ER19+ET19+ES19) -> 0 | EX19: =IF(EV19="","",EV19-EW19) -> 0 | EY19: =IF(OR($A19="",EP19=""),"",IF(EV19=0,"No Charges",IF(EX19<=0,"Paid",IF(EW19>0,"Partial","Pending")))) | FC19: =IF($A19="","",SUMIFS('Consumable Usage'!$E:$E,'Consumable Usage'!$A:$A,$A19,'Consumable Usage'!$D:$D,16)) -> 0 | FD19: =IF($A19="","",SUMIFS('Nursing Charges'!$I:$I,'Nursing Charges'!$A:$A,$A19,'Nursing Charges'!$C:$C,16)) -> 0 | FE19: =IF($A19="","",FB19+(FD19-SUMIFS('Nursing Charges'!$J:$J,'Nursing Charges'!$A:$A,$A19,'Nursing Charges'!$C:$C,16))+(FC19-SUMIFS('Consumable Usage'!$F:$F,'Consumable Usage'!$A:$A,$A19,'Consumable Usage'!$D:$D,16))) -> 0 | FF19: =IF($A19="","",FB19+FD19+FC19) -> 0 | FH19: =IF(FF19="","",FF19-FG19) -> 0 | FI19: =IF(OR($A19="",EZ19=""),"",IF(FF19=0,"No Charges",IF(FH19<=0,"Paid",IF(FG19>0,"Partial","Pending")))) | FM19: =IF($A19="","",SUMIFS('Consumable Usage'!$E:$E,'Consumable Usage'!$A:$A,$A19,'Consumable Usage'!$D:$D,16)) -> 0 | FN19: =IF($A19="","",SUMIFS('Nursing Charges'!$I:$I,'Nursing Charges'!$A:$A,$A19,'Nursing Charges'!$C:$C,16)) -> 0 | FO19: =IF($A19="","",FL19+(FN19-SUMIFS('Nursing Charges'!$J:$J,'Nursing Charges'!$A:$A,$A19,'Nursing Charges'!$C:$C,16))+(FM19-SUMIFS('Consumable Usage'!$F:$F,'Consumable Usage'!$A:$A,$A19,'Consumable Usage'!$D:$D,16))) -> 0 | FP19: =IF($A19="","",FL19+FN19+FM19) -> 0 | FR19: =IF(FP19="","",FP19-FQ19) -> 0 | FS19: =IF(OR($A19="",FJ19=""),"",IF(FP19=0,"No Charges",IF(FR19<=0,"Paid",IF(FQ19>0,"Partial","Pending"))))
A20: CC2026015 | B20: helen desouza | E20: nurse needs to be assigned | I20: =IF($A20="","",SUMIFS('Consumable Usage'!$E:$E,'Consumable Usage'!$A:$A,$A20,'Consumable Usage'!$D:$D,1)) -> 0 | J20: =IF($A20="","",SUMIFS('Nursing Charges'!$I:$I,'Nursing Charges'!$A:$A,$A20,'Nursing Charges'!$C:$C,1)) -> 0 | K20: =IF($A20="","",H20+(J20-SUMIFS('Nursing Charges'!$J:$J,'Nursing Charges'!$A:$A,$A20,'Nursing Charges'!$C:$C,1))+(I20-SUMIFS('Consumable Usage'!$F:$F,'Consumable Usage'!$A:$A,$A20,'Consumable Usage'!$D:$D,1))) -> 0 | L20: =IF($A20="","",H20+J20+I20) -> 0 | N20: =IF(L20="","",L20-M20) -> 0 | O20: =IF(OR($A20="",F20=""),"",IF(L20=0,"No Charges",IF(N20<=0,"Paid",IF(M20>0,"Partial","Pending")))) | S20: =IF($A20="","",SUMIFS('Consumable Usage'!$E:$E,'Consumable Usage'!$A:$A,$A20,'Consumable Usage'!$D:$D,2)) -> 0 | T20: =IF($A20="","",SUMIFS('Nursing Charges'!$I:$I,'Nursing Charges'!$A:$A,$A20,'Nursing Charges'!$C:$C,2)) -> 0 | U20: =IF($A20="","",R20+(T20-SUMIFS('Nursing Charges'!$J:$J,'Nursing Charges'!$A:$A,$A20,'Nursing Charges'!$C:$C,2))+(S20-SUMIFS('Consumable Usage'!$F:$F,'Consumable Usage'!$A:$A,$A20,'Consumable Usage'!$D:$D,2))) -> 0 | V20: =IF($A20="","",R20+T20+S20) -> 0 | X20: =IF(V20="","",V20-W20) -> 0 | Y20: =IF(OR($A20="",P20=""),"",IF(V20=0,"No Charges",IF(X20<=0,"Paid",IF(W20>0,"Partial","Pending")))) | AC20: =IF($A20="","",SUMIFS('Consumable Usage'!$E:$E,'Consumable Usage'!$A:$A,$A20,'Consumable Usage'!$D:$D,3)) -> 0 | AD20: =IF($A20="","",SUMIFS('Nursing Charges'!$I:$I,'Nursing Charges'!$A:$A,$A20,'Nursing Charges'!$C:$C,3)) -> 0 | AE20: =IF($A20="","",AB20+(AD20-SUMIFS('Nursing Charges'!$J:$J,'Nursing Charges'!$A:$A,$A20,'Nursing Charges'!$C:$C,3))+(AC20-SUMIFS('Consumable Usage'!$F:$F,'Consumable Usage'!$A:$A,$A20,'Consumable Usage'!$D:$D,3))) -> 0 | AF20: =IF($A20="","",AB20+AD20+AC20) -> 0 | AH20: =IF(AF20="","",AF20-AG20) -> 0 | AI20: =IF(OR($A20="",Z20=""),"",IF(AF20=0,"No Charges",IF(AH20<=0,"Paid",IF(AG20>0,"Partial","Pending")))) | AM20: =IF($A20="","",SUMIFS('Consumable Usage'!$E:$E,'Consumable Usage'!$A:$A,$A20,'Consumable Usage'!$D:$D,4)) -> 0 | AN20: =IF($A20="","",SUMIFS('Nursing Charges'!$I:$I,'Nursing Charges'!$A:$A,$A20,'Nursing Charges'!$C:$C,4)) -> 0 | AO20: =IF($A20="","",AL20+(AN20-SUMIFS('Nursing Charges'!$J:$J,'Nursing Charges'!$A:$A,$A20,'Nursing Charges'!$C:$C,4))+(AM20-SUMIFS('Consumable Usage'!$F:$F,'Consumable Usage'!$A:$A,$A20,'Consumable Usage'!$D:$D,4))) -> 0 | AP20: =IF($A20="","",AL20+AN20+AM20) -> 0 | AR20: =IF(AP20="","",AP20-AQ20) -> 0 | AS20: =IF(OR($A20="",AJ20=""),"",IF(AP20=0,"No Charges",IF(AR20<=0,"Paid",IF(AQ20>0,"Partial","Pending")))) | AW20: =IF($A20="","",SUMIFS('Consumable Usage'!$E:$E,'Consumable Usage'!$A:$A,$A20,'Consumable Usage'!$D:$D,5)) -> 0 | AX20: =IF($A20="","",SUMIFS('Nursing Charges'!$I:$I,'Nursing Charges'!$A:$A,$A20,'Nursing Charges'!$C:$C,5)) -> 0 | AY20: =IF($A20="","",AV20+(AX20-SUMIFS('Nursing Charges'!$J:$J,'Nursing Charges'!$A:$A,$A20,'Nursing Charges'!$C:$C,5))+(AW20-SUMIFS('Consumable Usage'!$F:$F,'Consumable Usage'!$A:$A,$A20,'Consumable Usage'!$D:$D,5))) -> 0 | AZ20: =IF($A20="","",AV20+AX20+AW20) -> 0 | BB20: =IF(AZ20="","",AZ20-BA20) -> 0 | BC20: =IF(OR($A20="",AT20=""),"",IF(AZ20=0,"No Charges",IF(BB20<=0,"Paid",IF(BA20>0,"Partial","Pending")))) | BG20: =IF($A20="","",SUMIFS('Consumable Usage'!$E:$E,'Consumable Usage'!$A:$A,$A20,'Consumable Usage'!$D:$D,6)) -> 0 | BH20: =IF($A20="","",SUMIFS('Nursing Charges'!$I:$I,'Nursing Charges'!$A:$A,$A20,'Nursing Charges'!$C:$C,6)) -> 0 | BI20: =IF($A20="","",BF20+(BH20-SUMIFS('Nursing Charges'!$J:$J,'Nursing Charges'!$A:$A,$A20,'Nursing Charges'!$C:$C,6))+(BG20-SUMIFS('Consumable Usage'!$F:$F,'Consumable Usage'!$A:$A,$A20,'Consumable Usage'!$D:$D,6))) -> 0 | BJ20: =IF($A20="","",BF20+BH20+BG20) -> 0 | BL20: =IF(BJ20="","",BJ20-BK20) -> 0 | BM20: =IF(OR($A20="",BD20=""),"",IF(BJ20=0,"No Charges",IF(BL20<=0,"Paid",IF(BK20>0,"Partial","Pending")))) | BQ20: =IF($A20="","",SUMIFS('Consumable Usage'!$E:$E,'Consumable Usage'!$A:$A,$A20,'Consumable Usage'!$D:$D,7)) -> 0 | BR20: =IF($A20="","",SUMIFS('Nursing Charges'!$I:$I,'Nursing Charges'!$A:$A,$A20,'Nursing Charges'!$C:$C,7)) -> 0 | BS20: =IF($A20="","",BP20+(BR20-SUMIFS('Nursing Charges'!$J:$J,'Nursing Charges'!$A:$A,$A20,'Nursing Charges'!$C:$C,7))+(BQ20-SUMIFS('Consumable Usage'!$F:$F,'Consumable Usage'!$A:$A,$A20,'Consumable Usage'!$D:$D,7))) -> 0 | BT20: =IF($A20="","",BP20+BR20+BQ20) -> 0 | BV20: =IF(BT20="","",BT20-BU20) -> 0 | BW20: =IF(OR($A20="",BN20=""),"",IF(BT20=0,"No Charges",IF(BV20<=0,"Paid",IF(BU20>0,"Partial","Pending")))) | CA20: =IF($A20="","",SUMIFS('Consumable Usage'!$E:$E,'Consumable Usage'!$A:$A,$A20,'Consumable Usage'!$D:$D,8)) -> 0 | CB20: =IF($A20="","",SUMIFS('Nursing Charges'!$I:$I,'Nursing Charges'!$A:$A,$A20,'Nursing Charges'!$C:$C,8)) -> 0 | CC20: =IF($A20="","",BZ20+(CB20-SUMIFS('Nursing Charges'!$J:$J,'Nursing Charges'!$A:$A,$A20,'Nursing Charges'!$C:$C,8))+(CA20-SUMIFS('Consumable Usage'!$F:$F,'Consumable Usage'!$A:$A,$A20,'Consumable Usage'!$D:$D,8))) -> 0 | CD20: =IF($A20="","",BZ20+CB20+CA20) -> 0 | CF20: =IF(CD20="","",CD20-CE20) -> 0 | CG20: =IF(OR($A20="",BX20=""),"",IF(CD20=0,"No Charges",IF(CF20<=0,"Paid",IF(CE20>0,"Partial","Pending")))) | CK20: =IF($A20="","",SUMIFS('Consumable Usage'!$E:$E,'Consumable Usage'!$A:$A,$A20,'Consumable Usage'!$D:$D,9)) -> 0 | CL20: =IF($A20="","",SUMIFS('Nursing Charges'!$I:$I,'Nursing Charges'!$A:$A,$A20,'Nursing Charges'!$C:$C,9)) -> 0 | CM20: =IF($A20="","",CJ20+(CL20-SUMIFS('Nursing Charges'!$J:$J,'Nursing Charges'!$A:$A,$A20,'Nursing Charges'!$C:$C,9))+(CK20-SUMIFS('Consumable Usage'!$F:$F,'Consumable Usage'!$A:$A,$A20,'Consumable Usage'!$D:$D,9))) -> 0 | CN20: =IF($A20="","",CJ20+CL20+CK20) -> 0 | CP20: =IF(CN20="","",CN20-CO20) -> 0 | CQ20: =IF(OR($A20="",CH20=""),"",IF(CN20=0,"No Charges",IF(CP20<=0,"Paid",IF(CO20>0,"Partial","Pending")))) | CU20: =IF($A20="","",SUMIFS('Consumable Usage'!$E:$E,'Consumable Usage'!$A:$A,$A20,'Consumable Usage'!$D:$D,10)) -> 0 | CV20: =IF($A20="","",SUMIFS('Nursing Charges'!$I:$I,'Nursing Charges'!$A:$A,$A20,'Nursing Charges'!$C:$C,10)) -> 0 | CW20: =IF($A20="","",CT20+(CV20-SUMIFS('Nursing Charges'!$J:$J,'Nursing Charges'!$A:$A,$A20,'Nursing Charges'!$C:$C,10))+(CU20-SUMIFS('Consumable Usage'!$F:$F,'Consumable Usage'!$A:$A,$A20,'Consumable Usage'!$D:$D,10))) -> 0 | CX20: =IF($A20="","",CT20+CV20+CU20) -> 0 | CZ20: =IF(CX20="","",CX20-CY20) -> 0 | DA20: =IF(OR($A20="",CR20=""),"",IF(CX20=0,"No Charges",IF(CZ20<=0,"Paid",IF(CY20>0,"Partial","Pending")))) | DE20: =IF($A20="","",SUMIFS('Consumable Usage'!$E:$E,'Consumable Usage'!$A:$A,$A20,'Consumable Usage'!$D:$D,11)) -> 0 | DF20: =IF($A20="","",SUMIFS('Nursing Charges'!$I:$I,'Nursing Charges'!$A:$A,$A20,'Nursing Charges'!$C:$C,11)) -> 0 | DG20: =IF($A20="","",DD20+(DF20-SUMIFS('Nursing Charges'!$J:$J,'Nursing Charges'!$A:$A,$A20,'Nursing Charges'!$C:$C,11))+(DE20-SUMIFS('Consumable Usage'!$F:$F,'Consumable Usage'!$A:$A,$A20,'Consumable Usage'!$D:$D,11))) -> 0 | DH20: =IF($A20="","",DD20+DF20+DE20) -> 0 | DJ20: =IF(DH20="","",DH20-DI20) -> 0 | DK20: =IF(OR($A20="",DB20=""),"",IF(DH20=0,"No Charges",IF(DJ20<=0,"Paid",IF(DI20>0,"Partial","Pending")))) | DO20: =IF($A20="","",SUMIFS('Consumable Usage'!$E:$E,'Consumable Usage'!$A:$A,$A20,'Consumable Usage'!$D:$D,12)) -> 0 | DP20: =IF($A20="","",SUMIFS('Nursing Charges'!$I:$I,'Nursing Charges'!$A:$A,$A20,'Nursing Charges'!$C:$C,12)) -> 0 | DQ20: =IF($A20="","",DN20+(DP20-SUMIFS('Nursing Charges'!$J:$J,'Nursing Charges'!$A:$A,$A20,'Nursing Charges'!$C:$C,12))+(DO20-SUMIFS('Consumable Usage'!$F:$F,'Consumable Usage'!$A:$A,$A20,'Consumable Usage'!$D:$D,12))) -> 0 | DR20: =IF($A20="","",DN20+DP20+DO20) -> 0 | DT20: =IF(DR20="","",DR20-DS20) -> 0 | DU20: =IF(OR($A20="",DL20=""),"",IF(DR20=0,"No Charges",IF(DT20<=0,"Paid",IF(DS20>0,"Partial","Pending")))) | DY20: =IF($A20="","",SUMIFS('Consumable Usage'!$E:$E,'Consumable Usage'!$A:$A,$A20,'Consumable Usage'!$D:$D,13)) -> 0 | DZ20: =IF($A20="","",SUMIFS('Nursing Charges'!$I:$I,'Nursing Charges'!$A:$A,$A20,'Nursing Charges'!$C:$C,13)) -> 0 | EA20: =IF($A20="","",DX20+(DZ20-SUMIFS('Nursing Charges'!$J:$J,'Nursing Charges'!$A:$A,$A20,'Nursing Charges'!$C:$C,13))+(DY20-SUMIFS('Consumable Usage'!$F:$F,'Consumable Usage'!$A:$A,$A20,'Consumable Usage'!$D:$D,13))) -> 0 | EB20: =IF($A20="","",DX20+DZ20+DY20) -> 0 | ED20: =IF(EB20="","",EB20-EC20) -> 0 | EE20: =IF(OR($A20="",DV20=""),"",IF(EB20=0,"No Charges",IF(ED20<=0,"Paid",IF(EC20>0,"Partial","Pending")))) | EI20: =IF($A20="","",SUMIFS('Consumable Usage'!$E:$E,'Consumable Usage'!$A:$A,$A20,'Consumable Usage'!$D:$D,14)) -> 0 | EJ20: =IF($A20="","",SUMIFS('Nursing Charges'!$I:$I,'Nursing Charges'!$A:$A,$A20,'Nursing Charges'!$C:$C,14)) -> 0 | EK20: =IF($A20="","",EH20+(EJ20-SUMIFS('Nursing Charges'!$J:$J,'Nursing Charges'!$A:$A,$A20,'Nursing Charges'!$C:$C,14))+(EI20-SUMIFS('Consumable Usage'!$F:$F,'Consumable Usage'!$A:$A,$A20,'Consumable Usage'!$D:$D,14))) -> 0 | EL20: =IF($A20="","",EH20+EJ20+EI20) -> 0 | EN20: =IF(EL20="","",EL20-EM20) -> 0 | EO20: =IF(OR($A20="",EF20=""),"",IF(EL20=0,"No Charges",IF(EN20<=0,"Paid",IF(EM20>0,"Partial","Pending")))) | ES20: =IF($A20="","",SUMIFS('Consumable Usage'!$E:$E,'Consumable Usage'!$A:$A,$A20,'Consumable Usage'!$D:$D,15)) -> 0 | ET20: =IF($A20="","",SUMIFS('Nursing Charges'!$I:$I,'Nursing Charges'!$A:$A,$A20,'Nursing Charges'!$C:$C,15)) -> 0 | EU20: =IF($A20="","",ER20+(ET20-SUMIFS('Nursing Charges'!$J:$J,'Nursing Charges'!$A:$A,$A20,'Nursing Charges'!$C:$C,15))+(ES20-SUMIFS('Consumable Usage'!$F:$F,'Consumable Usage'!$A:$A,$A20,'Consumable Usage'!$D:$D,15))) -> 0 | EV20: =IF($A20="","",ER20+ET20+ES20) -> 0 | EX20: =IF(EV20="","",EV20-EW20) -> 0 | EY20: =IF(OR($A20="",EP20=""),"",IF(EV20=0,"No Charges",IF(EX20<=0,"Paid",IF(EW20>0,"Partial","Pending")))) | FC20: =IF($A20="","",SUMIFS('Consumable Usage'!$E:$E,'Consumable Usage'!$A:$A,$A20,'Consumable Usage'!$D:$D,16)) -> 0 | FD20: =IF($A20="","",SUMIFS('Nursing Charges'!$I:$I,'Nursing Charges'!$A:$A,$A20,'Nursing Charges'!$C:$C,16)) -> 0 | FE20: =IF($A20="","",FB20+(FD20-SUMIFS('Nursing Charges'!$J:$J,'Nursing Charges'!$A:$A,$A20,'Nursing Charges'!$C:$C,16))+(FC20-SUMIFS('Consumable Usage'!$F:$F,'Consumable Usage'!$A:$A,$A20,'Consumable Usage'!$D:$D,16))) -> 0 | FF20: =IF($A20="","",FB20+FD20+FC20) -> 0 | FH20: =IF(FF20="","",FF20-FG20) -> 0 | FI20: =IF(OR($A20="",EZ20=""),"",IF(FF20=0,"No Charges",IF(FH20<=0,"Paid",IF(FG20>0,"Partial","Pending")))) | FM20: =IF($A20="","",SUMIFS('Consumable Usage'!$E:$E,'Consumable Usage'!$A:$A,$A20,'Consumable Usage'!$D:$D,16)) -> 0 | FN20: =IF($A20="","",SUMIFS('Nursing Charges'!$I:$I,'Nursing Charges'!$A:$A,$A20,'Nursing Charges'!$C:$C,16)) -> 0 | FO20: =IF($A20="","",FL20+(FN20-SUMIFS('Nursing Charges'!$J:$J,'Nursing Charges'!$A:$A,$A20,'Nursing Charges'!$C:$C,16))+(FM20-SUMIFS('Consumable Usage'!$F:$F,'Consumable Usage'!$A:$A,$A20,'Consumable Usage'!$D:$D,16))) -> 0 | FP20: =IF($A20="","",FL20+FN20+FM20) -> 0 | FR20: =IF(FP20="","",FP20-FQ20) -> 0 | FS20: =IF(OR($A20="",FJ20=""),"",IF(FP20=0,"No Charges",IF(FR20<=0,"Paid",IF(FQ20>0,"Partial","Pending"))))
A21: CC202616 | B21: hemalini | E21: nurse needs to be assigned | I21: =IF($A21="","",SUMIFS('Consumable Usage'!$E:$E,'Consumable Usage'!$A:$A,$A21,'Consumable Usage'!$D:$D,1)) -> 0 | J21: =IF($A21="","",SUMIFS('Nursing Charges'!$I:$I,'Nursing Charges'!$A:$A,$A21,'Nursing Charges'!$C:$C,1)) -> 0 | K21: =IF($A21="","",H21+(J21-SUMIFS('Nursing Charges'!$J:$J,'Nursing Charges'!$A:$A,$A21,'Nursing Charges'!$C:$C,1))+(I21-SUMIFS('Consumable Usage'!$F:$F,'Consumable Usage'!$A:$A,$A21,'Consumable Usage'!$D:$D,1))) -> 0 | L21: =IF($A21="","",H21+J21+I21) -> 0 | N21: =IF(L21="","",L21-M21) -> 0 | O21: =IF(OR($A21="",F21=""),"",IF(L21=0,"No Charges",IF(N21<=0,"Paid",IF(M21>0,"Partial","Pending")))) | S21: =IF($A21="","",SUMIFS('Consumable Usage'!$E:$E,'Consumable Usage'!$A:$A,$A21,'Consumable Usage'!$D:$D,2)) -> 0 | T21: =IF($A21="","",SUMIFS('Nursing Charges'!$I:$I,'Nursing Charges'!$A:$A,$A21,'Nursing Charges'!$C:$C,2)) -> 0 | U21: =IF($A21="","",R21+(T21-SUMIFS('Nursing Charges'!$J:$J,'Nursing Charges'!$A:$A,$A21,'Nursing Charges'!$C:$C,2))+(S21-SUMIFS('Consumable Usage'!$F:$F,'Consumable Usage'!$A:$A,$A21,'Consumable Usage'!$D:$D,2))) -> 0 | V21: =IF($A21="","",R21+T21+S21) -> 0 | X21: =IF(V21="","",V21-W21) -> 0 | Y21: =IF(OR($A21="",P21=""),"",IF(V21=0,"No Charges",IF(X21<=0,"Paid",IF(W21>0,"Partial","Pending")))) | AC21: =IF($A21="","",SUMIFS('Consumable Usage'!$E:$E,'Consumable Usage'!$A:$A,$A21,'Consumable Usage'!$D:$D,3)) -> 0 | AD21: =IF($A21="","",SUMIFS('Nursing Charges'!$I:$I,'Nursing Charges'!$A:$A,$A21,'Nursing Charges'!$C:$C,3)) -> 0 | AE21: =IF($A21="","",AB21+(AD21-SUMIFS('Nursing Charges'!$J:$J,'Nursing Charges'!$A:$A,$A21,'Nursing Charges'!$C:$C,3))+(AC21-SUMIFS('Consumable Usage'!$F:$F,'Consumable Usage'!$A:$A,$A21,'Consumable Usage'!$D:$D,3))) -> 0 | AF21: =IF($A21="","",AB21+AD21+AC21) -> 0 | AH21: =IF(AF21="","",AF21-AG21) -> 0 | AI21: =IF(OR($A21="",Z21=""),"",IF(AF21=0,"No Charges",IF(AH21<=0,"Paid",IF(AG21>0,"Partial","Pending")))) | AM21: =IF($A21="","",SUMIFS('Consumable Usage'!$E:$E,'Consumable Usage'!$A:$A,$A21,'Consumable Usage'!$D:$D,4)) -> 0 | AN21: =IF($A21="","",SUMIFS('Nursing Charges'!$I:$I,'Nursing Charges'!$A:$A,$A21,'Nursing Charges'!$C:$C,4)) -> 0 | AO21: =IF($A21="","",AL21+(AN21-SUMIFS('Nursing Charges'!$J:$J,'Nursing Charges'!$A:$A,$A21,'Nursing Charges'!$C:$C,4))+(AM21-SUMIFS('Consumable Usage'!$F:$F,'Consumable Usage'!$A:$A,$A21,'Consumable Usage'!$D:$D,4))) -> 0 | AP21: =IF($A21="","",AL21+AN21+AM21) -> 0 | AR21: =IF(AP21="","",AP21-AQ21) -> 0 | AS21: =IF(OR($A21="",AJ21=""),"",IF(AP21=0,"No Charges",IF(AR21<=0,"Paid",IF(AQ21>0,"Partial","Pending")))) | AW21: =IF($A21="","",SUMIFS('Consumable Usage'!$E:$E,'Consumable Usage'!$A:$A,$A21,'Consumable Usage'!$D:$D,5)) -> 0 | AX21: =IF($A21="","",SUMIFS('Nursing Charges'!$I:$I,'Nursing Charges'!$A:$A,$A21,'Nursing Charges'!$C:$C,5)) -> 0 | AY21: =IF($A21="","",AV21+(AX21-SUMIFS('Nursing Charges'!$J:$J,'Nursing Charges'!$A:$A,$A21,'Nursing Charges'!$C:$C,5))+(AW21-SUMIFS('Consumable Usage'!$F:$F,'Consumable Usage'!$A:$A,$A21,'Consumable Usage'!$D:$D,5))) -> 0 | AZ21: =IF($A21="","",AV21+AX21+AW21) -> 0 | BB21: =IF(AZ21="","",AZ21-BA21) -> 0 | BC21: =IF(OR($A21="",AT21=""),"",IF(AZ21=0,"No Charges",IF(BB21<=0,"Paid",IF(BA21>0,"Partial","Pending")))) | BG21: =IF($A21="","",SUMIFS('Consumable Usage'!$E:$E,'Consumable Usage'!$A:$A,$A21,'Consumable Usage'!$D:$D,6)) -> 0 | BH21: =IF($A21="","",SUMIFS('Nursing Charges'!$I:$I,'Nursing Charges'!$A:$A,$A21,'Nursing Charges'!$C:$C,6)) -> 0 | BI21: =IF($A21="","",BF21+(BH21-SUMIFS('Nursing Charges'!$J:$J,'Nursing Charges'!$A:$A,$A21,'Nursing Charges'!$C:$C,6))+(BG21-SUMIFS('Consumable Usage'!$F:$F,'Consumable Usage'!$A:$A,$A21,'Consumable Usage'!$D:$D,6))) -> 0 | BJ21: =IF($A21="","",BF21+BH21+BG21) -> 0 | BL21: =IF(BJ21="","",BJ21-BK21) -> 0 | BM21: =IF(OR($A21="",BD21=""),"",IF(BJ21=0,"No Charges",IF(BL21<=0,"Paid",IF(BK21>0,"Partial","Pending")))) | BQ21: =IF($A21="","",SUMIFS('Consumable Usage'!$E:$E,'Consumable Usage'!$A:$A,$A21,'Consumable Usage'!$D:$D,7)) -> 0 | BR21: =IF($A21="","",SUMIFS('Nursing Charges'!$I:$I,'Nursing Charges'!$A:$A,$A21,'Nursing Charges'!$C:$C,7)) -> 0 | BS21: =IF($A21="","",BP21+(BR21-SUMIFS('Nursing Charges'!$J:$J,'Nursing Charges'!$A:$A,$A21,'Nursing Charges'!$C:$C,7))+(BQ21-SUMIFS('Consumable Usage'!$F:$F,'Consumable Usage'!$A:$A,$A21,'Consumable Usage'!$D:$D,7))) -> 0 | BT21: =IF($A21="","",BP21+BR21+BQ21) -> 0 | BV21: =IF(BT21="","",BT21-BU21) -> 0 | BW21: =IF(OR($A21="",BN21=""),"",IF(BT21=0,"No Charges",IF(BV21<=0,"Paid",IF(BU21>0,"Partial","Pending")))) | CA21: =IF($A21="","",SUMIFS('Consumable Usage'!$E:$E,'Consumable Usage'!$A:$A,$A21,'Consumable Usage'!$D:$D,8)) -> 0 | CB21: =IF($A21="","",SUMIFS('Nursing Charges'!$I:$I,'Nursing Charges'!$A:$A,$A21,'Nursing Charges'!$C:$C,8)) -> 0 | CC21: =IF($A21="","",BZ21+(CB21-SUMIFS('Nursing Charges'!$J:$J,'Nursing Charges'!$A:$A,$A21,'Nursing Charges'!$C:$C,8))+(CA21-SUMIFS('Consumable Usage'!$F:$F,'Consumable Usage'!$A:$A,$A21,'Consumable Usage'!$D:$D,8))) -> 0 | CD21: =IF($A21="","",BZ21+CB21+CA21) -> 0 | CF21: =IF(CD21="","",CD21-CE21) -> 0 | CG21: =IF(OR($A21="",BX21=""),"",IF(CD21=0,"No Charges",IF(CF21<=0,"Paid",IF(CE21>0,"Partial","Pending")))) | CK21: =IF($A21="","",SUMIFS('Consumable Usage'!$E:$E,'Consumable Usage'!$A:$A,$A21,'Consumable Usage'!$D:$D,9)) -> 0 | CL21: =IF($A21="","",SUMIFS('Nursing Charges'!$I:$I,'Nursing Charges'!$A:$A,$A21,'Nursing Charges'!$C:$C,9)) -> 0 | CM21: =IF($A21="","",CJ21+(CL21-SUMIFS('Nursing Charges'!$J:$J,'Nursing Charges'!$A:$A,$A21,'Nursing Charges'!$C:$C,9))+(CK21-SUMIFS('Consumable Usage'!$F:$F,'Consumable Usage'!$A:$A,$A21,'Consumable Usage'!$D:$D,9))) -> 0 | CN21: =IF($A21="","",CJ21+CL21+CK21) -> 0 | CP21: =IF(CN21="","",CN21-CO21) -> 0 | CQ21: =IF(OR($A21="",CH21=""),"",IF(CN21=0,"No Charges",IF(CP21<=0,"Paid",IF(CO21>0,"Partial","Pending")))) | CU21: =IF($A21="","",SUMIFS('Consumable Usage'!$E:$E,'Consumable Usage'!$A:$A,$A21,'Consumable Usage'!$D:$D,10)) -> 0 | CV21: =IF($A21="","",SUMIFS('Nursing Charges'!$I:$I,'Nursing Charges'!$A:$A,$A21,'Nursing Charges'!$C:$C,10)) -> 0 | CW21: =IF($A21="","",CT21+(CV21-SUMIFS('Nursing Charges'!$J:$J,'Nursing Charges'!$A:$A,$A21,'Nursing Charges'!$C:$C,10))+(CU21-SUMIFS('Consumable Usage'!$F:$F,'Consumable Usage'!$A:$A,$A21,'Consumable Usage'!$D:$D,10))) -> 0 | CX21: =IF($A21="","",CT21+CV21+CU21) -> 0 | CZ21: =IF(CX21="","",CX21-CY21) -> 0 | DA21: =IF(OR($A21="",CR21=""),"",IF(CX21=0,"No Charges",IF(CZ21<=0,"Paid",IF(CY21>0,"Partial","Pending")))) | DE21: =IF($A21="","",SUMIFS('Consumable Usage'!$E:$E,'Consumable Usage'!$A:$A,$A21,'Consumable Usage'!$D:$D,11)) -> 0 | DF21: =IF($A21="","",SUMIFS('Nursing Charges'!$I:$I,'Nursing Charges'!$A:$A,$A21,'Nursing Charges'!$C:$C,11)) -> 0 | DG21: =IF($A21="","",DD21+(DF21-SUMIFS('Nursing Charges'!$J:$J,'Nursing Charges'!$A:$A,$A21,'Nursing Charges'!$C:$C,11))+(DE21-SUMIFS('Consumable Usage'!$F:$F,'Consumable Usage'!$A:$A,$A21,'Consumable Usage'!$D:$D,11))) -> 0 | DH21: =IF($A21="","",DD21+DF21+DE21) -> 0 | DJ21: =IF(DH21="","",DH21-DI21) -> 0 | DK21: =IF(OR($A21="",DB21=""),"",IF(DH21=0,"No Charges",IF(DJ21<=0,"Paid",IF(DI21>0,"Partial","Pending")))) | DO21: =IF($A21="","",SUMIFS('Consumable Usage'!$E:$E,'Consumable Usage'!$A:$A,$A21,'Consumable Usage'!$D:$D,12)) -> 0 | DP21: =IF($A21="","",SUMIFS('Nursing Charges'!$I:$I,'Nursing Charges'!$A:$A,$A21,'Nursing Charges'!$C:$C,12)) -> 0 | DQ21: =IF($A21="","",DN21+(DP21-SUMIFS('Nursing Charges'!$J:$J,'Nursing Charges'!$A:$A,$A21,'Nursing Charges'!$C:$C,12))+(DO21-SUMIFS('Consumable Usage'!$F:$F,'Consumable Usage'!$A:$A,$A21,'Consumable Usage'!$D:$D,12))) -> 0 | DR21: =IF($A21="","",DN21+DP21+DO21) -> 0 | DT21: =IF(DR21="","",DR21-DS21) -> 0 | DU21: =IF(OR($A21="",DL21=""),"",IF(DR21=0,"No Charges",IF(DT21<=0,"Paid",IF(DS21>0,"Partial","Pending")))) | DY21: =IF($A21="","",SUMIFS('Consumable Usage'!$E:$E,'Consumable Usage'!$A:$A,$A21,'Consumable Usage'!$D:$D,13)) -> 0 | DZ21: =IF($A21="","",SUMIFS('Nursing Charges'!$I:$I,'Nursing Charges'!$A:$A,$A21,'Nursing Charges'!$C:$C,13)) -> 0 | EA21: =IF($A21="","",DX21+(DZ21-SUMIFS('Nursing Charges'!$J:$J,'Nursing Charges'!$A:$A,$A21,'Nursing Charges'!$C:$C,13))+(DY21-SUMIFS('Consumable Usage'!$F:$F,'Consumable Usage'!$A:$A,$A21,'Consumable Usage'!$D:$D,13))) -> 0 | EB21: =IF($A21="","",DX21+DZ21+DY21) -> 0 | ED21: =IF(EB21="","",EB21-EC21) -> 0 | EE21: =IF(OR($A21="",DV21=""),"",IF(EB21=0,"No Charges",IF(ED21<=0,"Paid",IF(EC21>0,"Partial","Pending")))) | EI21: =IF($A21="","",SUMIFS('Consumable Usage'!$E:$E,'Consumable Usage'!$A:$A,$A21,'Consumable Usage'!$D:$D,14)) -> 0 | EJ21: =IF($A21="","",SUMIFS('Nursing Charges'!$I:$I,'Nursing Charges'!$A:$A,$A21,'Nursing Charges'!$C:$C,14)) -> 0 | EK21: =IF($A21="","",EH21+(EJ21-SUMIFS('Nursing Charges'!$J:$J,'Nursing Charges'!$A:$A,$A21,'Nursing Charges'!$C:$C,14))+(EI21-SUMIFS('Consumable Usage'!$F:$F,'Consumable Usage'!$A:$A,$A21,'Consumable Usage'!$D:$D,14))) -> 0 | EL21: =IF($A21="","",EH21+EJ21+EI21) -> 0 | EN21: =IF(EL21="","",EL21-EM21) -> 0 | EO21: =IF(OR($A21="",EF21=""),"",IF(EL21=0,"No Charges",IF(EN21<=0,"Paid",IF(EM21>0,"Partial","Pending")))) | ES21: =IF($A21="","",SUMIFS('Consumable Usage'!$E:$E,'Consumable Usage'!$A:$A,$A21,'Consumable Usage'!$D:$D,15)) -> 0 | ET21: =IF($A21="","",SUMIFS('Nursing Charges'!$I:$I,'Nursing Charges'!$A:$A,$A21,'Nursing Charges'!$C:$C,15)) -> 0 | EU21: =IF($A21="","",ER21+(ET21-SUMIFS('Nursing Charges'!$J:$J,'Nursing Charges'!$A:$A,$A21,'Nursing Charges'!$C:$C,15))+(ES21-SUMIFS('Consumable Usage'!$F:$F,'Consumable Usage'!$A:$A,$A21,'Consumable Usage'!$D:$D,15))) -> 0 | EV21: =IF($A21="","",ER21+ET21+ES21) -> 0 | EX21: =IF(EV21="","",EV21-EW21) -> 0 | EY21: =IF(OR($A21="",EP21=""),"",IF(EV21=0,"No Charges",IF(EX21<=0,"Paid",IF(EW21>0,"Partial","Pending")))) | FC21: =IF($A21="","",SUMIFS('Consumable Usage'!$E:$E,'Consumable Usage'!$A:$A,$A21,'Consumable Usage'!$D:$D,16)) -> 0 | FD21: =IF($A21="","",SUMIFS('Nursing Charges'!$I:$I,'Nursing Charges'!$A:$A,$A21,'Nursing Charges'!$C:$C,16)) -> 0 | FE21: =IF($A21="","",FB21+(FD21-SUMIFS('Nursing Charges'!$J:$J,'Nursing Charges'!$A:$A,$A21,'Nursing Charges'!$C:$C,16))+(FC21-SUMIFS('Consumable Usage'!$F:$F,'Consumable Usage'!$A:$A,$A21,'Consumable Usage'!$D:$D,16))) -> 0 | FF21: =IF($A21="","",FB21+FD21+FC21) -> 0 | FH21: =IF(FF21="","",FF21-FG21) -> 0 | FI21: =IF(OR($A21="",EZ21=""),"",IF(FF21=0,"No Charges",IF(FH21<=0,"Paid",IF(FG21>0,"Partial","Pending")))) | FM21: =IF($A21="","",SUMIFS('Consumable Usage'!$E:$E,'Consumable Usage'!$A:$A,$A21,'Consumable Usage'!$D:$D,16)) -> 0 | FN21: =IF($A21="","",SUMIFS('Nursing Charges'!$I:$I,'Nursing Charges'!$A:$A,$A21,'Nursing Charges'!$C:$C,16)) -> 0 | FO21: =IF($A21="","",FL21+(FN21-SUMIFS('Nursing Charges'!$J:$J,'Nursing Charges'!$A:$A,$A21,'Nursing Charges'!$C:$C,16))+(FM21-SUMIFS('Consumable Usage'!$F:$F,'Consumable Usage'!$A:$A,$A21,'Consumable Usage'!$D:$D,16))) -> 0 | FP21: =IF($A21="","",FL21+FN21+FM21) -> 0 | FR21: =IF(FP21="","",FP21-FQ21) -> 0 | FS21: =IF(OR($A21="",FJ21=""),"",IF(FP21=0,"No Charges",IF(FR21<=0,"Paid",IF(FQ21>0,"Partial","Pending"))))
I22: =IF($A22="","",SUMIFS('Consumable Usage'!$E:$E,'Consumable Usage'!$A:$A,$A22,'Consumable Usage'!$D:$D,1)) | J22: =IF($A22="","",SUMIFS('Nursing Charges'!$I:$I,'Nursing Charges'!$A:$A,$A22,'Nursing Charges'!$C:$C,1)) | K22: =IF($A22="","",H22+(J22-SUMIFS('Nursing Charges'!$J:$J,'Nursing Charges'!$A:$A,$A22,'Nursing Charges'!$C:$C,1))+(I22-SUMIFS('Consumable Usage'!$F:$F,'Consumable Usage'!$A:$A,$A22,'Consumable Usage'!$D:$D,1))) | L22: =IF($A22="","",H22+J22+I22) | N22: =IF(L22="","",L22-M22) | O22: =IF(OR($A22="",F22=""),"",IF(L22=0,"No Charges",IF(N22<=0,"Paid",IF(M22>0,"Partial","Pending")))) | S22: =IF($A22="","",SUMIFS('Consumable Usage'!$E:$E,'Consumable Usage'!$A:$A,$A22,'Consumable Usage'!$D:$D,2)) | T22: =IF($A22="","",SUMIFS('Nursing Charges'!$I:$I,'Nursing Charges'!$A:$A,$A22,'Nursing Charges'!$C:$C,2)) | U22: =IF($A22="","",R22+(T22-SUMIFS('Nursing Charges'!$J:$J,'Nursing Charges'!$A:$A,$A22,'Nursing Charges'!$C:$C,2))+(S22-SUMIFS('Consumable Usage'!$F:$F,'Consumable Usage'!$A:$A,$A22,'Consumable Usage'!$D:$D,2))) | V22: =IF($A22="","",R22+T22+S22) | X22: =IF(V22="","",V22-W22) | Y22: =IF(OR($A22="",P22=""),"",IF(V22=0,"No Charges",IF(X22<=0,"Paid",IF(W22>0,"Partial","Pending")))) | AC22: =IF($A22="","",SUMIFS('Consumable Usage'!$E:$E,'Consumable Usage'!$A:$A,$A22,'Consumable Usage'!$D:$D,3)) | AD22: =IF($A22="","",SUMIFS('Nursing Charges'!$I:$I,'Nursing Charges'!$A:$A,$A22,'Nursing Charges'!$C:$C,3)) | AE22: =IF($A22="","",AB22+(AD22-SUMIFS('Nursing Charges'!$J:$J,'Nursing Charges'!$A:$A,$A22,'Nursing Charges'!$C:$C,3))+(AC22-SUMIFS('Consumable Usage'!$F:$F,'Consumable Usage'!$A:$A,$A22,'Consumable Usage'!$D:$D,3))) | AF22: =IF($A22="","",AB22+AD22+AC22) | AH22: =IF(AF22="","",AF22-AG22) | AI22: =IF(OR($A22="",Z22=""),"",IF(AF22=0,"No Charges",IF(AH22<=0,"Paid",IF(AG22>0,"Partial","Pending")))) | AM22: =IF($A22="","",SUMIFS('Consumable Usage'!$E:$E,'Consumable Usage'!$A:$A,$A22,'Consumable Usage'!$D:$D,4)) | AN22: =IF($A22="","",SUMIFS('Nursing Charges'!$I:$I,'Nursing Charges'!$A:$A,$A22,'Nursing Charges'!$C:$C,4)) | AO22: =IF($A22="","",AL22+(AN22-SUMIFS('Nursing Charges'!$J:$J,'Nursing Charges'!$A:$A,$A22,'Nursing Charges'!$C:$C,4))+(AM22-SUMIFS('Consumable Usage'!$F:$F,'Consumable Usage'!$A:$A,$A22,'Consumable Usage'!$D:$D,4))) | AP22: =IF($A22="","",AL22+AN22+AM22) | AR22: =IF(AP22="","",AP22-AQ22) | AS22: =IF(OR($A22="",AJ22=""),"",IF(AP22=0,"No Charges",IF(AR22<=0,"Paid",IF(AQ22>0,"Partial","Pending")))) | AW22: =IF($A22="","",SUMIFS('Consumable Usage'!$E:$E,'Consumable Usage'!$A:$A,$A22,'Consumable Usage'!$D:$D,5)) | AX22: =IF($A22="","",SUMIFS('Nursing Charges'!$I:$I,'Nursing Charges'!$A:$A,$A22,'Nursing Charges'!$C:$C,5)) | AY22: =IF($A22="","",AV22+(AX22-SUMIFS('Nursing Charges'!$J:$J,'Nursing Charges'!$A:$A,$A22,'Nursing Charges'!$C:$C,5))+(AW22-SUMIFS('Consumable Usage'!$F:$F,'Consumable Usage'!$A:$A,$A22,'Consumable Usage'!$D:$D,5))) | AZ22: =IF($A22="","",AV22+AX22+AW22) | BB22: =IF(AZ22="","",AZ22-BA22) | BC22: =IF(OR($A22="",AT22=""),"",IF(AZ22=0,"No Charges",IF(BB22<=0,"Paid",IF(BA22>0,"Partial","Pending")))) | BG22: =IF($A22="","",SUMIFS('Consumable Usage'!$E:$E,'Consumable Usage'!$A:$A,$A22,'Consumable Usage'!$D:$D,6)) | BH22: =IF($A22="","",SUMIFS('Nursing Charges'!$I:$I,'Nursing Charges'!$A:$A,$A22,'Nursing Charges'!$C:$C,6)) | BI22: =IF($A22="","",BF22+(BH22-SUMIFS('Nursing Charges'!$J:$J,'Nursing Charges'!$A:$A,$A22,'Nursing Charges'!$C:$C,6))+(BG22-SUMIFS('Consumable Usage'!$F:$F,'Consumable Usage'!$A:$A,$A22,'Consumable Usage'!$D:$D,6))) | BJ22: =IF($A22="","",BF22+BH22+BG22) | BL22: =IF(BJ22="","",BJ22-BK22) | BM22: =IF(OR($A22="",BD22=""),"",IF(BJ22=0,"No Charges",IF(BL22<=0,"Paid",IF(BK22>0,"Partial","Pending")))) | BQ22: =IF($A22="","",SUMIFS('Consumable Usage'!$E:$E,'Consumable Usage'!$A:$A,$A22,'Consumable Usage'!$D:$D,7)) | BR22: =IF($A22="","",SUMIFS('Nursing Charges'!$I:$I,'Nursing Charges'!$A:$A,$A22,'Nursing Charges'!$C:$C,7)) | BS22: =IF($A22="","",BP22+(BR22-SUMIFS('Nursing Charges'!$J:$J,'Nursing Charges'!$A:$A,$A22,'Nursing Charges'!$C:$C,7))+(BQ22-SUMIFS('Consumable Usage'!$F:$F,'Consumable Usage'!$A:$A,$A22,'Consumable Usage'!$D:$D,7))) | BT22: =IF($A22="","",BP22+BR22+BQ22) | BV22: =IF(BT22="","",BT22-BU22) | BW22: =IF(OR($A22="",BN22=""),"",IF(BT22=0,"No Charges",IF(BV22<=0,"Paid",IF(BU22>0,"Partial","Pending")))) | CA22: =IF($A22="","",SUMIFS('Consumable Usage'!$E:$E,'Consumable Usage'!$A:$A,$A22,'Consumable Usage'!$D:$D,8)) | CB22: =IF($A22="","",SUMIFS('Nursing Charges'!$I:$I,'Nursing Charges'!$A:$A,$A22,'Nursing Charges'!$C:$C,8)) | CC22: =IF($A22="","",BZ22+(CB22-SUMIFS('Nursing Charges'!$J:$J,'Nursing Charges'!$A:$A,$A22,'Nursing Charges'!$C:$C,8))+(CA22-SUMIFS('Consumable Usage'!$F:$F,'Consumable Usage'!$A:$A,$A22,'Consumable Usage'!$D:$D,8))) | CD22: =IF($A22="","",BZ22+CB22+CA22) | CF22: =IF(CD22="","",CD22-CE22) | CG22: =IF(OR($A22="",BX22=""),"",IF(CD22=0,"No Charges",IF(CF22<=0,"Paid",IF(CE22>0,"Partial","Pending")))) | CK22: =IF($A22="","",SUMIFS('Consumable Usage'!$E:$E,'Consumable Usage'!$A:$A,$A22,'Consumable Usage'!$D:$D,9)) | CL22: =IF($A22="","",SUMIFS('Nursing Charges'!$I:$I,'Nursing Charges'!$A:$A,$A22,'Nursing Charges'!$C:$C,9)) | CM22: =IF($A22="","",CJ22+(CL22-SUMIFS('Nursing Charges'!$J:$J,'Nursing Charges'!$A:$A,$A22,'Nursing Charges'!$C:$C,9))+(CK22-SUMIFS('Consumable Usage'!$F:$F,'Consumable Usage'!$A:$A,$A22,'Consumable Usage'!$D:$D,9))) | CN22: =IF($A22="","",CJ22+CL22+CK22) | CP22: =IF(CN22="","",CN22-CO22) | CQ22: =IF(OR($A22="",CH22=""),"",IF(CN22=0,"No Charges",IF(CP22<=0,"Paid",IF(CO22>0,"Partial","Pending")))) | CU22: =IF($A22="","",SUMIFS('Consumable Usage'!$E:$E,'Consumable Usage'!$A:$A,$A22,'Consumable Usage'!$D:$D,10)) | CV22: =IF($A22="","",SUMIFS('Nursing Charges'!$I:$I,'Nursing Charges'!$A:$A,$A22,'Nursing Charges'!$C:$C,10)) | CW22: =IF($A22="","",CT22+(CV22-SUMIFS('Nursing Charges'!$J:$J,'Nursing Charges'!$A:$A,$A22,'Nursing Charges'!$C:$C,10))+(CU22-SUMIFS('Consumable Usage'!$F:$F,'Consumable Usage'!$A:$A,$A22,'Consumable Usage'!$D:$D,10))) | CX22: =IF($A22="","",CT22+CV22+CU22) | CZ22: =IF(CX22="","",CX22-CY22) | DA22: =IF(OR($A22="",CR22=""),"",IF(CX22=0,"No Charges",IF(CZ22<=0,"Paid",IF(CY22>0,"Partial","Pending")))) | DE22: =IF($A22="","",SUMIFS('Consumable Usage'!$E:$E,'Consumable Usage'!$A:$A,$A22,'Consumable Usage'!$D:$D,11)) | DF22: =IF($A22="","",SUMIFS('Nursing Charges'!$I:$I,'Nursing Charges'!$A:$A,$A22,'Nursing Charges'!$C:$C,11)) | DG22: =IF($A22="","",DD22+(DF22-SUMIFS('Nursing Charges'!$J:$J,'Nursing Charges'!$A:$A,$A22,'Nursing Charges'!$C:$C,11))+(DE22-SUMIFS('Consumable Usage'!$F:$F,'Consumable Usage'!$A:$A,$A22,'Consumable Usage'!$D:$D,11))) | DH22: =IF($A22="","",DD22+DF22+DE22) | DJ22: =IF(DH22="","",DH22-DI22) | DK22: =IF(OR($A22="",DB22=""),"",IF(DH22=0,"No Charges",IF(DJ22<=0,"Paid",IF(DI22>0,"Partial","Pending")))) | DO22: =IF($A22="","",SUMIFS('Consumable Usage'!$E:$E,'Consumable Usage'!$A:$A,$A22,'Consumable Usage'!$D:$D,12)) | DP22: =IF($A22="","",SUMIFS('Nursing Charges'!$I:$I,'Nursing Charges'!$A:$A,$A22,'Nursing Charges'!$C:$C,12)) | DQ22: =IF($A22="","",DN22+(DP22-SUMIFS('Nursing Charges'!$J:$J,'Nursing Charges'!$A:$A,$A22,'Nursing Charges'!$C:$C,12))+(DO22-SUMIFS('Consumable Usage'!$F:$F,'Consumable Usage'!$A:$A,$A22,'Consumable Usage'!$D:$D,12))) | DR22: =IF($A22="","",DN22+DP22+DO22) | DT22: =IF(DR22="","",DR22-DS22) | DU22: =IF(OR($A22="",DL22=""),"",IF(DR22=0,"No Charges",IF(DT22<=0,"Paid",IF(DS22>0,"Partial","Pending")))) | DY22: =IF($A22="","",SUMIFS('Consumable Usage'!$E:$E,'Consumable Usage'!$A:$A,$A22,'Consumable Usage'!$D:$D,13)) | DZ22: =IF($A22="","",SUMIFS('Nursing Charges'!$I:$I,'Nursing Charges'!$A:$A,$A22,'Nursing Charges'!$C:$C,13)) | EA22: =IF($A22="","",DX22+(DZ22-SUMIFS('Nursing Charges'!$J:$J,'Nursing Charges'!$A:$A,$A22,'Nursing Charges'!$C:$C,13))+(DY22-SUMIFS('Consumable Usage'!$F:$F,'Consumable Usage'!$A:$A,$A22,'Consumable Usage'!$D:$D,13))) | EB22: =IF($A22="","",DX22+DZ22+DY22) | ED22: =IF(EB22="","",EB22-EC22) | EE22: =IF(OR($A22="",DV22=""),"",IF(EB22=0,"No Charges",IF(ED22<=0,"Paid",IF(EC22>0,"Partial","Pending")))) | EI22: =IF($A22="","",SUMIFS('Consumable Usage'!$E:$E,'Consumable Usage'!$A:$A,$A22,'Consumable Usage'!$D:$D,14)) | EJ22: =IF($A22="","",SUMIFS('Nursing Charges'!$I:$I,'Nursing Charges'!$A:$A,$A22,'Nursing Charges'!$C:$C,14)) | EK22: =IF($A22="","",EH22+(EJ22-SUMIFS('Nursing Charges'!$J:$J,'Nursing Charges'!$A:$A,$A22,'Nursing Charges'!$C:$C,14))+(EI22-SUMIFS('Consumable Usage'!$F:$F,'Consumable Usage'!$A:$A,$A22,'Consumable Usage'!$D:$D,14))) | EL22: =IF($A22="","",EH22+EJ22+EI22) | EN22: =IF(EL22="","",EL22-EM22) | EO22: =IF(OR($A22="",EF22=""),"",IF(EL22=0,"No Charges",IF(EN22<=0,"Paid",IF(EM22>0,"Partial","Pending")))) | ES22: =IF($A22="","",SUMIFS('Consumable Usage'!$E:$E,'Consumable Usage'!$A:$A,$A22,'Consumable Usage'!$D:$D,15)) | ET22: =IF($A22="","",SUMIFS('Nursing Charges'!$I:$I,'Nursing Charges'!$A:$A,$A22,'Nursing Charges'!$C:$C,15)) | EU22: =IF($A22="","",ER22+(ET22-SUMIFS('Nursing Charges'!$J:$J,'Nursing Charges'!$A:$A,$A22,'Nursing Charges'!$C:$C,15))+(ES22-SUMIFS('Consumable Usage'!$F:$F,'Consumable Usage'!$A:$A,$A22,'Consumable Usage'!$D:$D,15))) | EV22: =IF($A22="","",ER22+ET22+ES22) | EX22: =IF(EV22="","",EV22-EW22) | EY22: =IF(OR($A22="",EP22=""),"",IF(EV22=0,"No Charges",IF(EX22<=0,"Paid",IF(EW22>0,"Partial","Pending")))) | FC22: =IF($A22="","",SUMIFS('Consumable Usage'!$E:$E,'Consumable Usage'!$A:$A,$A22,'Consumable Usage'!$D:$D,16)) | FD22: =IF($A22="","",SUMIFS('Nursing Charges'!$I:$I,'Nursing Charges'!$A:$A,$A22,'Nursing Charges'!$C:$C,16)) | FE22: =IF($A22="","",FB22+(FD22-SUMIFS('Nursing Charges'!$J:$J,'Nursing Charges'!$A:$A,$A22,'Nursing Charges'!$C:$C,16))+(FC22-SUMIFS('Consumable Usage'!$F:$F,'Consumable Usage'!$A:$A,$A22,'Consumable Usage'!$D:$D,16))) | FF22: =IF($A22="","",FB22+FD22+FC22) | FH22: =IF(FF22="","",FF22-FG22) | FI22: =IF(OR($A22="",EZ22=""),"",IF(FF22=0,"No Charges",IF(FH22<=0,"Paid",IF(FG22>0,"Partial","Pending")))) | FM22: =IF($A22="","",SUMIFS('Consumable Usage'!$E:$E,'Consumable Usage'!$A:$A,$A22,'Consumable Usage'!$D:$D,16)) | FN22: =IF($A22="","",SUMIFS('Nursing Charges'!$I:$I,'Nursing Charges'!$A:$A,$A22,'Nursing Charges'!$C:$C,16)) | FO22: =IF($A22="","",FL22+(FN22-SUMIFS('Nursing Charges'!$J:$J,'Nursing Charges'!$A:$A,$A22,'Nursing Charges'!$C:$C,16))+(FM22-SUMIFS('Consumable Usage'!$F:$F,'Consumable Usage'!$A:$A,$A22,'Consumable Usage'!$D:$D,16))) | FP22: =IF($A22="","",FL22+FN22+FM22) | FR22: =IF(FP22="","",FP22-FQ22) | FS22: =IF(OR($A22="",FJ22=""),"",IF(FP22=0,"No Charges",IF(FR22<=0,"Paid",IF(FQ22>0,"Partial","Pending"))))
